Workbook
Name 白银支线: 管道站场阀室关系!$B$1826
Name 白银支线: #REF!
Name 宝钢支线: 管道站场阀室关系!$B$230
Name 宝钢支线: #REF!
Name 宝香西管道: 管道站场阀室关系!$B$1599
Name 宝香西管道: #REF!
Name 北海支线: 管道站场阀室关系!#REF!
Name 北海支线: #REF!
Name 北疆联络线: 管道站场阀室关系!#REF!
Name 北疆联络线: #REF!
Name 滨州支线: 管道站场阀室关系!#REF!
Name 滨州支线: #REF!
Name 采育通州东支线: 管道站场阀室关系!#REF!
Name 采育通州东支线: #REF!
Name 苍梧贺州支线: 管道站场阀室关系!$B$832
Name 苍梧贺州支线: #REF!
Name 沧淄线干线: 管道站场阀室关系!#REF!
Name 沧淄线干线: #REF!
Name 昌邑支线: 管道站场阀室关系!#REF!
Name 昌邑支线: #REF!
Name 昌邑支线: #REF!
Name 常长支线: 管道站场阀室关系!$B$213
Name 常长支线: #REF!
Name 大连支线: 管道站场阀室关系!$B$1988
Name 大连支线: #REF!
Name 大沈线干线: 管道站场阀室关系!$B$1959
Name 大沈线干线: #REF!
Name 大唐煤制气管道: 管道站场阀室关系!$B$1587
Name 大唐煤制气管道: #REF!
Name 德德支线: 管道站场阀室关系!$B$325
Name 德德支线: #REF!
Name 德武支线: 管道站场阀室关系!$B$323
Name 德武支线: #REF!
Name 定合支线: 管道站场阀室关系!$B$190
Name 定合支线: #REF!
Name 都匀支线: 管道站场阀室关系!$B$2559
Name 都匀支线: #REF!
Name 独石化支线: 管道站场阀室关系!$B$604
Name 独石化支线: #REF!
Name 防城港支线: 管道站场阀室关系!$B$2584
Name 防城港支线: #REF!
Name 抚顺支线: 管道站场阀室关系!$B$1993
Name 抚顺支线: #REF!
Name 甘南支线: 管道站场阀室关系!$B$1736
Name 甘南支线: #REF!
Name 甘南支线支线: 管道站场阀室关系!$B$1743
Name 甘南支线支线: #REF!
Name 甘西南地区供气管道: 管道站场阀室关系!$B$1731
Name 甘西南地区供气管道: #REF!
Name 港沧一线: 管道站场阀室关系!#REF!
Name 港沧一线: #REF!
Name 港沧一线: #REF!
Name 港清复线: 管道站场阀室关系!$B$1419
Name 港清复线: #REF!
Name 港清三线: 管道站场阀室关系!$B$1424
Name 港清三线: #REF!
Name 港清线: 管道站场阀室关系!$B$1409
Name 港清线: #REF!
Name 高丽营西沙屯联络线: 管道站场阀室关系!$B$1580
Name 高丽营西沙屯联络线: #REF!

Sheet 数据统计
B2: 天然气管网基本现状
B3: 管道类型 | C3: 条数 | D3: 里程，km | E3: 站场 | F3: 阀室 | G3: 压气站 | H3: 压缩机
B4: 一级管道 | C4: 55 | D4: =SUMIF(干线管道!C:C,"一级",干线管道!D:D) -> 55638.935 | E4: =SUMIF(干线管道!C:C,"一级",干线管道!F:F) -> 799 | F4: =SUMIF(干线管道!C:C,"一级",干线管道!G:G) -> 2120 | G4: =SUMIF(干线管道!C:C,"一级",干线管道!H:H) -> 110 | H4: =COUNTIFS(压缩机!B:B,"一级",压缩机!R:R,"投产") -> 408
B5: 二级管道 | C5: =COUNTIF(干线管道!C:C,"二级") -> 7 | D5: =SUMIF(干线管道!C:C,"二级",干线管道!D:D) -> 6901.3496 | E5: =SUMIF(干线管道!C:C,"二级",干线管道!F:F) -> 217 | F5: =SUMIF(干线管道!C:C,"二级",干线管道!G:G) -> 302 | G5: =SUMIF(干线管道!C:C,"二级",干线管道!H:H) -> 1 | H5: =COUNTIFS(压缩机!B:B,"二级",压缩机!R:R,"投产") -> 4
B6: 总合计 | C6: =C4+C5 -> 62 | D6: =D4+D5 -> 62540.285 | E6: =E4+E5 -> 1016 | F6: =F4+F5 -> 2422 | G6: =G4+G5 -> 111 | H6: =H4+H5 -> 412
B8: 用户与分输口 | D8: 远控
B9: 供气点 | C9: 937 | E9: 压气站 | F9: 分输站 | G9: 其他站 | H9: 代管站 | I9: RTU阀室
B10: 分输口 | C10: 1633 | D10: 已投运场站总数 | E10: =SUMIF(干线管道!$C:$C,"一级",干线管道!H:H)+SUMIF(干线管道!$C:$C,"二级",干线管道!H:H) -> 111 | F10: =SUMIF(干线管道!$C:$C,"一级",干线管道!I:I)+SUMIF(干线管道!$C:$C,"二级",干线管道!I:I) -> 657 | G10: =SUMIF(干线管道!$C:$C,"一级",干线管道!J:J)+SUMIF(干线管道!$C:$C,"二级",干线管道!J:J) -> 191 | H10: =SUMIF(干线管道!$C:$C,"一级",干线管道!K:K)+SUMIF(干线管道!$C:$C,"二级",干线管道!K:K) -> 57 | I10: =SUMIF(干线管道!$C:$C,"一级",干线管道!L:L)+SUMIF(干线管道!$C:$C,"二级",干线管道!L:L) -> 1695

Sheet 干线管道
A1: 序号 | B1: 干线管道 | C1: 调控级别 | D1: 长度 | E1: 物理管容 | F1: 站场 | G1: 阀室 | H1: 压气站 | I1: 分输站 | J1: 其他站 | K1: 代管站 | L1: 监控阀室 | M1: 监视阀室 | N1: 普通阀室
A2: 1 | B2: 西气东输一线 | C2: 一级 | D2: =SUMIF(管道站场阀室关系!A:A,B2,管道站场阀室关系!H:H) -> 4474.7199 | E2: =SUMIF(管道站场阀室关系!A:A,B2,管道站场阀室关系!J:J) -> 3098264.6 | F2: =SUM(H2:K2) -> 65 | G2: =SUM(L2:N2) -> 158 | H2: =COUNTIFS(管道站场阀室关系!A:A,B2,管道站场阀室关系!P:P,H$1) -> 22 | I2: =COUNTIFS(管道站场阀室关系!A:A,B2,管道站场阀室关系!P:P,I$1) -> 41 | J2: =COUNTIFS(管道站场阀室关系!A:A,B2,管道站场阀室关系!P:P,J$1) -> 2 | K2: =COUNTIFS(管道站场阀室关系!A:A,B2,管道站场阀室关系!P:P,K$1) -> 0 | L2: =COUNTIFS(管道站场阀室关系!A:A,B2,管道站场阀室关系!P:P,L$1) -> 139 | M2: =COUNTIFS(管道站场阀室关系!A:A,B2,管道站场阀室关系!P:P,M$1) -> 2 | N2: =COUNTIFS(管道站场阀室关系!A:A,B2,管道站场阀室关系!P:P,N$1) -> 17
A3: 2 | B3: 冀宁线 | C3: 一级 | D3: =SUMIF(管道站场阀室关系!A:A,B3,管道站场阀室关系!H:H) -> 1331.2707 | E3: =SUMIF(管道站场阀室关系!A:A,B3,管道站场阀室关系!J:J) -> 487778.67 | F3: =SUM(H3:K3) -> 32 | G3: =SUM(L3:N3) -> 45 | H3: =COUNTIFS(管道站场阀室关系!A:A,B3,管道站场阀室关系!P:P,H$1) -> 1 | I3: =COUNTIFS(管道站场阀室关系!A:A,B3,管道站场阀室关系!P:P,I$1) -> 29 | J3: =COUNTIFS(管道站场阀室关系!A:A,B3,管道站场阀室关系!P:P,J$1) -> 0 | K3: =COUNTIFS(管道站场阀室关系!A:A,B3,管道站场阀室关系!P:P,K$1) -> 2 | L3: =COUNTIFS(管道站场阀室关系!A:A,B3,管道站场阀室关系!P:P,L$1) -> 6 | M3: =COUNTIFS(管道站场阀室关系!A:A,B3,管道站场阀室关系!P:P,M$1) -> 1 | N3: =COUNTIFS(管道站场阀室关系!A:A,B3,管道站场阀室关系!P:P,N$1) -> 38
A4: 3 | B4: 江苏LNG外输管道 | C4: 一级 | D4: =SUMIF(管道站场阀室关系!A:A,B4,管道站场阀室关系!H:H) -> 391.877 | E4: =SUMIF(管道站场阀室关系!A:A,B4,管道站场阀室关系!J:J) -> 250339.45 | F4: =SUM(H4:K4) -> 10 | G4: =SUM(L4:N4) -> 20 | H4: =COUNTIFS(管道站场阀室关系!A:A,B4,管道站场阀室关系!P:P,H$1) -> 0 | I4: =COUNTIFS(管道站场阀室关系!A:A,B4,管道站场阀室关系!P:P,I$1) -> 9 | J4: =COUNTIFS(管道站场阀室关系!A:A,B4,管道站场阀室关系!P:P,J$1) -> 1 | K4: =COUNTIFS(管道站场阀室关系!A:A,B4,管道站场阀室关系!P:P,K$1) -> 0 | L4: =COUNTIFS(管道站场阀室关系!A:A,B4,管道站场阀室关系!P:P,L$1) -> 18 | M4: =COUNTIFS(管道站场阀室关系!A:A,B4,管道站场阀室关系!P:P,M$1) -> 2 | N4: =COUNTIFS(管道站场阀室关系!A:A,B4,管道站场阀室关系!P:P,N$1) -> 0
A5: 4 | B5: 淮武线 | C5: 一级 | D5: =SUMIF(管道站场阀室关系!A:A,B5,管道站场阀室关系!H:H) -> 436.889 | E5: =SUMIF(管道站场阀室关系!A:A,B5,管道站场阀室关系!J:J) -> 116059 | F5: =SUM(H5:K5) -> 3 | G5: =SUM(L5:N5) -> 21 | H5: =COUNTIFS(管道站场阀室关系!A:A,B5,管道站场阀室关系!P:P,H$1) -> 0 | I5: =COUNTIFS(管道站场阀室关系!A:A,B5,管道站场阀室关系!P:P,I$1) -> 3 | J5: =COUNTIFS(管道站场阀室关系!A:A,B5,管道站场阀室关系!P:P,J$1) -> 0 | K5: =COUNTIFS(管道站场阀室关系!A:A,B5,管道站场阀室关系!P:P,K$1) -> 0 | L5: =COUNTIFS(管道站场阀室关系!A:A,B5,管道站场阀室关系!P:P,L$1) -> 8 | M5: =COUNTIFS(管道站场阀室关系!A:A,B5,管道站场阀室关系!P:P,M$1) -> 0 | N5: =COUNTIFS(管道站场阀室关系!A:A,B5,管道站场阀室关系!P:P,N$1) -> 13
A6: 5 | B6: 西气东输二线 | C6: 一级 | D6: =SUMIF(管道站场阀室关系!A:A,B6,管道站场阀室关系!H:H) -> 5098.0123 | E6: =SUMIF(管道站场阀室关系!A:A,B6,管道站场阀室关系!J:J) -> 5365107.9 | F6: =SUM(H6:K6) -> 64 | G6: =SUM(L6:N6) -> 150 | H6: =COUNTIFS(管道站场阀室关系!A:A,B6,管道站场阀室关系!P:P,H$1) -> 27 | I6: =COUNTIFS(管道站场阀室关系!A:A,B6,管道站场阀室关系!P:P,I$1) -> 36 | J6: =COUNTIFS(管道站场阀室关系!A:A,B6,管道站场阀室关系!P:P,J$1) -> 1 | K6: =COUNTIFS(管道站场阀室关系!A:A,B6,管道站场阀室关系!P:P,K$1) -> 0 | L6: =COUNTIFS(管道站场阀室关系!A:A,B6,管道站场阀室关系!P:P,L$1) -> 33 | M6: =COUNTIFS(管道站场阀室关系!A:A,B6,管道站场阀室关系!P:P,M$1) -> 116 | N6: =COUNTIFS(管道站场阀室关系!A:A,B6,管道站场阀室关系!P:P,N$1) -> 1
A7: 6 | B7: 轮吐支干线 | C7: 一级 | D7: =SUMIF(管道站场阀室关系!A:A,B7,管道站场阀室关系!H:H) -> 524 | E7: =SUMIF(管道站场阀室关系!A:A,B7,管道站场阀室关系!J:J) -> 424150 | F7: =SUM(H7:K7) -> 1 | G7: =SUM(L7:N7) -> 15 | H7: =COUNTIFS(管道站场阀室关系!A:A,B7,管道站场阀室关系!P:P,H$1) -> 1 | I7: =COUNTIFS(管道站场阀室关系!A:A,B7,管道站场阀室关系!P:P,I$1) -> 0 | J7: =COUNTIFS(管道站场阀室关系!A:A,B7,管道站场阀室关系!P:P,J$1) -> 0 | K7: =COUNTIFS(管道站场阀室关系!A:A,B7,管道站场阀室关系!P:P,K$1) -> 0 | L7: =COUNTIFS(管道站场阀室关系!A:A,B7,管道站场阀室关系!P:P,L$1) -> 3 | M7: =COUNTIFS(管道站场阀室关系!A:A,B7,管道站场阀室关系!P:P,M$1) -> 12 | N7: =COUNTIFS(管道站场阀室关系!A:A,B7,管道站场阀室关系!P:P,N$1) -> 0
A8: 7 | B8: 中靖支干线 | C8: 一级 | D8: =SUMIF(管道站场阀室关系!A:A,B8,管道站场阀室关系!H:H) -> 335.4 | E8: =SUMIF(管道站场阀室关系!A:A,B8,管道站场阀室关系!J:J) -> 262751.21 | F8: =SUM(H8:K8) -> 2 | G8: =SUM(L8:N8) -> 12 | H8: =COUNTIFS(管道站场阀室关系!A:A,B8,管道站场阀室关系!P:P,H$1) -> 0 | I8: =COUNTIFS(管道站场阀室关系!A:A,B8,管道站场阀室关系!P:P,I$1) -> 2 | J8: =COUNTIFS(管道站场阀室关系!A:A,B8,管道站场阀室关系!P:P,J$1) -> 0 | K8: =COUNTIFS(管道站场阀室关系!A:A,B8,管道站场阀室关系!P:P,K$1) -> 0 | L8: =COUNTIFS(管道站场阀室关系!A:A,B8,管道站场阀室关系!P:P,L$1) -> 0 | M8: =COUNTIFS(管道站场阀室关系!A:A,B8,管道站场阀室关系!P:P,M$1) -> 12 | N8: =COUNTIFS(管道站场阀室关系!A:A,B8,管道站场阀室关系!P:P,N$1) -> 0
A9: 8 | B9: 枣十支干线 | C9: 一级 | D9: =SUMIF(管道站场阀室关系!A:A,B9,管道站场阀室关系!H:H) -> 206.1798 | E9: =SUMIF(管道站场阀室关系!A:A,B9,管道站场阀室关系!J:J) -> 38420.46 | F9: =SUM(H9:K9) -> 7 | G9: =SUM(L9:N9) -> 11 | H9: =COUNTIFS(管道站场阀室关系!A:A,B9,管道站场阀室关系!P:P,H$1) -> 0 | I9: =COUNTIFS(管道站场阀室关系!A:A,B9,管道站场阀室关系!P:P,I$1) -> 7 | J9: =COUNTIFS(管道站场阀室关系!A:A,B9,管道站场阀室关系!P:P,J$1) -> 0 | K9: =COUNTIFS(管道站场阀室关系!A:A,B9,管道站场阀室关系!P:P,K$1) -> 0 | L9: =COUNTIFS(管道站场阀室关系!A:A,B9,管道站场阀室关系!P:P,L$1) -> 5 | M9: =COUNTIFS(管道站场阀室关系!A:A,B9,管道站场阀室关系!P:P,M$1) -> 6 | N9: =COUNTIFS(管道站场阀室关系!A:A,B9,管道站场阀室关系!P:P,N$1) -> 0
A10: 9 | B10: 樟湘支干线 | C10: 一级 | D10: =SUMIF(管道站场阀室关系!A:A,B10,管道站场阀室关系!H:H) -> 262.2999 | E10: =SUMIF(管道站场阀室关系!A:A,B10,管道站场阀室关系!J:J) -> 81166.319 | F10: =SUM(H10:K10) -> 8 | G10: =SUM(L10:N10) -> 10 | H10: =COUNTIFS(管道站场阀室关系!A:A,B10,管道站场阀室关系!P:P,H$1) -> 1 | I10: =COUNTIFS(管道站场阀室关系!A:A,B10,管道站场阀室关系!P:P,I$1) -> 7 | J10: =COUNTIFS(管道站场阀室关系!A:A,B10,管道站场阀室关系!P:P,J$1) -> 0 | K10: =COUNTIFS(管道站场阀室关系!A:A,B10,管道站场阀室关系!P:P,K$1) -> 0 | L10: =COUNTIFS(管道站场阀室关系!A:A,B10,管道站场阀室关系!P:P,L$1) -> 3 | M10: =COUNTIFS(管道站场阀室关系!A:A,B10,管道站场阀室关系!P:P,M$1) -> 7 | N10: =COUNTIFS(管道站场阀室关系!A:A,B10,管道站场阀室关系!P:P,N$1) -> 0
A11: 10 | B11: 上海支干线 | C11: 一级 | D11: =SUMIF(管道站场阀室关系!A:A,B11,管道站场阀室关系!H:H) -> 902.8247 | E11: =SUMIF(管道站场阀室关系!A:A,B11,管道站场阀室关系!J:J) -> 687510.59 | F11: =SUM(H11:K11) -> 13 | G11: =SUM(L11:N11) -> 49 | H11: =COUNTIFS(管道站场阀室关系!A:A,B11,管道站场阀室关系!P:P,H$1) -> 2 | I11: =COUNTIFS(管道站场阀室关系!A:A,B11,管道站场阀室关系!P:P,I$1) -> 11 | J11: =COUNTIFS(管道站场阀室关系!A:A,B11,管道站场阀室关系!P:P,J$1) -> 0 | K11: =COUNTIFS(管道站场阀室关系!A:A,B11,管道站场阀室关系!P:P,K$1) -> 0 | L11: =COUNTIFS(管道站场阀室关系!A:A,B11,管道站场阀室关系!P:P,L$1) -> 20 | M11: =COUNTIFS(管道站场阀室关系!A:A,B11,管道站场阀室关系!P:P,M$1) -> 29 | N11: =COUNTIFS(管道站场阀室关系!A:A,B11,管道站场阀室关系!P:P,N$1) -> 0
A12: 11 | B12: 平泰支干线 | C12: 一级 | D12: =SUMIF(管道站场阀室关系!A:A,B12,管道站场阀室关系!H:H) -> 570.9099 | E12: =SUMIF(管道站场阀室关系!A:A,B12,管道站场阀室关系!J:J) -> 398273.48 | F12: =SUM(H12:K12) -> 9 | G12: =SUM(L12:N12) -> 17 | H12: =COUNTIFS(管道站场阀室关系!A:A,B12,管道站场阀室关系!P:P,H$1) -> 1 | I12: =COUNTIFS(管道站场阀室关系!A:A,B12,管道站场阀室关系!P:P,I$1) -> 8 | J12: =COUNTIFS(管道站场阀室关系!A:A,B12,管道站场阀室关系!P:P,J$1) -> 0 | K12: =COUNTIFS(管道站场阀室关系!A:A,B12,管道站场阀室关系!P:P,K$1) -> 0 | L12: =COUNTIFS(管道站场阀室关系!A:A,B12,管道站场阀室关系!P:P,L$1) -> 5 | M12: =COUNTIFS(管道站场阀室关系!A:A,B12,管道站场阀室关系!P:P,M$1) -> 12 | N12: =COUNTIFS(管道站场阀室关系!A:A,B12,管道站场阀室关系!P:P,N$1) -> 0
A13: 12 | B13: 广南支干线 | C13: 一级 | D13: =SUMIF(管道站场阀室关系!A:A,B13,管道站场阀室关系!H:H) -> 1327.0113 | E13: =SUMIF(管道站场阀室关系!A:A,B13,管道站场阀室关系!J:J) -> 579597.54 | F13: =SUM(H13:K13) -> 21 | G13: =SUM(L13:N13) -> 53 | H13: =COUNTIFS(管道站场阀室关系!A:A,B13,管道站场阀室关系!P:P,H$1) -> 1 | I13: =COUNTIFS(管道站场阀室关系!A:A,B13,管道站场阀室关系!P:P,I$1) -> 14 | J13: =COUNTIFS(管道站场阀室关系!A:A,B13,管道站场阀室关系!P:P,J$1) -> 2 | K13: =COUNTIFS(管道站场阀室关系!A:A,B13,管道站场阀室关系!P:P,K$1) -> 4 | L13: =COUNTIFS(管道站场阀室关系!A:A,B13,管道站场阀室关系!P:P,L$1) -> 36 | M13: =COUNTIFS(管道站场阀室关系!A:A,B13,管道站场阀室关系!P:P,M$1) -> 17 | N13: =COUNTIFS(管道站场阀室关系!A:A,B13,管道站场阀室关系!P:P,N$1) -> 0
... A57: 56 | B57: 漳州LNG外输管道 | C57: 一级 | D57: =SUMIF(管道站场阀室关系!A:A,B57,管道站场阀室关系!H:H) -> 123.25 | E57: =SUMIF(管道站场阀室关系!A:A,B57,管道站场阀室关系!J:J) -> 85360.55 | F57: =SUM(H57:K57) -> 2 | G57: =SUM(L57:N57) -> 5 | H57: =COUNTIFS(管道站场阀室关系!A:A,B57,管道站场阀室关系!P:P,H$1) -> 0 | I57: =COUNTIFS(管道站场阀室关系!A:A,B57,管道站场阀室关系!P:P,I$1) -> 2 | J57: =COUNTIFS(管道站场阀室关系!A:A,B57,管道站场阀室关系!P:P,J$1) -> 0 | K57: =COUNTIFS(管道站场阀室关系!A:A,B57,管道站场阀室关系!P:P,K$1) -> 0 | L57: =COUNTIFS(管道站场阀室关系!A:A,B57,管道站场阀室关系!P:P,L$1) -> 5 | M57: =COUNTIFS(管道站场阀室关系!A:A,B57,管道站场阀室关系!P:P,M$1) -> 0 | N57: =COUNTIFS(管道站场阀室关系!A:A,B57,管道站场阀室关系!P:P,N$1) -> 0
A58: 57 | B58: 广东省管网 | C58: 二级 | D58: 1989.464 | E58: 1503624 | F58: 59 | G58: =SUM(L58:N58) -> 77 | H58: =COUNTIFS(管道站场阀室关系!A:A,B58,管道站场阀室关系!P:P,H$1) -> 0 | I58: 43 | J58: 15 | K58: =COUNTIFS(管道站场阀室关系!A:A,B58,管道站场阀室关系!P:P,K$1) -> 1 | L58: =COUNTIFS(管道站场阀室关系!A:A,B58,管道站场阀室关系!P:P,L$1) -> 77 | M58: =COUNTIFS(管道站场阀室关系!A:A,B58,管道站场阀室关系!P:P,M$1) -> 0 | N58: =COUNTIFS(管道站场阀室关系!A:A,B58,管道站场阀室关系!P:P,N$1) -> 0
B59: 广东省管网（新丰专线） | C59: 一级 | D59: 15.474 | E59: 1173 | F59: 2 | G59: 0 | H59: 0 | I59: 1 | J59: 1 | K59: 0 | L59: 0 | M59: 0 | N59: 0
A60: 58 | B60: 粤东LNG外输管道 | C60: 二级 | D60: =SUMIF(管道站场阀室关系!A:A,B60,管道站场阀室关系!H:H) -> 179.28 | E60: =SUMIF(管道站场阀室关系!A:A,B60,管道站场阀室关系!J:J) -> 93041 | F60: =SUM(H60:K60) -> 9 | G60: =SUM(L60:N60) -> 5 | H60: =COUNTIFS(管道站场阀室关系!A:A,B60,管道站场阀室关系!P:P,H$1) -> 0 | I60: =COUNTIFS(管道站场阀室关系!A:A,B60,管道站场阀室关系!P:P,I$1) -> 2 | J60: =COUNTIFS(管道站场阀室关系!A:A,B60,管道站场阀室关系!P:P,J$1) -> 7 | K60: =COUNTIFS(管道站场阀室关系!A:A,B60,管道站场阀室关系!P:P,K$1) -> 0 | L60: =COUNTIFS(管道站场阀室关系!A:A,B60,管道站场阀室关系!P:P,L$1) -> 5 | M60: =COUNTIFS(管道站场阀室关系!A:A,B60,管道站场阀室关系!P:P,M$1) -> 0 | N60: =COUNTIFS(管道站场阀室关系!A:A,B60,管道站场阀室关系!P:P,N$1) -> 0
A61: 59 | B61: 浙江省管网 | C61: 二级 | D61: =SUMIF(管道站场阀室关系!A:A,B61,管道站场阀室关系!H:H) -> 2493.8877 | E61: =SUMIF(管道站场阀室关系!A:A,B61,管道站场阀室关系!J:J) -> 959122 | F61: =SUM(H61:K61) -> 91 | G61: =SUM(L61:N61) -> 119 | H61: =COUNTIFS(管道站场阀室关系!A:A,B61,管道站场阀室关系!P:P,H$1) -> 0 | I61: =COUNTIFS(管道站场阀室关系!A:A,B61,管道站场阀室关系!P:P,I$1) -> 75 | J61: =COUNTIFS(管道站场阀室关系!A:A,B61,管道站场阀室关系!P:P,J$1) -> 16 | K61: =COUNTIFS(管道站场阀室关系!A:A,B61,管道站场阀室关系!P:P,K$1) -> 0 | L61: =COUNTIFS(管道站场阀室关系!A:A,B61,管道站场阀室关系!P:P,L$1) -> 119 | M61: =COUNTIFS(管道站场阀室关系!A:A,B61,管道站场阀室关系!P:P,M$1) -> 0 | N61: =COUNTIFS(管道站场阀室关系!A:A,B61,管道站场阀室关系!P:P,N$1) -> 0
A62: 60 | B62: 湖南省管网 | C62: 二级 | D62: =SUMIF(管道站场阀室关系!A:A,B62,管道站场阀室关系!H:H) -> 957.4799 | E62: =SUMIF(管道站场阀室关系!A:A,B62,管道站场阀室关系!J:J) -> 0 | F62: =SUM(H62:K62) -> 24 | G62: =SUM(L62:N62) -> 50 | H62: =COUNTIFS(管道站场阀室关系!A:A,B62,管道站场阀室关系!P:P,H$1) -> 0 | I62: =COUNTIFS(管道站场阀室关系!A:A,B62,管道站场阀室关系!P:P,I$1) -> 18 | J62: =COUNTIFS(管道站场阀室关系!A:A,B62,管道站场阀室关系!P:P,J$1) -> 6 | K62: =COUNTIFS(管道站场阀室关系!A:A,B62,管道站场阀室关系!P:P,K$1) -> 0 | L62: =COUNTIFS(管道站场阀室关系!A:A,B62,管道站场阀室关系!P:P,L$1) -> 35 | M62: =COUNTIFS(管道站场阀室关系!A:A,B62,管道站场阀室关系!P:P,M$1) -> 3 | N62: =COUNTIFS(管道站场阀室关系!A:A,B62,管道站场阀室关系!P:P,N$1) -> 12
A63: 61 | B63: 贵州省管网 | C63: 二级 | D63: =SUMIF(管道站场阀室关系!A:A,B63,管道站场阀室关系!H:H) -> 92.379 | E63: =SUMIF(管道站场阀室关系!A:A,B63,管道站场阀室关系!J:J) -> 5680.983 | F63: =SUM(H63:K63) -> 15 | G63: =SUM(L63:N63) -> 1 | H63: =COUNTIFS(管道站场阀室关系!A:A,B63,管道站场阀室关系!P:P,H$1) -> 0 | I63: =COUNTIFS(管道站场阀室关系!A:A,B63,管道站场阀室关系!P:P,I$1) -> 14 | J63: =COUNTIFS(管道站场阀室关系!A:A,B63,管道站场阀室关系!P:P,J$1) -> 1 | K63: =COUNTIFS(管道站场阀室关系!A:A,B63,管道站场阀室关系!P:P,K$1) -> 0 | L63: =COUNTIFS(管道站场阀室关系!A:A,B63,管道站场阀室关系!P:P,L$1) -> 0 | M63: =COUNTIFS(管道站场阀室关系!A:A,B63,管道站场阀室关系!P:P,M$1) -> 0 | N63: =COUNTIFS(管道站场阀室关系!A:A,B63,管道站场阀室关系!P:P,N$1) -> 1
A64: 62 | B64: 鄯乌线 | C64: 二级 | D64: =SUMIF(管道站场阀室关系!A:A,B64,管道站场阀室关系!H:H) -> 301.73 | E64: =SUMIF(管道站场阀室关系!A:A,B64,管道站场阀室关系!J:J) -> 47355 | F64: =SUM(H64:K64) -> 5 | G64: =SUM(L64:N64) -> 7 | H64: =COUNTIFS(管道站场阀室关系!A:A,B64,管道站场阀室关系!P:P,H$1) -> 1 | I64: =COUNTIFS(管道站场阀室关系!A:A,B64,管道站场阀室关系!P:P,I$1) -> 3 | J64: =COUNTIFS(管道站场阀室关系!A:A,B64,管道站场阀室关系!P:P,J$1) -> 1 | K64: =COUNTIFS(管道站场阀室关系!A:A,B64,管道站场阀室关系!P:P,K$1) -> 0 | L64: =COUNTIFS(管道站场阀室关系!A:A,B64,管道站场阀室关系!P:P,L$1) -> 0 | M64: =COUNTIFS(管道站场阀室关系!A:A,B64,管道站场阀室关系!P:P,M$1) -> 7 | N64: =COUNTIFS(管道站场阀室关系!A:A,B64,管道站场阀室关系!P:P,N$1) -> 0
B65: 注：广东省管网和广东省管网（新丰专线）数据非公式取值。广东省管网（新丰专线）不计入干线条数。

Sheet 支线管道
A1: [原始]序号 | B1: [关联]干线管道 | C1: [原始]支线管道 | D1: [原始]起点 | E1: [原始]终点 | F1: [计算]长度/km | G1: [原始]管径/mm | H1: [原始]主要壁厚/mm | I1: [原始]设计压力/MPa | J1: [原始]设计输量/108m3/a | K1: [原始]设计输量/104m3/d | L1: [计算]物理管容/m3 | M1: [原始]管道投产时间 | N1: [关联]调度台 | O1: [原始]备注
A2: 1 | B2: 西气东输一线 | C2: 西一线干线新疆段 | D2: 轮南压气站 | E2: 红柳压气站 | F2: =SUMIF(管道站场阀室关系!B:B,支线管道!C2,管道站场阀室关系!H:H) -> 954.9577 | G2: 1016 | H2: 14 | I2: 10 | J2: 170 | L2: =SUMIF(管道站场阀室关系!B:B,支线管道!C2,管道站场阀室关系!J:J) -> 711669 | M2: 20041001 | N2: 西部
A3: 2 | B3: 西气东输一线 | C3: 西一线干线甘肃段 | D3: 红柳压气站 | E3: 中卫压气站 | F3: =SUMIF(管道站场阀室关系!B:B,支线管道!C3,管道站场阀室关系!H:H) -> 1028.9439 | G3: 1016 | H3: 14 | I3: 10 | J3: 170 | L3: =SUMIF(管道站场阀室关系!B:B,支线管道!C3,管道站场阀室关系!J:J) -> 810642.05 | M3: 20041001 | N3: 西部
A4: 3 | B4: 西气东输一线 | C4: 西一线干线东段 | D4: 中卫压气站 | E4: 白鹤末站 | F4: =SUMIF(管道站场阀室关系!B:B,支线管道!C4,管道站场阀室关系!H:H) -> 1862.2965 | G4: 1016 | H4: 14 | I4: 10 | J4: 170 | L4: =SUMIF(管道站场阀室关系!B:B,支线管道!C4,管道站场阀室关系!J:J) -> 1392366.5 | M4: 20041001 | N4: 东部
A5: 4 | B5: 西气东输一线 | C5: 常长支线 | D5: 芙蓉分输站 | E5: 长兴末站 | F5: =SUMIF(管道站场阀室关系!B:B,支线管道!C5,管道站场阀室关系!H:H) -> 99.6003 | G5: 813 | I5: 6.4 | J5: 17.86 | L5: =SUMIF(管道站场阀室关系!B:B,支线管道!C5,管道站场阀室关系!J:J) -> 48562.526 | M5: 20031218 | N5: 东部
A6: 5 | B6: 西气东输一线 | C6: 南芜支线 | D6: 西一线南京站 | E6: 芜湖末站 | F6: =SUMIF(管道站场阀室关系!B:B,支线管道!C6,管道站场阀室关系!H:H) -> 130 | G6: 508 | H6: 7.1 | I6: 6.3 | J6: 16.71 | L6: =SUMIF(管道站场阀室关系!B:B,支线管道!C6,管道站场阀室关系!J:J) -> 24780.719 | M6: 200405 | N6: 东部
A7: 6 | B7: 西气东输一线 | C7: 金陵电厂支线 | D7: 西一线南京站 | E7: 金陵电厂 | F7: =SUMIF(管道站场阀室关系!B:B,支线管道!C7,管道站场阀室关系!H:H) -> 3.696 | L7: =SUMIF(管道站场阀室关系!B:B,支线管道!C7,管道站场阀室关系!J:J) -> 320.656 | N7: 东部
A8: 7 | B8: 西气东输一线 | C8: 定合支线 | D8: 定远压气站 | E8: 合肥末站 | F8: =SUMIF(管道站场阀室关系!B:B,支线管道!C8,管道站场阀室关系!H:H) -> 79.5999 | G8: 406.4 | H8: 6.3 | I8: 6.3 | J8: 3.28 | L8: =SUMIF(管道站场阀室关系!B:B,支线管道!C8,管道站场阀室关系!J:J) -> 9989.0904 | M8: 200306 | N8: 东部
A9: 8 | B9: 西气东输一线 | C9: 定合复线 | D9: 定远压气站 | E9: 合肥北站 | F9: =SUMIF(管道站场阀室关系!B:B,支线管道!C9,管道站场阀室关系!H:H) -> 67.2999 | G9: 711 | H9: 14.3/15.9/20.6 | I9: 10 | J9: 34.89 | L9: =SUMIF(管道站场阀室关系!B:B,支线管道!C9,管道站场阀室关系!J:J) -> 26730.737 | M9: 20191106 | N9: 东部
A10: 9 | B10: 西气东输一线 | C10: 扬巴支线 | D10: 龙池分输站 | E10: 扬子扬巴末站 | F10: =SUMIF(管道站场阀室关系!B:B,支线管道!C10,管道站场阀室关系!H:H) -> 6.2 | G10: 406.4 | I10: 10 | J10: 15 | L10: =SUMIF(管道站场阀室关系!B:B,支线管道!C10,管道站场阀室关系!J:J) -> 718.22538 | M10: 200312 | N10: 东部
A11: 10 | B11: 西气东输一线 | C11: 长铝支线 | D11: 郑州压气站 | E11: 长铝末站 | F11: =SUMIF(管道站场阀室关系!B:B,支线管道!C11,管道站场阀室关系!H:H) -> 24 | G11: 219 | I11: 6.4 | J11: 1 | L11: =SUMIF(管道站场阀室关系!B:B,支线管道!C11,管道站场阀室关系!J:J) -> 934 | M11: 20040630 | N11: 东部
A12: 11 | B12: 西气东输一线 | C12: 望亭电厂支线 | D12: 东桥分输站 | E12: 望亭分输站 | F12: =SUMIF(管道站场阀室关系!B:B,支线管道!C12,管道站场阀室关系!H:H) -> 8.2 | G12: 508 | I12: 10 | J12: 10 | L12: =SUMIF(管道站场阀室关系!B:B,支线管道!C12,管道站场阀室关系!J:J) -> 1481.9348 | M12: 200506 | N12: 东部
A13: 12 | B13: 西气东输一线 | C13: 甪宝支线 | D13: 甪直分输站 | E13: 浏河分输站 | F13: =SUMIF(管道站场阀室关系!B:B,支线管道!C13,管道站场阀室关系!H:H) -> 80.219 | G13: 610 | I13: 4 | J13: 20 | L13: =SUMIF(管道站场阀室关系!B:B,支线管道!C13,管道站场阀室关系!J:J) -> 23909.55 | M13: 20110816 | N13: 东部
A14: 13 | B14: 西气东输一线 | C14: 金坛储气库支线 | D14: 镇江分输站 | E14: 金坛分输站 | F14: =SUMIF(管道站场阀室关系!B:B,支线管道!C14,管道站场阀室关系!H:H) -> 34.81 | G14: 1016 | H14: 26 | I14: 10 | J14: - | L14: =SUMIF(管道站场阀室关系!B:B,支线管道!C14,管道站场阀室关系!J:J) -> 25726.619 | M14: 20070101 | N14: 东部
A15: 14 | B15: 西气东输一线 | C15: 金溧支线 | D15: 金坛分输站 | E15: 南渡分输站 | F15: =SUMIF(管道站场阀室关系!B:B,支线管道!C15,管道站场阀室关系!H:H) -> 52.3467 | G15: 508 | I15: 6.3 | J15: 21.66 | L15: =SUMIF(管道站场阀室关系!B:B,支线管道!C15,管道站场阀室关系!J:J) -> 10084.375 | M15: 20160612 | N15: 东部
A16: 15 | B16: 西气东输一线 | C16: 沁水煤层气管道 | D16: 端氏首站 | E16: 沁水压气站 | F16: =SUMIF(管道站场阀室关系!B:B,支线管道!C16,管道站场阀室关系!H:H) -> 35 | G16: 610 | H16: 8 | I16: 6.3 | J16: 30 | L16: =SUMIF(管道站场阀室关系!B:B,支线管道!C16,管道站场阀室关系!J:J) -> 9668 | M16: 20090915 | N16: 东部
A17: 16 | B17: 西气东输一线 | C17: 长江备用线 | D17: 青山分输站 | E17: 龙潭站上游1.5km | F17: =SUMIF(管道站场阀室关系!B:B,支线管道!C17,管道站场阀室关系!H:H) -> 5.8 | G17: 406.4 | L17: =SUMIF(管道站场阀室关系!B:B,支线管道!C17,管道站场阀室关系!J:J) -> 0 | N17: 东部
A18: 17 | B18: 西气东输一线 | C18: 西一线与青宁线青山-南京联络线 | D18: 青山分输站 | E18: 南京末站 | F18: =SUMIF(管道站场阀室关系!B:B,支线管道!C18,管道站场阀室关系!H:H) -> 1.25 | L18: =SUMIF(管道站场阀室关系!B:B,支线管道!C18,管道站场阀室关系!J:J) -> 680.64
A19: 18 | B19: 西气东输一线 | C19: 南京计量中心支线 | D19: 龙潭分输站 | E19: 南京计量中心 | F19: =SUMIF(管道站场阀室关系!B:B,支线管道!C19,管道站场阀室关系!H:H) -> 0.5 | L19: =SUMIF(管道站场阀室关系!B:B,支线管道!C19,管道站场阀室关系!J:J) -> 0
A20: 19 | B20: 冀宁线 | C20: 冀宁线干线冀鲁段 | D20: 泰安分输站 | E20: 安平压气站 | F20: =SUMIF(管道站场阀室关系!B:B,支线管道!C20,管道站场阀室关系!H:H) -> 530.476 | G20: 1016 | H20: 17.5 | I20: 10 | J20: 110 | L20: =SUMIF(管道站场阀室关系!B:B,支线管道!C20,管道站场阀室关系!J:J) -> 273090 | M20: 20060115 | N20: 东部
A21: 20 | B21: 冀宁线 | C21: 冀宁线干线苏北段 | D21: 青山分输站 | E21: 泰安分输站 | F21: =SUMIF(管道站场阀室关系!B:B,支线管道!C21,管道站场阀室关系!H:H) -> 386.5989 | G21: 711 | H21: 12.3 | I21: 10 | J21: 110 | L21: =SUMIF(管道站场阀室关系!B:B,支线管道!C21,管道站场阀室关系!J:J) -> 138439.3 | M21: 20060115 | N21: 东部
A22: 21 | B22: 冀宁线 | C22: 临沂支线 | D22: 滕州分输站 | E22: 临沂末站 | F22: =SUMIF(管道站场阀室关系!B:B,支线管道!C22,管道站场阀室关系!H:H) -> 90.5009 | G22: 406.4 | I22: 6.3 | J22: 6.5 | L22: =SUMIF(管道站场阀室关系!B:B,支线管道!C22,管道站场阀室关系!J:J) -> 10707 | M22: 20060710 | N22: 东部
A23: 22 | B23: 冀宁线 | C23: 济宁支线 | D23: 曲阜分输站 | E23: 济宁末站 | F23: =SUMIF(管道站场阀室关系!B:B,支线管道!C23,管道站场阀室关系!H:H) -> 40.21 | G23: 323.9 | I23: 6.3 | J23: 7.5 | L23: =SUMIF(管道站场阀室关系!B:B,支线管道!C23,管道站场阀室关系!J:J) -> 3060 | M23: 200710 | N23: 东部
A24: 23 | B24: 冀宁线 | C24: 邳徐支线 | D24: 邳州压气站 | E24: 徐州分输站 | F24: =SUMIF(管道站场阀室关系!B:B,支线管道!C24,管道站场阀室关系!H:H) -> 55.1159 | G24: 610 | I24: 10 | J24: 11.79 | L24: =SUMIF(管道站场阀室关系!B:B,支线管道!C24,管道站场阀室关系!J:J) -> 14964.372 | M24: 20070130 | N24: 东部
A25: 24 | B25: 冀宁线 | C25: 邳连支线 | D25: 邳州压气站 | E25: 连云港分输站 | F25: =SUMIF(管道站场阀室关系!B:B,支线管道!C25,管道站场阀室关系!H:H) -> 139.869 | G25: 610 | I25: 10 | J25: 4.4 | L25: =SUMIF(管道站场阀室关系!B:B,支线管道!C25,管道站场阀室关系!J:J) -> 39154.1 | M25: 20061206 | N25: 东部
A26: 25 | B26: 冀宁线 | C26: 武城支线 | D26: 德州分输站 | E26: 武城末站 | F26: =SUMIF(管道站场阀室关系!B:B,支线管道!C26,管道站场阀室关系!H:H) -> 18.39 | G26: 168.3 | I26: 6.3 | J26: 4.5 | L26: =SUMIF(管道站场阀室关系!B:B,支线管道!C26,管道站场阀室关系!J:J) -> 338 | M26: 200610 | N26: 东部
A27: 26 | B27: 冀宁线 | C27: 德州支线 | D27: 德州分输站 | E27: 德州末站 | F27: =SUMIF(管道站场阀室关系!B:B,支线管道!C27,管道站场阀室关系!H:H) -> 15.11 | G27: 219.1 | I27: 6.3 | J27: 5 | L27: =SUMIF(管道站场阀室关系!B:B,支线管道!C27,管道站场阀室关系!J:J) -> 512 | M27: 200706 | N27: 东部
A28: 27 | B28: 冀宁线 | C28: 泰安站联络线 | D28: 泰安压气站 | E28: 泰安分输站 | F28: =SUMIF(管道站场阀室关系!B:B,支线管道!C28,管道站场阀室关系!H:H) -> 7 | G28: 1016 | I28: 10 | J28: 110 | L28: =SUMIF(管道站场阀室关系!B:B,支线管道!C28,管道站场阀室关系!J:J) -> 0 | N28: 东部
A29: 28 | B29: 冀宁线 | C29: 刘庄储气库支线 | D29: 淮安分输站 | E29: 刘庄储气库 | F29: =SUMIF(管道站场阀室关系!B:B,支线管道!C29,管道站场阀室关系!H:H) -> 48 | G29: 457 | I29: 10 | J29: 1 | L29: =SUMIF(管道站场阀室关系!B:B,支线管道!C29,管道站场阀室关系!J:J) -> 7513.8928 | N29: 东部
A30: 29 | B30: 江苏LNG外输管道 | C30: 江如管道 | D30: 江都分输站 | E30: 如东分输站 | F30: =SUMIF(管道站场阀室关系!B:B,支线管道!C30,管道站场阀室关系!H:H) -> 221.4 | G30: 1016 | H30: 21 | I30: 10 | J30: 135 | L30: =SUMIF(管道站场阀室关系!B:B,支线管道!C30,管道站场阀室关系!J:J) -> 164554.12 | M30: 201007江都-泰州 20110518泰州-如东 | N30: 东部
A31: 30 | B31: 江苏LNG外输管道 | C31: 如东-海门-崇明岛支线 | D31: 如东分输站 | E31: 崇明燃气门站 | F31: =SUMIF(管道站场阀室关系!B:B,支线管道!C31,管道站场阀室关系!H:H) -> 83.857 | G31: 610 | I31: 10/6.3 | L31: =SUMIF(管道站场阀室关系!B:B,支线管道!C31,管道站场阀室关系!J:J) -> 42374.008 | M31: 20170908 | N31: 东部
A32: 31 | B32: 江苏LNG外输管道 | C32: 泰芙联络线 | D32: 泰兴分输站 | E32: 芙蓉分输站 | F32: =SUMIF(管道站场阀室关系!B:B,支线管道!C32,管道站场阀室关系!H:H) -> 57.9 | G32: 1016 | H32: 26.2 | I32: 10 | J32: 62.5 | L32: =SUMIF(管道站场阀室关系!B:B,支线管道!C32,管道站场阀室关系!J:J) -> 42509.318 | M32: 20140915 | N32: 东部
A33: 32 | B33: 江苏LNG外输管道 | C33: 大唐如皋电厂支线 | D33: 如皋分输站 | E33: 大唐电厂末站 | F33: =SUMIF(管道站场阀室关系!B:B,支线管道!C33,管道站场阀室关系!H:H) -> 28.72 | G33: 219.1 | I33: 6.3 | J33: 2 | K33: 57 | L33: 902 | M33: 20250802 | N33: 东部
A34: 33 | B34: 淮武线 | C34: 淮武线 | D34: 淮阳压气站 | E34: 武汉西分输站 | F34: =SUMIF(管道站场阀室关系!B:B,支线管道!C34,管道站场阀室关系!H:H) -> 436.889 | G34: 610 | H34: 7 | I34: 6.3 | J34: 22 | L34: =SUMIF(管道站场阀室关系!B:B,支线管道!C34,管道站场阀室关系!J:J) -> 116059 | M34: 20061215 | N34: 东部
A35: 34 | B35: 西气东输二线 | C35: 西二线干线新疆段 | D35: 霍尔果斯压气站 | E35: 红柳压气站 | F35: =SUMIF(管道站场阀室关系!B:B,支线管道!C35,管道站场阀室关系!H:H) -> 1350.101 | G35: 1219 | H35: 27 | I35: 12 | J35: 300 | K35: 8571 | L35: =SUMIF(管道站场阀室关系!B:B,支线管道!C35,管道站场阀室关系!J:J) -> 1472005 | M35: 20091215 | N35: 西部
A36: 35 | B36: 西气东输二线 | C36: 西二线干线甘肃段 | D36: 红柳压气站 | E36: 中卫压气站 | F36: =SUMIF(管道站场阀室关系!B:B,支线管道!C36,管道站场阀室关系!H:H) -> 1076.2283 | G36: 1219 | H36: 27 | I36: 12 | J36: 300 | K36: 8571 | L36: =SUMIF(管道站场阀室关系!B:B,支线管道!C36,管道站场阀室关系!J:J) -> 1171905 | M36: 20091215 | N36: 西部
A37: 36 | B37: 西气东输二线 | C37: 西二线干线中卫-吉安段 | D37: 中卫压气站 | E37: 吉安分输站 | F37: =SUMIF(管道站场阀室关系!B:B,支线管道!C37,管道站场阀室关系!H:H) -> 1953.7728 | G37: 1219 | H37: 20 | I37: 10 | J37: 280 | K37: 8000 | L37: =SUMIF(管道站场阀室关系!B:B,支线管道!C37,管道站场阀室关系!J:J) -> 2151274.9 | M37: 中卫至黄陂20101118 黄陂至吉安20110620 | N37: 中部
A38: 37 | B38: 西气东输二线 | C38: 西二线干线吉安-广州段 | D38: 吉安分输站 | E38: 广州压气站 | F38: =SUMIF(管道站场阀室关系!B:B,支线管道!C38,管道站场阀室关系!H:H) -> 530.7142 | G38: 1219 | H38: 20 | I38: 10 | J38: 280 | K38: 8000 | L38: =SUMIF(管道站场阀室关系!B:B,支线管道!C38,管道站场阀室关系!J:J) -> 557972.76 | M38: 20110620 | N38: 南部
A39: 38 | B39: 西气东输二线 | C39: 独石化支线 | D39: 奎屯分输站 | E39: 独石化末站 | F39: =SUMIF(管道站场阀室关系!B:B,支线管道!C39,管道站场阀室关系!H:H) -> 8.1 | G39: 219 | H39: 7.1 | I39: 6.3 | J39: 6 | K39: 171 | L39: =SUMIF(管道站场阀室关系!B:B,支线管道!C39,管道站场阀室关系!J:J) -> 267 | M39: 201012 | N39: 西部
A40: 39 | B40: 西气东输二线 | C40: 嘉峪关支线 | D40: 嘉峪关压气站 | E40: 嘉峪关门站 | F40: =SUMIF(管道站场阀室关系!B:B,支线管道!C40,管道站场阀室关系!H:H) -> 15.14 | G40: 168 | H40: 5.6 | I40: 6.3 | J40: 2.4 | L40: =SUMIF(管道站场阀室关系!B:B,支线管道!C40,管道站场阀室关系!J:J) -> 292 | M40: 20110413 | N40: 西部 | O40: 河西五市供气支线
A41: 40 | B41: 西气东输二线 | C41: 酒泉支线 | D41: 嘉峪关压气站 | E41: 酒泉门站 | F41: =SUMIF(管道站场阀室关系!B:B,支线管道!C41,管道站场阀室关系!H:H) -> 11 | G41: 168 | H41: 5.6 | I41: 6.3 | J41: 1.28 | L41: =SUMIF(管道站场阀室关系!B:B,支线管道!C41,管道站场阀室关系!J:J) -> 212 | M41: 20111207 | N41: 西部 | O41: 河西五市供气支线
A42: 41 | B42: 西气东输二线 | C42: 张掖支线 | D42: 张掖压气站 | E42: 张掖门站 | F42: =SUMIF(管道站场阀室关系!B:B,支线管道!C42,管道站场阀室关系!H:H) -> 22.93 | G42: 168 | H42: 5.6 | I42: 6.3 | J42: 2.06 | L42: =SUMIF(管道站场阀室关系!B:B,支线管道!C42,管道站场阀室关系!J:J) -> 443 | M42: 20110903 | N42: 西部 | O42: 河西五市供气支线
A43: 42 | B43: 西气东输二线 | C43: 金昌支线 | D43: 西二61#阀室 | E43: 金昌末站 | F43: =SUMIF(管道站场阀室关系!B:B,支线管道!C43,管道站场阀室关系!H:H) -> 48.029 | G43: 168 | H43: 5.6 | I43: 12 | J43: 3.68 | L43: =SUMIF(管道站场阀室关系!B:B,支线管道!C43,管道站场阀室关系!J:J) -> 926.3 | M43: 20111110 | N43: 西部 | O43: 河西五市供气支线
A44: 43 | B44: 西气东输二线 | C44: 武威支线 | D44: 武威分输站 | E44: 武威门站 | F44: =SUMIF(管道站场阀室关系!B:B,支线管道!C44,管道站场阀室关系!H:H) -> 9.12 | G44: 168 | H44: 5.6 | I44: 6.3 | J44: 1.47 | L44: =SUMIF(管道站场阀室关系!B:B,支线管道!C44,管道站场阀室关系!J:J) -> 176 | M44: 20110630 | N44: 西部 | O44: 河西五市供气支线
A45: 44 | B45: 西气东输二线 | C45: 洛阳支线 | D45: 洛阳分输站 | E45: 洛阳末站 | F45: =SUMIF(管道站场阀室关系!B:B,支线管道!C45,管道站场阀室关系!H:H) -> 24.64 | G45: 508 | H45: 8 | I45: 6.3 | J45: 35.73 | L45: =SUMIF(管道站场阀室关系!B:B,支线管道!C45,管道站场阀室关系!J:J) -> 4697 | M45: 20111212 | N45: 中部
A46: 45 | B46: 西气东输二线 | C46: 西二淮武-黄陂淮武联络线 | D46: 黄陂压气站 | E46: 淮武线15-16#阀室之间 | F46: =SUMIF(管道站场阀室关系!B:B,支线管道!C46,管道站场阀室关系!H:H) -> 4.051 | G46: 508 | H46: 7 | I46: 6.3 | J46: 25 | L46: =SUMIF(管道站场阀室关系!B:B,支线管道!C46,管道站场阀室关系!J:J) -> 711 | M46: 20101118 | N46: 东部
A47: 46 | B47: 西气东输二线 | C47: 西二川气东送-武穴姜家湾联络线 | D47: 130#阀室与武穴站间干线 | E47: 川气东送互联站 | F47: =SUMIF(管道站场阀室关系!B:B,支线管道!C47,管道站场阀室关系!H:H) -> 20.796 | G47: 813 | H47: 17.5 | I47: 10 | J47: 49.6/12 | L47: =SUMIF(管道站场阀室关系!B:B,支线管道!C47,管道站场阀室关系!J:J) -> 647 | M47: 20150610 | N47: 中部
A48: 47 | B48: 西气东输二线 | C48: 富平支线 | D48: 92#阀室下游 | E48: 富平分输站 | F48: =SUMIF(管道站场阀室关系!B:B,支线管道!C48,管道站场阀室关系!H:H) -> 23.39 | G48: 1216/406.4 | H48: 动火连接处25.7/穿越段10/其他7.9 | I48: 10/6.3 | J48: 13.8 | K48: 378.1 | L48: =SUMIF(管道站场阀室关系!B:B,支线管道!C48,管道站场阀室关系!J:J) -> 3579 | M48: 20250928 | N48: 中部
A49: 48 | B49: 轮吐支干线 | C49: 轮吐支干线 | D49: 轮南压气站 | E49: 吐鲁番压气站 | F49: =SUMIF(管道站场阀室关系!B:B,支线管道!C49,管道站场阀室关系!H:H) -> 524 | G49: 1016 | H49: 14 | I49: 10 | J49: 170 | L49: =SUMIF(管道站场阀室关系!B:B,支线管道!C49,管道站场阀室关系!J:J) -> 424150 | M49: 20121010 | N49: 西部
A50: 49 | B50: 中靖支干线 | C50: 中靖支干线 | D50: 中卫压气站 | E50: 西一靖边压气站 | F50: =SUMIF(管道站场阀室关系!B:B,支线管道!C50,管道站场阀室关系!H:H) -> 335.4 | G50: 1016 | H50: 14 | I50: 10 | J50: 100 | L50: =SUMIF(管道站场阀室关系!B:B,支线管道!C50,管道站场阀室关系!J:J) -> 262751.21 | M50: 20091130 | N50: 东部
A51: 50 | B51: 枣十支干线 | C51: 枣十支干线 | D51: 枣阳压气站 | E51: 十堰末站 | F51: =SUMIF(管道站场阀室关系!B:B,支线管道!C51,管道站场阀室关系!H:H) -> 178.0499 | G51: 枣阳-襄樊508 襄樊-十堰406 | H51: 5.2 | I51: 6.3 | J51: 枣阳-襄樊12 襄樊-十堰7 | L51: =SUMIF(管道站场阀室关系!B:B,支线管道!C51,管道站场阀室关系!J:J) -> 35089 | M51: 枣阳-襄樊20101118 襄樊-十堰20111227 | N51: 中部
A52: 51 | B52: 枣十支干线 | C52: 西二忠武襄樊联络线 | D52: 襄樊分输站 | E52: 襄樊计量站 | F52: =SUMIF(管道站场阀室关系!B:B,支线管道!C52,管道站场阀室关系!H:H) -> 27.6999 | G52: 406 | H52: 5.2 | I52: 6.3 | J52: 10 | L52: =SUMIF(管道站场阀室关系!B:B,支线管道!C52,管道站场阀室关系!J:J) -> 3278 | M52: 20101118 | N52: 中部
A53: 52 | B53: 枣十支干线 | C53: 枣十1#分输支线 | D53: 枣十1#阀室 | E53: 枣十1#分输阀室 | F53: =SUMIF(管道站场阀室关系!B:B,支线管道!C53,管道站场阀室关系!H:H) -> 0.43 | L53: =SUMIF(管道站场阀室关系!B:B,支线管道!C53,管道站场阀室关系!J:J) -> 53.46
A54: 53 | B54: 樟湘支干线 | C54: 樟湘支干线 | D54: 樟树分输站 | E54: 湘潭末站 | F54: =SUMIF(管道站场阀室关系!B:B,支线管道!C54,管道站场阀室关系!H:H) -> 262.2999 | G54: 660 | H54: 8 | I54: 10 | J54: 40 | L54: =SUMIF(管道站场阀室关系!B:B,支线管道!C54,管道站场阀室关系!J:J) -> 81166.319 | M54: 20110724 | N54: 中部
A55: 54 | B55: 上海支干线 | C55: 上海支干线 | D55: 南昌压气站 | E55: 金山末站 | F55: =SUMIF(管道站场阀室关系!B:B,支线管道!C55,管道站场阀室关系!H:H) -> 802.5978 | G55: 1016 | H55: 14 | I55: 10 | J55: 100 | L55: =SUMIF(管道站场阀室关系!B:B,支线管道!C55,管道站场阀室关系!J:J) -> 611724.31 | M55: 20120519 | N55: 中部
A56: 55 | B56: 上海支干线 | C56: 西二西一嘉甪联络线 | D56: 嘉兴分输站 | E56: 甪直分输站 | F56: =SUMIF(管道站场阀室关系!B:B,支线管道!C56,管道站场阀室关系!H:H) -> 100.2269 | G56: 1016 | H56: 14 | I56: 10 | J56: 41 | L56: =SUMIF(管道站场阀室关系!B:B,支线管道!C56,管道站场阀室关系!J:J) -> 75786.279 | M56: 嘉兴-5#阀室20120520 5#阀室-甪直20120706 | N56: 中部
A57: 56 | B57: 平泰支干线 | C57: 平泰河南段 | D57: 鲁山压气站 | E57: 兰考分输站 | F57: =SUMIF(管道站场阀室关系!B:B,支线管道!C57,管道站场阀室关系!H:H) -> 253.34 | G57: 1016 | H57: 14 | I57: 10 | J57: 100 | L57: =SUMIF(管道站场阀室关系!B:B,支线管道!C57,管道站场阀室关系!J:J) -> 186461.75 | M57: 鲁山-薛店20120314 薛店-泰安20120519 | N57: 中部
A58: 57 | B58: 平泰支干线 | C58: 平泰山东段 | D58: 兰考分输站 | E58: 泰安压气站 | F58: =SUMIF(管道站场阀室关系!B:B,支线管道!C58,管道站场阀室关系!H:H) -> 291.9699 | G58: 1016 | H58: 14 | I58: 10 | J58: 100 | L58: =SUMIF(管道站场阀室关系!B:B,支线管道!C58,管道站场阀室关系!J:J) -> 211811.73 | N58: 中部
A59: 58 | B59: 平泰支干线 | C59: 西二中开-中开平泰联络线 | D59: 中开线开封站 | E59: 杞县分输站 | F59: =SUMIF(管道站场阀室关系!B:B,支线管道!C59,管道站场阀室关系!H:H) -> 25.6 | G59: 711 | I59: 8 | J59: 30 | M59: 20231023 | N59: 中部
A60: 59 | B60: 广南支干线 | C60: 广南广东段 | D60: 广州压气站 | E60: 梧州压气站 | F60: =SUMIF(管道站场阀室关系!B:B,支线管道!C60,管道站场阀室关系!H:H) -> 246.2541 | G60: 1016 | H60: 14 | I60: 10 | J60: 90 | L60: =SUMIF(管道站场阀室关系!B:B,支线管道!C60,管道站场阀室关系!J:J) -> 200080.88 | M60: 20121228 | N60: 南部
A61: 60 | B61: 广南支干线 | C61: 广南广西段 | D61: 梧州压气站 | E61: 南宁分输站 | F61: =SUMIF(管道站场阀室关系!B:B,支线管道!C61,管道站场阀室关系!H:H) -> 353.3858 | G61: 1016 | H61: 14 | I61: 10 | J61: 90 | L61: =SUMIF(管道站场阀室关系!B:B,支线管道!C61,管道站场阀室关系!J:J) -> 263439.13 | M61: 20121228 | N61: 南部
A62: 61 | B62: 广南支干线 | C62: 珊瑚支线 | D62: 广南2#阀室 | E62: 珊瑚门站 | F62: =SUMIF(管道站场阀室关系!B:B,支线管道!C62,管道站场阀室关系!H:H) -> 0.17 | L62: =SUMIF(管道站场阀室关系!B:B,支线管道!C62,管道站场阀室关系!J:J) -> 0
A63: 62 | B63: 广南支干线 | C63: 苍梧-贺州支线 | D63: 梧州压气站 | E63: 贺州末站 | F63: =SUMIF(管道站场阀室关系!B:B,支线管道!C63,管道站场阀室关系!H:H) -> 205.15 | G63: 406.4 | H63: 6.3 | I63: 6.3 | J63: 8.86 | L63: =SUMIF(管道站场阀室关系!B:B,支线管道!C63,管道站场阀室关系!J:J) -> 25869.963 | M63: 20141009 | N63: 南部
A64: 63 | B64: 广南支干线 | C64: 南宁-百色支线 | D64: 南宁分输站 | E64: 百色末站 | F64: =SUMIF(管道站场阀室关系!B:B,支线管道!C64,管道站场阀室关系!H:H) -> 300 | G64: 南宁-吴圩660 吴圩-百色457 | H64: 8/6.3 | I64: 6.3 | J64: 16.91 | L64: =SUMIF(管道站场阀室关系!B:B,支线管道!C64,管道站场阀室关系!J:J) -> 56258.346 | M64: 南宁-吴圩20140813 吴圩-百色20150630 | N64: 南部
A65: 64 | B65: 广南支干线 | C65: 贵港-玉林支线 | D65: 贵港压气站 | E65: 玉林末站 | F65: =SUMIF(管道站场阀室关系!B:B,支线管道!C65,管道站场阀室关系!H:H) -> 99.2964 | G65: 406.4 | H65: 6.3 | I65: 6.3 | J65: 7.41 | L65: =SUMIF(管道站场阀室关系!B:B,支线管道!C65,管道站场阀室关系!J:J) -> 12545.227 | M65: 20151225 | N65: 南部
A66: 65 | B66: 广南支干线 | C66: 南宁-凭祥支线（南宁-崇左段） | D66: 吴圩分输站 | E66: 崇左输气站 | F66: =SUMIF(管道站场阀室关系!B:B,支线管道!C66,管道站场阀室关系!H:H) -> 114.755 | G66: 457 | H66: 7.1/8.0 | I66: 6.3 | J66: 7 | L66: =SUMIF(管道站场阀室关系!B:B,支线管道!C66,管道站场阀室关系!J:J) -> 17671 | M66: 20250522 | N66: 南部
A67: 66 | B67: 广南支干线 | C67: 广西管道与广南支干线南宁联络线 | D67: 广西管道南宁站 | E67: 广南南宁站 | F67: =SUMIF(管道站场阀室关系!B:B,支线管道!C67,管道站场阀室关系!H:H) -> 8 | G67: 813 | I67: 10 | J67: 45.5 | L67: =SUMIF(管道站场阀室关系!B:B,支线管道!C67,管道站场阀室关系!J:J) -> 3733 | M67: 20221202 | N67: 南部
A68: 67 | B68: 广深支干线 | C68: 广深支干线 | D68: 广州压气站 | E68: 大铲岛压气站 | F68: =SUMIF(管道站场阀室关系!B:B,支线管道!C68,管道站场阀室关系!H:H) -> 258.3999 | G68: 广州-求雨岭1016 求雨岭-大铲岛914 | H68: 14 | I68: 10 | J68: 100 | L68: =SUMIF(管道站场阀室关系!B:B,支线管道!C68,管道站场阀室关系!J:J) -> 189834 | M68: 广求段20120504 求大段20121219 | N68: 南部
A69: 68 | B69: 广深支干线 | C69: 樟木头支线 | D69: 11#和12#阀室之间 | E69: 樟木头分输站 | F69: =SUMIF(管道站场阀室关系!B:B,支线管道!C69,管道站场阀室关系!H:H) -> 0.8 | L69: =SUMIF(管道站场阀室关系!B:B,支线管道!C69,管道站场阀室关系!J:J) -> 0 | N69: 南部
A70: 69 | B70: 香港支线 | C70: 香港支线 | D70: 大铲岛压气站 | E70: 龙鼓滩分输站 | F70: =SUMIF(管道站场阀室关系!B:B,支线管道!C70,管道站场阀室关系!H:H) -> 21.074 | G70: 813 | H70: 22.2 | I70: 7 | J70: 100 | L70: =SUMIF(管道站场阀室关系!B:B,支线管道!C70,管道站场阀室关系!J:J) -> 9738 | M70: 20121219 | N70: 南部
A71: 70 | B71: 西气东输三线 | C71: 西三线干线新疆段 | D71: 霍尔果斯压气站 | E71: 红柳压气站 | F71: =SUMIF(管道站场阀室关系!B:B,支线管道!C71,管道站场阀室关系!H:H) -> 1350.101 | G71: 1219 | H71: 18.4 | I71: 12 | J71: 300 | L71: =SUMIF(管道站场阀室关系!B:B,支线管道!C71,管道站场阀室关系!J:J) -> 1427226 | M71: 霍尔果斯-乌鲁木齐20130723 乌鲁木齐-连木沁20131211 连木沁-瓜州20140702 | N71: 西部
A72: 71 | B72: 西气东输三线 | C72: 西三线干线甘肃段 | D72: 红柳压气站 | E72: 中卫压气站 | F72: =SUMIF(管道站场阀室关系!B:B,支线管道!C72,管道站场阀室关系!H:H) -> 1083.8993 | G72: 1219 | H72: 18.4 | I72: 12 | J72: 300 | L72: =SUMIF(管道站场阀室关系!B:B,支线管道!C72,管道站场阀室关系!J:J) -> 1163379 | M72: 瓜州-67#阀室20140901 67#阀室-中卫20141120 | N72: 西部
A73: 72 | B73: 西气东输三线 | C73: 西三线中段 | D73: 枣阳压气站 | E73: 仙桃联络站 | F73: =SUMIF(管道站场阀室关系!B:B,支线管道!C73,管道站场阀室关系!H:H) -> 1483.1 | G73: 1219 | H73: 22 | I73: 10 | J73: 250 | L73: =SUMIF(管道站场阀室关系!B:B,支线管道!C73,管道站场阀室关系!J:J) -> 1619493.5 | M73: 枣阳-仙桃20231209 | N73: 中部
A74: 73 | B74: 西气东输三线 | C74: 西三线干线东段 | D74: 吉安分输站 | E74: 福州末站 | F74: =SUMIF(管道站场阀室关系!B:B,支线管道!C74,管道站场阀室关系!H:H) -> 812.4902 | G74: 吉安-漳州1219 漳州-福州末1016 | H74: 22/21 | I74: 10 | J74: 150 | L74: =SUMIF(管道站场阀室关系!B:B,支线管道!C74,管道站场阀室关系!J:J) -> 790367.59 | M74: 20161013 | N74: 南部
A75: 74 | B75: 西气东输三线 | C75: 伊霍支线 | D75: 伊宁首站 | E75: 霍尔果斯压气站 | F75: =SUMIF(管道站场阀室关系!B:B,支线管道!C75,管道站场阀室关系!H:H) -> 65 | G75: 1219 | H75: 18.4 | I75: 12 | J75: 300 | L75: =SUMIF(管道站场阀室关系!B:B,支线管道!C75,管道站场阀室关系!J:J) -> 75728 | M75: 20130710 | N75: 西部
A76: 75 | B76: 西气东输三线 | C76: 石河子支线 | D76: 15#阀室 | E76: 石河子分输站 | F76: =SUMIF(管道站场阀室关系!B:B,支线管道!C76,管道站场阀室关系!H:H) -> 1.76 | L76: =SUMIF(管道站场阀室关系!B:B,支线管道!C76,管道站场阀室关系!J:J) -> 0 | N76: 西部
A77: 76 | B77: 西气东输三线 | C77: 新气西三潜江仙桃联络线 | D77: 仙桃联络站 | E77: 新气潜江站 | F77: =SUMIF(管道站场阀室关系!B:B,支线管道!C77,管道站场阀室关系!H:H) -> 19.02 | G77: 1219 | H77: 22 | I77: 10 | J77: 200 | L77: =SUMIF(管道站场阀室关系!B:B,支线管道!C77,管道站场阀室关系!J:J) -> 21459.1 | M77: 20231209 | N77: 中部
A78: 77 | B78: 西气东输三线 | C78: 长沙支线 | D78: 安沙分输站 | E78: 望城末站 | F78: =SUMIF(管道站场阀室关系!B:B,支线管道!C78,管道站场阀室关系!H:H) -> 44.87 | G78: 508 | I78: 6.3 | J78: 30 | L78: =SUMIF(管道站场阀室关系!B:B,支线管道!C78,管道站场阀室关系!J:J) -> 8831 | M78: 20190903 | N78: 中部
A79: 78 | B79: 西气东输三线 | C79: 西三新气长沙联络线 | D79: 石潭村站 | E79: 安沙站 | F79: =SUMIF(管道站场阀室关系!B:B,支线管道!C79,管道站场阀室关系!H:H) -> 9.25
A80: 79 | B80: 西气东输三线 | C80: 西三德化联络线 | D80: 东田站 | E80: 南安分输联络站 | F80: =SUMIF(管道站场阀室关系!B:B,支线管道!C80,管道站场阀室关系!H:H) -> 8.9 | G80: 508 | I80: 10 | J80: 47.5 | L80: =SUMIF(管道站场阀室关系!B:B,支线管道!C80,管道站场阀室关系!J:J) -> 0 | M80: 20221223 | N80: 南部
A81: 80 | B81: 西气东输三线 | C81: 西三福州联络线 | D81: 福州末站 | E81: 中海油青口分输站 | F81: =SUMIF(管道站场阀室关系!B:B,支线管道!C81,管道站场阀室关系!H:H) -> 21.6 | G81: 813 | I81: 7.5 | K81: 2000 | L81: =SUMIF(管道站场阀室关系!B:B,支线管道!C81,管道站场阀室关系!J:J) -> 10336 | M81: 20201109 | N81: 南部
A82: 81 | B82: 西气东输三线 | C82: 西三线中靖联络线 | D82: 中卫压气站 | E82: 西一靖边压气站 | F82: =SUMIF(管道站场阀室关系!B:B,支线管道!C82,管道站场阀室关系!H:H) -> 375.15 | G82: 1219 | H82: 22 | I82: 12 | J82: 300 | L82: =SUMIF(管道站场阀室关系!B:B,支线管道!C82,管道站场阀室关系!J:J) -> 408133.87 | M82: 20171031 | N82: 东部
A83: 82 | B83: 西气东输三线 | C83: 闽粤支干线 | D83: 广深6#阀室 | E83: 潮州分输站 | F83: =SUMIF(管道站场阀室关系!B:B,支线管道!C83,管道站场阀室关系!H:H) -> 379.9998 | G83: 813 | I83: 10 | J83: 58.1 | L83: =SUMIF(管道站场阀室关系!B:B,支线管道!C83,管道站场阀室关系!J:J) -> 180556.2 | M83: 20200121 | N83: 南部
A84: 83 | B84: 西气东输四线 | C84: 西四线干线新疆段 | D84: 吐鲁番压气站 | E84: 红柳压气站 | F84: =SUMIF(管道站场阀室关系!B:B,支线管道!C84,管道站场阀室关系!H:H) -> 602.8 | G84: 1219 | I84: 12 | J84: 150
A85: 84 | B85: 西气东输四线 | C85: 西四线干线甘肃段 | D85: 红柳压气站 | E85: 西四线54#阀室 | F85: =SUMIF(管道站场阀室关系!B:B,支线管道!C85,管道站场阀室关系!H:H) -> 1052.5 | G85: 1219 | H85: 18.4/22 | I85: 12 | J85: 150 | L85: =SUMIF(管道站场阀室关系!B:B,支线管道!C85,管道站场阀室关系!J:J) -> 0 | M85: 20250625 | N85: 西部
A86: 85 | B86: 西气东输四线 | C86: 西四线干线宁夏段 | D86: 西四线54#阀室 | E86: 中卫压气站 | F86: =SUMIF(管道站场阀室关系!B:B,支线管道!C86,管道站场阀室关系!H:H) -> 89.7 | G86: 1219 | H86: 18.4/22 | I86: 12 | J86: 150 | L86: =SUMIF(管道站场阀室关系!B:B,支线管道!C86,管道站场阀室关系!J:J) -> 0 | M86: 20250625 | N86: 西部
A87: 86 | B87: 漳州LNG外输管道 | C87: 漳州LNG外输管道 | D87: 漳州LNG接收站 | E87: 漳州分输清管站 | F87: =SUMIF(管道站场阀室关系!B:B,支线管道!C87,管道站场阀室关系!H:H) -> 123.25 | G87: 1016 | H87: 17.5/21/26.2 | I87: 10 | J87: 42 | K87: 1150.68 | L87: =SUMIF(管道站场阀室关系!B:B,支线管道!C87,管道站场阀室关系!J:J) -> 85360.55 | M87: 20240707 | N87: 南部
A88: 87 | B88: 深圳LNG外输管道 | C88: 深圳LNG外输管道 | D88: 深圳LNG东侧阀井 | E88: 广深樟木头-12#阀室之间 | F88: =SUMIF(管道站场阀室关系!B:B,支线管道!C88,管道站场阀室关系!H:H) -> 64.3 | G88: 1016 | I88: 10 | J88: 161 | K88: 4600 | L88: =SUMIF(管道站场阀室关系!B:B,支线管道!C88,管道站场阀室关系!J:J) -> 39480.98 | M88: 20200708 | N88: 南部
A89: 88 | B89: 深圳LNG外输管道 | C89: 深圳LNG深圳燃气联络线 | D89: 深圳LNG接收站 | E89: 深圳燃气迭福门站 | F89: =SUMIF(管道站场阀室关系!B:B,支线管道!C89,管道站场阀室关系!H:H) -> 0.3 | L89: =SUMIF(管道站场阀室关系!B:B,支线管道!C89,管道站场阀室关系!J:J) -> 78.771173
A90: 89 | B90: 深圳LNG外输管道 | C90: 西二线深圳LNG联络线 | D90: 深圳LNG接收站 | E90: 深圳LNG东侧阀井 | F90: =SUMIF(管道站场阀室关系!B:B,支线管道!C90,管道站场阀室关系!H:H) -> 1.9 | L90: =SUMIF(管道站场阀室关系!B:B,支线管道!C90,管道站场阀室关系!J:J) -> 775.30581
A91: 90 | B91: 陕京一线 | C91: 陕京一线干线 | D91: 陕京靖边首站 | E91: 石景山分输站 | F91: =SUMIF(管道站场阀室关系!B:B,支线管道!C91,管道站场阀室关系!H:H) -> 855.4997 | G91: 660 | H91: 7 | I91: 6.4 | J91: 33 | L91: =SUMIF(管道站场阀室关系!B:B,支线管道!C91,管道站场阀室关系!J:J) -> 279288.97 | M91: 19970910 | N91: 北部
A92: 91 | B92: 陕京二线 | C92: 靖边联络线 | D92: 西一靖边压气站 | E92: 陕京靖边首站 | F92: =SUMIF(管道站场阀室关系!B:B,支线管道!C92,管道站场阀室关系!H:H) -> 0.78 | G92: 1219 | I92: 12 | J92: 250 | L92: =SUMIF(管道站场阀室关系!B:B,支线管道!C92,管道站场阀室关系!J:J) -> 0 | N92: 北部
A93: 92 | B93: 陕京一线 | C93: 琉璃河-永清支线 | D93: 琉璃河分输站 | E93: 永清分输站 | F93: =SUMIF(管道站场阀室关系!B:B,支线管道!C93,管道站场阀室关系!H:H) -> 63.9999 | G93: 660 | H93: 7 | I93: 5 | J93: 33 | L93: =SUMIF(管道站场阀室关系!B:B,支线管道!C93,管道站场阀室关系!J:J) -> 21377.314 | M93: 199709 | N93: 北部
A94: 93 | B94: 陕京二线 | C94: 陕京二线干线 | D94: 西一靖边压气站 | E94: 通州东分输站 | F94: =SUMIF(管道站场阀室关系!B:B,支线管道!C94,管道站场阀室关系!H:H) -> 974.9693 | G94: 1016 | H94: 14 | I94: 10 | J94: 170 | L94: =SUMIF(管道站场阀室关系!B:B,支线管道!C94,管道站场阀室关系!J:J) -> 731008 | M94: 靖边-采育20050720 采育-通州东20081215 | N94: 北部
A95: 94 | B95: 陕京二线 | C95: 任丘支线 | D95: 任丘分输站 | E95: 任丘东站 | F95: =SUMIF(管道站场阀室关系!B:B,支线管道!C95,管道站场阀室关系!H:H) -> 1.5 | G95: 323.9 | I95: 6.3 | J95: 19.25 | L95: =SUMIF(管道站场阀室关系!B:B,支线管道!C95,管道站场阀室关系!J:J) -> 0 | M95: 20240329 | N95: 北部
A96: 95 | B96: 陕京二线 | C96: 永京线 | D96: 永清分输站 | E96: 通州南分输站 | F96: =SUMIF(管道站场阀室关系!B:B,支线管道!C96,管道站场阀室关系!H:H) -> 57.9999 | G96: 711 | H96: 7 | I96: 5.5 | J96: 14.5 | L96: =SUMIF(管道站场阀室关系!B:B,支线管道!C96,管道站场阀室关系!J:J) -> 22804.127 | M96: 200007 | N96: 北部
A97: 96 | B97: 陕京二线 | C97: 港清线 | D97: 永清分输站 | E97: 大港分输站 | F97: =SUMIF(管道站场阀室关系!B:B,支线管道!C97,管道站场阀室关系!H:H) -> 108 | G97: 711 | H97: 7 | I97: 5.5 | J97: 84 | L97: =SUMIF(管道站场阀室关系!B:B,支线管道!C97,管道站场阀室关系!J:J) -> 40353.337 | M97: 200412 | N97: 北部
A98: 97 | B98: 陕京二线 | C98: 港清复线 | D98: 永清分输站 | E98: 大港分输站 | F98: =SUMIF(管道站场阀室关系!B:B,支线管道!C98,管道站场阀室关系!H:H) -> 108 | G98: 711 | H98: 7 | I98: 10 | J98: 84 | L98: =SUMIF(管道站场阀室关系!B:B,支线管道!C98,管道站场阀室关系!J:J) -> 41493 | M98: 200408 | N98: 北部
A99: 98 | B99: 陕京二线 | C99: 港清三线 | D99: 永清首站 | E99: 大港末站 | F99: =SUMIF(管道站场阀室关系!B:B,支线管道!C99,管道站场阀室关系!H:H) -> 164.9999 | G99: 1016 | H99: 17.5 | I99: 10 | J99: 68.1 | K99: 1946 | L99: =SUMIF(管道站场阀室关系!B:B,支线管道!C99,管道站场阀室关系!J:J) -> 121262.98 | M99: 霸州-大港20151121 | N99: 北部
A100: 99 | B100: 陕京二线 | C100: 华北储气库配套管网 | D100: 永清分输站 | E100: 京58储气库 | F100: =SUMIF(管道站场阀室关系!B:B,支线管道!C100,管道站场阀室关系!H:H) -> 12.5 | G100: 559 | I100: 10 | L100: =SUMIF(管道站场阀室关系!B:B,支线管道!C100,管道站场阀室关系!J:J) -> 2762.5755 | M100: 2010 | N100: 北部
...

Sheet 管道站场阀室关系
A1: [关联]干线管道 | B1: [关联]支线管道 | C1: [原始]站场阀室 | D1: [计算]站场阀室 | E1: [原始]区域公司 | F1: [原始]作业区 | G1: [原始]里程,km | H1: [原始]站间距,km | I1: [原始]高程,m | J1: [原始]站间管容,方 | K1: [原始]累计管容,方 | L1: [原始]备注 | M1: [原始]支线管道简称 | N1: [原始]符号 ●跨接 ★监控阀室 ▲监视阀室 | O1: [原始]2024年类型 | P1: [原始]2025年类型 | Q1: [原始]地理位置
A2: 西气东输一线 | B2: 西一线干线新疆段 | C2: 轮南压气站 | D2: 轮南压气站● | E2: 西部管道 | F2: 轮南作业区 | G2: 0 | H2: 0 | I2: 930 | J2: 0 | K2: 0 | L2: 西一、轮吐合建 | M2: 西一 | N2: ● | O2: 压气站 | P2: 压气站 | Q2: 新疆维吾尔自治区巴音郭楞蒙古自治州轮台县轮南镇西南侧约1m
A3: 西气东输一线 | B3: 西一线干线新疆段 | C3: 西一1#阀室 | D3: 1#阀室★ | E3: 西部管道 | F3: 轮南作业区 | G3: 32.5005 | H3: =G3-G2 -> 32.5005 | I3: 924 | J3: 24800 | K3: 24800 | M3: 西一 | N3: ★ | O3: 监控阀室 | P3: 监控阀室 | Q3: 新疆维吾尔自治区巴音郭楞蒙古自治州轮台县阿克萨来乡
A4: 西气东输一线 | B4: 西一线干线新疆段 | C4: 西一2#阀室 | D4: 2#阀室★ | E4: 西部管道 | F4: 轮南作业区 | G4: 62.5294 | H4: =G4-G3 -> 30.0289 | I4: 910 | J4: 22914 | K4: 47714 | M4: 西一 | N4: ★ | O4: 监控阀室 | P4: 监控阀室 | Q4: 新疆维吾尔自治区巴音郭楞蒙古自治州轮台县
A5: 西气东输一线 | B5: 西一线干线新疆段 | C5: 西一3#阀室 | D5: 3#阀室★ | E5: 西部管道 | F5: 轮南作业区 | G5: 95.5411 | H5: =G5-G4 -> 33.0117 | I5: 901 | J5: 25190 | K5: 72904 | M5: 西一 | N5: ★ | O5: 监控阀室 | P5: 监控阀室 | Q5: 新疆维吾尔自治区巴音郭楞蒙古自治州轮台县
A6: 西气东输一线 | B6: 西一线干线新疆段 | C6: 西一4#阀室 | D6: 4#阀室★ | E6: 西部管道 | F6: 库尔勒作业区 | G6: 128.5829 | H6: =G6-G5 -> 33.0418 | I6: 925 | J6: 25213 | K6: 98117 | M6: 西一 | N6: ★ | O6: 监控阀室 | P6: 监控阀室 | Q6: 新疆维吾尔自治区巴音郭楞蒙古自治州库尔勒市
A7: 西气东输一线 | B7: 西一线干线新疆段 | C7: 西一5#阀室 | D7: 5#阀室★ | E7: 西部管道 | F7: 库尔勒作业区 | G7: 159.4256 | H7: =G7-G6 -> 30.8427 | I7: 983 | J7: 23535 | K7: 121652 | M7: 西一 | N7: ★ | O7: 监控阀室 | P7: 监控阀室 | Q7: 新疆维吾尔自治区巴音郭楞蒙古自治州库尔勒市上户镇
A8: 西气东输一线 | B8: 西一线干线新疆段 | C8: 孔雀河压气站 | D8: 孔雀河压气站● | E8: 西部管道 | F8: 库尔勒作业区 | G8: 178.5865 | H8: =G8-G7 -> 19.1609 | I8: 1078 | J8: 16070 | K8: 137722 | L8: 西一、轮吐合建、连通 | M8: 西一 | N8: ● | O8: 压气站 | P8: 压气站 | Q8: 新疆维吾尔自治区巴音郭楞蒙古自治州库尔勒市新城街道
A9: 西气东输一线 | B9: 西一线干线新疆段 | C9: 西一6#阀室 | D9: 6#阀室★ | E9: 西部管道 | F9: 库尔勒作业区 | G9: 205.8962 | H9: =G9-G8 -> 27.3097 | I9: 1091 | J9: 20839 | K9: 158561 | M9: 西一 | N9: ★ | O9: 监控阀室 | P9: 监控阀室 | Q9: 新疆维吾尔自治区巴音郭楞蒙古自治州博湖县博斯腾湖乡西南侧约25km
A10: 西气东输一线 | B10: 西一线干线新疆段 | C10: 西一7#阀室 | D10: 7#阀室★ | E10: 西部管道 | F10: 库尔勒作业区 | G10: 231.7165 | H10: =G10-G9 -> 25.8203 | I10: 1082 | J10: 19702 | K10: 178263 | M10: 西一 | N10: ★ | O10: 监控阀室 | P10: 监控阀室 | Q10: 新疆维吾尔自治区巴音郭楞蒙古自治州博湖县博斯腾湖乡东侧约6km
A11: 西气东输一线 | B11: 西一线干线新疆段 | C11: 西一8#阀室 | D11: 8#阀室★ | E11: 西部管道 | F11: 库尔勒作业区 | G11: 258.4479 | H11: =G11-G10 -> 26.7314 | I11: 1099 | J11: 20398 | K11: 198661 | M11: 西一 | N11: ★ | O11: 监控阀室 | P11: 监控阀室 | Q11: 新疆维吾尔自治区巴音郭楞蒙古自治州博湖县博斯腾湖乡东侧约38km
A12: 西气东输一线 | B12: 西一线干线新疆段 | C12: 西一9#阀室 | D12: 9#阀室★ | E12: 西部管道 | F12: 马兰作业区 | G12: 283.6799 | H12: =G12-G11 -> 25.232 | I12: 1051 | J12: 19253 | K12: 217914 | M12: 西一 | N12: ★ | O12: 监控阀室 | P12: 监控阀室 | Q12: 新疆维吾尔自治区巴音郭楞蒙古自治州和硕县乌什塔拉乡南侧6km
A13: 西气东输一线 | B13: 西一线干线新疆段 | C13: 四道班压气站 | D13: 四道班压气站 | E13: 西部管道 | F13: 马兰作业区 | G13: 315.9608 | H13: =G13-G12 -> 32.2809 | I13: 1164 | J13: 23664 | K13: 241578 | M13: 西一 | O13: 压气站 | P13: 压气站 | Q13: 新疆维吾尔自治区巴音郭楞蒙古自治州和硕县乌什塔拉乡南侧65km
A14: 西气东输一线 | B14: 西一线干线新疆段 | C14: 西一10#阀室 | D14: 10#阀室★ | E14: 西部管道 | F14: 库米什压气站 | G14: 347.4971 | H14: =G14-G13 -> 31.5363 | I14: 1336 | J14: 24064 | K14: 265642 | L14: 5#阀室 | M14: 西一 | N14: ★ | O14: 监控阀室 | P14: 监控阀室 | Q14: 新疆维吾尔自治区吐鲁番市托克逊县库米什镇
A15: 西气东输一线 | B15: 西一线干线新疆段 | C15: 西一11#阀室 | D15: 11#阀室★ | E15: 西部管道 | F15: 库米什压气站 | G15: 378.0201 | H15: =G15-G14 -> 30.523 | I15: 914 | J15: 23291 | K15: 288933 | M15: 西一 | N15: ★ | O15: 监控阀室 | P15: 监控阀室 | Q15: 新疆维吾尔自治区吐鲁番市托克逊县库米什镇西南侧43km
A16: 西气东输一线 | B16: 西一线干线新疆段 | C16: 西一11A#阀室 | D16: 11A#阀室★ | E16: 西部管道 | F16: 库米什压气站 | G16: 398.0201 | H16: =G16-G15 -> 20 | I16: - | J16: - | K16: - | M16: 西一 | N16: ★ | O16: 监控阀室 | P16: 监控阀室 | Q16: 新疆维吾尔自治区吐鲁番地区托克逊县
A17: 西气东输一线 | B17: 西一线干线新疆段 | C17: 西一12#阀室 | D17: 12#阀室★ | E17: 西部管道 | F17: 库米什压气站 | G17: 405.859 | H17: =G17-G16 -> 7.8389 | I17: 1352 | J17: 21243 | K17: 310176 | M17: 西一 | N17: ★ | O17: 监控阀室 | P17: 监控阀室 | Q17: 新疆维吾尔自治区吐鲁番市托克逊县库米什镇
A18: 西气东输一线 | B18: 西一线干线新疆段 | C18: 西一13#阀室 | D18: 13#阀室★ | E18: 西部管道 | F18: 库米什压气站 | G18: 435.7706 | H18: =G18-G17 -> 29.9116 | I18: 1363 | J18: 22824 | K18: 333000 | M18: 西一 | N18: ★ | O18: 监控阀室 | P18: 监控阀室 | Q18: 新疆维吾尔自治区吐鲁番市鄯善县迪坎乡
A19: 西气东输一线 | B19: 西一线干线新疆段 | C19: 西一14#阀室 | D19: 14#阀室★ | E19: 西部管道 | F19: 库米什压气站 | G19: 466.1453 | H19: =G19-G18 -> 30.3747 | I19: 960 | J19: 23178 | K19: 356178 | M19: 西一 | N19: ★ | O19: 监控阀室 | P19: 监控阀室 | Q19: 新疆维吾尔自治区吐鲁番市鄯善县迪坎乡
A20: 西气东输一线 | B20: 西一线干线新疆段 | C20: 鄯善压气站 | D20: 鄯善压气站 | E20: 西部管道 | F20: 库米什压气站 | G20: 494.5473 | H20: =G20-G19 -> 28.402 | I20: 815 | J20: 23672 | K20: 379850 | M20: 西一 | O20: 压气站 | P20: 压气站 | Q20: 新疆维吾尔自治区吐鲁番市鄯善县迪坎乡
A21: 西气东输一线 | B21: 西一线干线新疆段 | C21: 西一15#阀室 | D21: 15#阀室★ | E21: 西部管道 | F21: 库米什压气站 | G21: 525.2838 | H21: =G21-G20 -> 30.7365 | I21: 883 | J21: 23454 | K21: 403304 | M21: 西一 | N21: ★ | O21: 监控阀室 | P21: 监控阀室 | Q21: 新疆维吾尔自治区吐鲁番市鄯善县迪坎乡
A22: 西气东输一线 | B22: 西一线干线新疆段 | C22: 西一16#阀室 | D22: 16#阀室★ | E22: 西部管道 | F22: 库米什压气站 | G22: 552.4161 | H22: =G22-G21 -> 27.1323 | I22: 942 | J22: 20704 | K22: 424008 | M22: 西一 | N22: ★ | O22: 监控阀室 | P22: 监控阀室 | Q22: 新疆维吾尔自治区吐鲁番市鄯善县迪坎乡
A23: 西气东输一线 | B23: 西一线干线新疆段 | C23: 西一17#阀室 | D23: 17#阀室★ | E23: 西部管道 | F23: 库米什压气站 | G23: 583.6908 | H23: =G23-G22 -> 31.2747 | I23: 1040 | J23: 23864 | K23: 447872 | M23: 西一 | N23: ★ | O23: 监控阀室 | P23: 监控阀室 | Q23: 新疆维吾尔自治区吐鲁番市鄯善县迪坎乡
A24: 西气东输一线 | B24: 西一线干线新疆段 | C24: 西一18#阀室 | D24: 18#阀室★ | E24: 西部管道 | F24: 哈密压气站 | G24: 614.4744 | H24: =G24-G23 -> 30.7836 | I24: 1045 | J24: 23490 | K24: 471362 | M24: 西一 | N24: ★ | O24: 监控阀室 | P24: 监控阀室 | Q24: 新疆维吾尔自治区吐鲁番市鄯善县迪坎乡
A25: 西气东输一线 | B25: 西一线干线新疆段 | C25: 西一19#阀室 | D25: 19#阀室★ | E25: 西部管道 | F25: 哈密压气站 | G25: 645.242 | H25: =G25-G24 -> 30.7676 | I25: 1017 | J25: 23477 | K25: 494839 | M25: 西一 | N25: ★ | O25: 监控阀室 | P25: 监控阀室 | Q25: 新疆维吾尔自治区吐鲁番市鄯善县迪坎乡
A26: 西气东输一线 | B26: 西一线干线新疆段 | C26: 哈密压气站 | D26: 哈密压气站 | E26: 西部管道 | F26: 哈密压气站 | G26: 659.3964 | H26: =G26-G25 -> 14.1544 | I26: 1070 | J26: 13235 | K26: 508074 | M26: 西一 | O26: 压气站 | P26: 压气站 | Q26: 新疆维吾尔自治区吐鲁番市鄯善县迪坎乡
A27: 西气东输一线 | B27: 西一线干线新疆段 | C27: 西一20#阀室 | D27: 20#阀室★ | E27: 西部管道 | F27: 哈密压气站 | G27: 688.8259 | H27: =G27-G26 -> 29.4295 | I27: 1083 | J27: 22456 | K27: 530530 | M27: 西一 | N27: ★ | O27: 监控阀室 | P27: 监控阀室 | Q27: 新疆维吾尔自治区吐鲁番市鄯善县迪坎乡
A28: 西气东输一线 | B28: 西一线干线新疆段 | C28: 西一21#阀室 | D28: 21#阀室★ | E28: 西部管道 | F28: 哈密压气站 | G28: 718.7445 | H28: =G28-G27 -> 29.9186 | I28: 951 | J28: 22830 | K28: 553360 | M28: 西一 | N28: ★ | O28: 监控阀室 | P28: 监控阀室 | Q28: 新疆维吾尔自治区吐鲁番市鄯善县迪坎乡
A29: 西气东输一线 | B29: 西一线干线新疆段 | C29: 西一22#阀室 | D29: 22#阀室★ | E29: 西部管道 | F29: 哈密压气站 | G29: 760.9221 | H29: =G29-G28 -> 42.1776 | I29: 979 | J29: 32184 | K29: 585544 | M29: 西一 | N29: ★ | O29: 监控阀室 | P29: 监控阀室 | Q29: 新疆维吾尔自治区哈密市伊州区大南湖乡
A30: 西气东输一线 | B30: 西一线干线新疆段 | C30: 西一23#阀室 | D30: 23#阀室★ | E30: 西部管道 | F30: 哈密压气站 | G30: 793.3765 | H30: =G30-G29 -> 32.4544 | I30: 1035 | J30: 24765 | K30: 610309 | M30: 西一 | N30: ★ | O30: 监控阀室 | P30: 监控阀室 | Q30: 新疆维吾尔自治区哈密市伊州区大南湖乡
A31: 西气东输一线 | B31: 西一线干线新疆段 | C31: 雅满苏压气站 | D31: 雅满苏压气站 | E31: 西部管道 | F31: 雅满苏压气站 | G31: 824.2455 | H31: =G31-G30 -> 30.869 | I31: 969 | J31: 21996 | K31: 632305 | M31: 西一 | O31: 压气站 | P31: 压气站 | Q31: 新疆维吾尔自治区哈密市伊州区雅满苏镇
A32: 西气东输一线 | B32: 西一线干线新疆段 | C32: 西一25#阀室 | D32: 25#阀室★ | E32: 西部管道 | F32: 雅满苏压气站 | G32: 860.244 | H32: =G32-G31 -> 35.9985 | I32: 1028 | J32: 27469 | K32: 659774 | M32: 西一 | N32: ★ | O32: 监控阀室 | P32: 监控阀室 | Q32: 新疆维吾尔自治区哈密市伊州区雅满苏镇
A33: 西气东输一线 | B33: 西一线干线新疆段 | C33: 西一26#阀室 | D33: 26#阀室★ | E33: 西部管道 | F33: 雅满苏压气站 | G33: 892.2669 | H33: =G33-G32 -> 32.0229 | I33: 1046 | J33: 4058 | K33: 663832 | M33: 西一 | N33: ★ | O33: 监控阀室 | P33: 监控阀室 | Q33: 新疆维吾尔自治区哈密市伊州区雅满苏镇
A34: 西气东输一线 | B34: 西一线干线新疆段 | C34: 西一27#阀室 | D34: 27#阀室★ | E34: 西部管道 | F34: 雅满苏压气站 | G34: 923.5386 | H34: =G34-G33 -> 31.2717 | I34: 1297 | J34: 23862 | K34: 687694 | M34: 西一 | N34: ★ | O34: 监控阀室 | P34: 监控阀室 | Q34: 新疆维吾尔自治区哈密市伊州区雅满苏镇
A35: 西气东输一线 | B35: 西一线干线新疆段 | C35: 西一28#阀室 | D35: 28#阀室★ | E35: 西部管道 | F35: 烟墩作业区 | G35: 954.9577 | H35: =G35-G34 -> 31.4191 | I35: 1530 | J35: 23975 | K35: 711669 | M35: 西一 | N35: ★ | O35: 监控阀室 | P35: 监控阀室 | Q35: 新疆维吾尔自治区哈密市伊州区星星峡镇
A36: 西气东输一线 | B36: 西一线干线甘肃段 | C36: 红柳压气站 | D36: 红柳压气站● | E36: 甘肃公司 | F36: 红柳作业区 | G36: 961.6198 | H36: =G36-G35 -> 6.6621 | I36: 1627 | J36: 23779 | K36: 735448 | L36: 西一、西二、西三合建、连通 | M36: 西一 | N36: ● | O36: 压气站 | P36: 压气站 | Q36: 甘肃省酒泉市安西县柳园镇安西极旱荒漠自然保护区
A37: 西气东输一线 | B37: 西一线干线甘肃段 | C37: 西一29#阀室 | D37: 29#阀室★ | E37: 甘肃公司 | F37: 红柳作业区 | G37: 995.5445 | H37: =G37-G36 -> 33.9247 | I37: 1770 | J37: 25913 | K37: 761361 | M37: 西一 | N37: ★ | O37: 监控阀室 | P37: 监控阀室 | Q37: 甘肃省酒泉市安西县柳园镇安西极旱荒漠自然保护区
A38: 西气东输一线 | B38: 西一线干线甘肃段 | C38: 西一30#阀室 | D38: 30#阀室★ | E38: 甘肃公司 | F38: 红柳作业区 | G38: 1025.5133 | H38: =G38-G37 -> 29.9688 | I38: 1768 | J38: 22892 | K38: 784253 | M38: 西一 | N38: ★ | O38: 监控阀室 | P38: 监控阀室 | Q38: 甘肃省酒泉市安西县柳园镇戈壁滩
A39: 西气东输一线 | B39: 西一线干线甘肃段 | C39: 西一31#阀室 | D39: 31#阀室★ | E39: 甘肃公司 | F39: 红柳作业区 | G39: 1057.029 | H39: =G39-G38 -> 31.5157 | I39: 1649 | J39: 24073 | K39: 808326 | M39: 西一 | N39: ★ | O39: 监控阀室 | P39: 监控阀室 | Q39: 甘肃省酒泉市安西县柳园镇戈壁滩
A40: 西气东输一线 | B40: 西一线干线甘肃段 | C40: 西一32#阀室 | D40: 32#阀室★ | E40: 甘肃公司 | F40: 瓜州作业区 | G40: 1087.6116 | H40: =G40-G39 -> 30.5826 | I40: 1539 | J40: 23360 | K40: 831686 | M40: 西一 | N40: ★ | O40: 监控阀室 | P40: 监控阀室 | Q40: 甘肃省酒泉市瓜州县戈壁滩
A41: 西气东输一线 | B41: 西一线干线甘肃段 | C41: 柳园压气站 | D41: 柳园压气站 | E41: 甘肃公司 | F41: 瓜州作业区 | G41: 1119.4368 | H41: =G41-G40 -> 31.8252 | I41: 1416 | J41: 24532 | K41: 856218 | M41: 西一 | O41: 压气站 | P41: 压气站 | Q41: 甘肃省酒泉市瓜州县布隆吉乡
A42: 西气东输一线 | B42: 西一线干线甘肃段 | C42: 西一33#阀室 | D42: 33#阀室★ | E42: 甘肃公司 | F42: 瓜州作业区 | G42: 1144.5195 | H42: =G42-G41 -> 25.0827 | I42: 1358 | J42: 18935 | K42: 875153 | M42: 西一 | N42: ★ | O42: 监控阀室 | P42: 监控阀室 | Q42: 甘肃省酒泉市瓜州县腰站子乡9组
A43: 西气东输一线 | B43: 西一线干线甘肃段 | C43: 西一34#阀室 | D43: 34#阀室★ | E43: 甘肃公司 | F43: 玉门作业区 | G43: 1174.4132 | H43: =G43-G42 -> 29.8937 | I43: 1474 | J43: 22834 | K43: 897987 | M43: 西一 | N43: ★ | O43: 监控阀室 | P43: 监控阀室 | Q43: 甘肃省酒泉市玉门市柳河乡向南5公里
A44: 西气东输一线 | B44: 西一线干线甘肃段 | C44: 西一35#阀室 | D44: 35#阀室★ | E44: 甘肃公司 | F44: 玉门作业区 | G44: 1195.3798 | H44: =G44-G43 -> 20.9666 | I44: 1536 | J44: 16015 | K44: 914002 | M44: 西一 | N44: ★ | O44: 监控阀室 | P44: 监控阀室 | Q44: 甘肃省酒泉市玉门市下西号代家滩村东侧1公里处
A45: 西气东输一线 | B45: 西一线干线甘肃段 | C45: 西一36#阀室 | D45: 36#阀室★ | E45: 甘肃公司 | F45: 玉门作业区 | G45: 1223.312 | H45: =G45-G44 -> 27.9322 | I45: 1583 | J45: 21510 | K45: 935512 | M45: 西一 | N45: ★ | O45: 监控阀室 | P45: 监控阀室 | Q45: 甘肃省酒泉市玉门市银达乡低窝铺
A46: 西气东输一线 | B46: 西一线干线甘肃段 | C46: 西一37#阀室 | D46: 37#阀室★ | E46: 甘肃公司 | F46: 玉门作业区 | G46: 1247.3234 | H46: =G46-G45 -> 24.0114 | I46: 1736 | J46: 18274 | K46: 953786 | M46: 西一 | N46: ★ | O46: 监控阀室 | P46: 监控阀室 | Q46: 甘肃省酒泉市玉门市赤金镇东湖村
A47: 西气东输一线 | B47: 西一线干线甘肃段 | C47: 玉门压气站 | D47: 玉门压气站 | E47: 甘肃公司 | F47: 酒泉作业区 | G47: 1276.59 | H47: =G47-G46 -> 29.2666 | I47: 1867 | J47: 20738 | K47: 974524 | M47: 西一 | O47: 压气站 | P47: 压气站 | Q47: 甘肃省酒泉市玉门市清泉乡新民堡村
A48: 西气东输一线 | B48: 西一线干线甘肃段 | C48: 西一38#阀室 | D48: 38#阀室★ | E48: 甘肃公司 | F48: 酒泉作业区 | G48: 1300.6421 | H48: =G48-G47 -> 24.0521 | I48: 1770 | J48: 18305 | K48: 992829 | M48: 西一 | N48: ★ | O48: 监控阀室 | P48: 监控阀室 | Q48: 甘肃省嘉峪关市黑山湖戈壁滩
A49: 西气东输一线 | B49: 西一线干线甘肃段 | C49: 西一39#阀室 | D49: 39#阀室★ | E49: 甘肃公司 | F49: 酒泉作业区 | G49: 1325.8184 | H49: =G49-G48 -> 25.1763 | I49: 1585 | J49: 19161 | K49: 1011990 | M49: 西一 | N49: ★ | O49: 监控阀室 | P49: 监控阀室 | Q49: 甘肃省嘉峪关市文殊镇
A50: 西气东输一线 | B50: 西一线干线甘肃段 | C50: 西一40#阀室 | D50: 40#阀室★ | E50: 甘肃公司 | F50: 酒泉作业区 | G50: 1352.5837 | H50: =G50-G49 -> 26.7653 | I50: 1501 | J50: 20612 | K50: 1032602 | M50: 西一 | N50: ★ | O50: 监控阀室 | P50: 监控阀室 | Q50: 甘肃省酒泉市肃州区上坝镇新上村
A51: 西气东输一线 | B51: 西一线干线甘肃段 | C51: 西一41#阀室 | D51: 41#阀室★ | E51: 甘肃公司 | F51: 酒泉作业区 | G51: 1382.9014 | H51: =G51-G50 -> 30.3177 | I51: 1644 | J51: 23347 | K51: 1055949 | M51: 西一 | N51: ★ | O51: 监控阀室 | P51: 监控阀室 | Q51: 甘肃省酒泉市肃州区丰乐乡三坝村
A52: 西气东输一线 | B52: 西一线干线甘肃段 | C52: 西一42#阀室 | D52: 42#阀室★ | E52: 甘肃公司 | F52: 酒泉作业区 | G52: 1407.5662 | H52: =G52-G51 -> 24.6648 | I52: 1653 | J52: 18994 | K52: 1074943 | M52: 西一 | N52: ★ | O52: 监控阀室 | P52: 监控阀室 | Q52: 甘肃省酒泉市肃州区清水镇沙山村
A53: 西气东输一线 | B53: 西一线干线甘肃段 | C53: 西一43#阀室 | D53: 43#阀室★ | E53: 甘肃公司 | F53: 张掖作业区 | G53: 1438.1382 | H53: =G53-G52 -> 30.572 | I53: 1513 | J53: 23543 | K53: 1098486 | M53: 西一 | N53: ★ | O53: 监控阀室 | P53: 监控阀室 | Q53: 甘肃省张掖市高台县骆驼城乡戈壁滩
A54: 西气东输一线 | B54: 西一线干线甘肃段 | C54: 酒泉压气站 | D54: 酒泉压气站 | E54: 甘肃公司 | F54: 张掖作业区 | G54: 1467.1574 | H54: =G54-G53 -> 29.0192 | I54: 1437 | J54: 21806 | K54: 1120292 | M54: 西一 | O54: 压气站 | P54: 压气站 | Q54: 甘肃省张掖市临泽县新华镇明泉村
A55: 西气东输一线 | B55: 西一线干线甘肃段 | C55: 西一44#阀室 | D55: 44#阀室★ | E55: 甘肃公司 | F55: 张掖作业区 | G55: 1490.8222 | H55: =G55-G54 -> 23.6648 | I55: 1434 | J55: 18010 | K55: 1138302 | M55: 西一 | N55: ★ | O55: 监控阀室 | P55: 监控阀室 | Q55: 甘肃省张掖市临泽县沙河镇何家庄村
A56: 西气东输一线 | B56: 西一线干线甘肃段 | C56: 西一45#阀室 | D56: 45#阀室★ | E56: 甘肃公司 | F56: 张掖作业区 | G56: 1513.7232 | H56: =G56-G55 -> 22.901 | I56: 1457 | J56: 17429 | K56: 1155731 | M56: 西一 | N56: ★ | O56: 监控阀室 | P56: 监控阀室 | Q56: 甘肃省张掖市甘州区乌江镇平原堡
A57: 西气东输一线 | B57: 西一线干线甘肃段 | C57: 西一46#阀室 | D57: 46#阀室★ | E57: 甘肃公司 | F57: 张掖作业区 | G57: 1536.8368 | H57: =G57-G56 -> 23.1136 | I57: 1471 | J57: 17591 | K57: 1173322 | M57: 西一 | N57: ★ | O57: 监控阀室 | P57: 监控阀室 | Q57: 甘肃省张掖市甘州区三闸镇东王堡村
A58: 西气东输一线 | B58: 西一线干线甘肃段 | C58: 西一47#阀室 | D58: 47#阀室★ | E58: 甘肃公司 | F58: 山丹作业区 | G58: 1559.856 | H58: =G58-G57 -> 23.0192 | I58: 1627 | J58: 17519 | K58: 1190841 | M58: 西一 | N58: ★ | O58: 监控阀室 | P58: 监控阀室 | Q58: 甘肃省张掖市山丹县东乐乡西屯村北侧约1km处
A59: 西气东输一线 | B59: 西一线干线甘肃段 | C59: 西一48#阀室 | D59: 48#阀室★ | E59: 甘肃公司 | F59: 山丹作业区 | G59: 1588.311 | H59: =G59-G58 -> 28.455 | I59: 1772 | J59: 21656 | K59: 1212497 | M59: 西一 | N59: ★ | O59: 监控阀室 | P59: 监控阀室 | Q59: 甘肃省张掖市山丹县清泉镇南湾村山平公路东侧2m
A60: 西气东输一线 | B60: 西一线干线甘肃段 | C60: 山丹压气站 | D60: 山丹压气站 | E60: 甘肃公司 | F60: 山丹作业区 | G60: 1610.083 | H60: =G60-G59 -> 21.772 | I60: 1920 | J60: 17282 | K60: 1229779 | M60: 西一 | O60: 压气站 | P60: 压气站 | Q60: 甘肃省张掖市山丹县陈户镇东门村山丹压气站
A61: 西气东输一线 | B61: 西一线干线甘肃段 | C61: 西一49#阀室 | D61: 49#阀室★ | E61: 甘肃公司 | F61: 山丹作业区 | G61: 1642.0544 | H61: =G61-G60 -> 31.9714 | I61: 2593 | J61: 24621 | K61: 1254400 | M61: 西一 | N61: ★ | O61: 监控阀室 | P61: 监控阀室 | Q61: 甘肃省张掖市山丹县老军乡牧场区内
A62: 西气东输一线 | B62: 西一线干线甘肃段 | C62: 西一50#阀室 | D62: 50#阀室★ | E62: 甘肃公司 | F62: 永昌作业区 | G62: 1667.1571 | H62: =G62-G61 -> 25.1027 | I62: 2177 | J62: 19331 | K62: 1273731 | M62: 西一 | N62: ★ | O62: 监控阀室 | P62: 监控阀室 | Q62: 甘肃省金昌市永昌县红山窑乡马家坪村六组
A63: 西气东输一线 | B63: 西一线干线甘肃段 | C63: 西一51#阀室 | D63: 51#阀室★ | E63: 甘肃公司 | F63: 永昌作业区 | G63: 1689.1253 | H63: =G63-G62 -> 21.9682 | I63: 2027 | J63: 16651 | K63: 1290382 | M63: 西一 | N63: ★ | O63: 监控阀室 | P63: 监控阀室 | Q63: 甘肃省金昌市永昌县永昌盐场门口2m处
A64: 西气东输一线 | B64: 西一线干线甘肃段 | C64: 金昌压气站 | D64: 金昌压气站 | E64: 甘肃公司 | F64: 永昌作业区 | G64: 1719.0686 | H64: =G64-G63 -> 29.9433 | I64: 1842 | J64: 21222 | K64: 1311604 | M64: 西一 | O64: 压气站 | P64: 压气站 | Q64: 甘肃省金昌市永昌县六坝乡南庄
A65: 西气东输一线 | B65: 西一线干线甘肃段 | C65: 西一53#阀室 | D65: 53#阀室★ | E65: 甘肃公司 | F65: 永昌作业区 | G65: 1751.9426 | H65: =G65-G64 -> 32.874 | I65: 1643 | J65: 22258 | K65: 1333862 | M65: 西一 | N65: ★ | O65: 监控阀室 | P65: 监控阀室 | Q65: 甘肃省武威市凉州区怀安乡三中村
A66: 西气东输一线 | B66: 西一线干线甘肃段 | C66: 西一54#阀室 | D66: 54#阀室★ | E66: 甘肃公司 | F66: 永昌作业区 | G66: 1781.189 | H66: =G66-G65 -> 29.2464 | I66: 1651 | J66: 25316 | K66: 1359178 | M66: 西一 | N66: ★ | O66: 监控阀室 | P66: 监控阀室 | Q66: 甘肃省武威市凉州区武南镇大河滩沙头坝村
A67: 西气东输一线 | B67: 西一线干线甘肃段 | C67: 古浪分输站 | D67: 古浪分输站 | E67: 甘肃公司 | F67: 古浪作业区 | G67: 1812.911 | H67: =G67-G66 -> 31.722 | I67: 1715 | J67: 24143 | K67: 1383321 | M67: 西一 | O67: 监控阀室 | P67: 分输站 | Q67: 甘肃省武威市古浪县土门镇新胜村
A68: 西气东输一线 | B68: 西一线干线甘肃段 | C68: 古浪压气站 | D68: 古浪压气站 | E68: 甘肃公司 | F68: 古浪作业区 | G68: 1841.5762 | H68: =G68-G67 -> 28.6652 | I68: 1856 | J68: 23966 | K68: 1407287 | M68: 西一 | O68: 压气站 | P68: 压气站 | Q68: 甘肃省武威市古浪县大靖镇李家湾村
A69: 西气东输一线 | B69: 西一线干线甘肃段 | C69: 西一56#阀室 | D69: 56#阀室★ | E69: 甘肃公司 | F69: 古浪作业区 | G69: 1873.1322 | H69: =G69-G68 -> 31.556 | I69: 2135 | J69: 24614 | K69: 1431901 | M69: 西一 | N69: ★ | O69: 监控阀室 | P69: 监控阀室 | Q69: 甘肃省武威市古浪县直滩乡大岭村
A70: 西气东输一线 | B70: 西一线干线甘肃段 | C70: 西一57#阀室 | D70: 57#阀室★ | E70: 甘肃公司 | F70: 古浪作业区 | G70: 1902.4369 | H70: =G70-G69 -> 29.3047 | I70: 1558 | J70: 22567 | K70: 1454468 | M70: 西一 | N70: ★ | O70: 监控阀室 | P70: 监控阀室 | Q70: 甘肃省白银市景泰县上沙沃镇白墩子村
A71: 西气东输一线 | B71: 西一线干线甘肃段 | C71: 西一58#阀室 | D71: 58#阀室★ | E71: 甘肃公司 | F71: 古浪作业区 | G71: 1921.0039 | H71: =G71-G70 -> 18.567 | I71: 1681 | J71: 14298 | K71: 1468766 | M71: 西一 | N71: ★ | O71: 监控阀室 | P71: 监控阀室 | Q71: 甘肃省白银市景泰县上沙沃镇白墩子村
A72: 西气东输一线 | B72: 西一线干线甘肃段 | C72: 西一59#阀室 | D72: 59#阀室★ | E72: 西北公司 | F72: 甘塘作业区 | G72: 1932.3321 | H72: =G72-G71 -> 11.3282 | I72: 1682 | J72: 9238 | K72: 1478004 | M72: 西一 | N72: ★ | O72: 监控阀室 | P72: 监控阀室 | Q72: 宁夏回族自治区中卫市沙坡头区甘塘镇
A73: 西气东输一线 | B73: 西一线干线甘肃段 | C73: 西一60#阀室 | D73: 60#阀室★ | E73: 西北公司 | F73: 甘塘作业区 | G73: 1957.3368 | H73: =G73-G72 -> 25.0047 | I73: 1699 | J73: 19789.547 | K73: =K72+J73 -> 1497793.5 | M73: 西一 | N73: ★ | O73: 监控阀室 | P73: 监控阀室 | Q73: 宁夏回族自治区中卫市沙坡头区甘塘镇
A74: 西气东输一线 | B74: 西一线干线甘肃段 | C74: 西一61#阀室 | D74: 61#阀室★ | E74: 西北公司 | F74: 甘塘作业区 | G74: 1967.0717 | H74: =G74-G73 -> 9.7349 | I74: 1599 | J74: 9403.0153 | K74: =K73+J74 -> 1507196.6 | M74: 西一 | N74: ★ | O74: 监控阀室 | P74: 监控阀室 | Q74: 宁夏回族自治区中卫市沙坡头区孟家湾乡
A75: 西气东输一线 | B75: 西一线干线甘肃段 | C75: 西一62#阀室 | D75: 62#阀室★ | E75: 西北公司 | F75: 甘塘作业区 | G75: 1981.9018 | H75: =G75-G74 -> 14.8301 | I75: 1248 | J75: 13240.22 | K75: =K74+J75 -> 1520436.8 | M75: 西一 | N75: ★ | O75: 监控阀室 | P75: 监控阀室 | Q75: 宁夏回族自治区中卫市沙坡头区孟家湾乡
A76: 西气东输一线 | B76: 西一线干线甘肃段 | C76: 西一63#阀室 | D76: 63#阀室★ | E76: 西北公司 | F76: 中卫压气站 | G76: 1983.9016 | H76: =G76-G75 -> 1.9998 | I76: 1341 | J76: 1874.2698 | K76: =K75+J76 -> 1522311.1 | M76: 西一 | N76: ★ | O76: 监控阀室 | P76: 监控阀室 | Q76: 宁夏回族自治区中卫市沙坡头区常乐镇
A77: 西气东输一线 | B77: 西一线干线东段 | C77: 中卫压气站 | D77: 中卫压气站● | E77: 西北公司 | F77: 中卫压气站 | G77: 2008.2399 | H77: =G77-G76 -> 24.3383 | I77: 1247 | J77: 8948.8839 | K77: =K76+J77 -> 1531259.9 | L77: 西一、西二、西三、中贵、中靖合建、连通 | M77: 西一 | N77: ● | O77: 压气站 | P77: 压气站 | Q77: 宁夏回族自治区中卫市沙坡头区常乐镇
A78: 西气东输一线 | B78: 西一线干线东段 | C78: 西一64#阀室 | D78: 64#阀室★ | E78: 西北公司 | F78: 中卫压气站 | G78: 2020.991 | H78: =G78-G77 -> 12.7511 | I78: 1215 | J78: 9459.2695 | K78: =K77+J78 -> 1540719.2 | M78: 西一 | N78: ★ | O78: 监控阀室 | P78: 监控阀室 | Q78: 宁夏回族自治区中卫市沙坡头区永康镇
A79: 西气东输一线 | B79: 西一线干线东段 | C79: 西一65#阀室 | D79: 65#阀室★ | E79: 西北公司 | F79: 中卫压气站 | G79: 2036.4441 | H79: =G79-G78 -> 15.4531 | I79: 1199 | J79: 12722.757 | K79: =K78+J79 -> 1553442 | M79: 西一 | N79: ★ | O79: 监控阀室 | P79: 监控阀室 | Q79: 宁夏回族自治区中卫市沙坡头区宣和镇
A80: 西气东输一线 | B80: 西一线干线东段 | C80: 西一66#阀室 | D80: 66#阀室★ | E80: 西北公司 | F80: 中卫压气站 | G80: 2054.4698 | H80: =G80-G79 -> 18.0257 | I80: 1189 | J80: 11845.042 | K80: =K79+J80 -> 1565287 | M80: 西一 | N80: ★ | O80: 监控阀室 | P80: 监控阀室 | Q80: 宁夏回族自治区中卫市中宁县宁安镇古城村
A81: 西气东输一线 | B81: 西一线干线东段 | C81: 西一67#阀室 | D81: 67#阀室★ | E81: 西北公司 | F81: 中卫压气站 | G81: 2071.0733 | H81: =G81-G80 -> 16.6035 | I81: 1266 | J81: 12667.277 | K81: =K80+J81 -> 1577954.3 | M81: 西一 | N81: ★ | O81: 监控阀室 | P81: 监控阀室 | Q81: 宁夏回族自治区中卫市中宁县新堡乡
A82: 西气东输一线 | B82: 西一线干线东段 | C82: 西一68#阀室 | D82: 68#阀室★ | E82: 西北公司 | F82: 盐池作业区 | G82: 2091.0727 | H82: =G82-G81 -> 19.9994 | I82: 1340 | J82: 14235.19 | K82: =K81+J82 -> 1592189.5 | M82: 西一 | N82: ★ | O82: 监控阀室 | P82: 监控阀室 | Q82: 宁夏回族自治区吴忠市红寺堡区开发区
A83: 西气东输一线 | B83: 西一线干线东段 | C83: 西一69#阀室 | D83: 69#阀室★ | E83: 西北公司 | F83: 盐池作业区 | G83: 2111.965 | H83: =G83-G82 -> 20.8923 | I83: 1337 | J83: 14825.892 | K83: =K82+J83 -> 1607015.4 | M83: 西一 | N83: ★ | O83: 监控阀室 | P83: 监控阀室 | Q83: 宁夏回族自治区吴忠市红寺堡区开发区红塔村
A84: 西气东输一线 | B84: 西一线干线东段 | C84: 西一70#阀室 | D84: 70#阀室★ | E84: 西北公司 | F84: 盐池作业区 | G84: 2113.8639 | H84: =G84-G83 -> 1.8989 | I84: 1342 | J84: 2144.0297 | K84: =K83+J84 -> 1609159.4 | M84: 西一 | N84: ★ | O84: 监控阀室 | P84: 监控阀室 | Q84: 宁夏回族自治区吴忠市红寺堡区开发区红塔村
A85: 西气东输一线 | B85: 西一线干线东段 | C85: 西一71#阀室 | D85: 71#阀室★ | E85: 西北公司 | F85: 盐池作业区 | G85: 2143.5286 | H85: =G85-G84 -> 29.6647 | I85: 1339 | J85: 20258.892 | K85: =K84+J85 -> 1629418.3 | M85: 西一 | N85: ★ | O85: 监控阀室 | P85: 监控阀室 | Q85: 宁夏回族自治区吴忠市盐池县惠安堡镇
A86: 西气东输一线 | B86: 西一线干线东段 | C86: 西一72#阀室 | D86: 72#阀室★ | E86: 西北公司 | F86: 盐池作业区 | G86: 2175.7044 | H86: =G86-G85 -> 32.1758 | I86: 1555 | J86: 23803.677 | K86: =K85+J86 -> 1653222 | M86: 西一 | N86: ★ | O86: 监控阀室 | P86: 监控阀室 | Q86: 宁夏回族自治区吴忠市盐池县大水坑镇
A87: 西气东输一线 | B87: 西一线干线东段 | C87: 西一盐池压气站 | D87: 盐池压气站● | E87: 西北公司 | F87: 盐池作业区 | G87: 2190.506 | H87: =G87-G86 -> 14.8016 | I87: 1536 | J87: 11232.36 | K87: =K86+J87 -> 1664454.3 | M87: 西一 | N87: ● | O87: 压气站 | P87: 压气站 | Q87: 宁夏回族自治区吴忠市盐池县大水坑镇红井子村
A88: 西气东输一线 | B88: 西一线干线东段 | C88: 西一73#阀室 | D88: 73#阀室★ | E88: 西北公司 | F88: 靖边作业区 | G88: 2219.906 | H88: =G88-G87 -> 29.4 | I88: 1416 | J88: 22366.883 | K88: =K87+J88 -> 1686821.2 | M88: 西一 | N88: ★ | O88: 监控阀室 | P88: 监控阀室 | Q88: 陕西省榆林市定边县贺圈镇红庄村
A89: 西气东输一线 | B89: 西一线干线东段 | C89: 西一74#阀室 | D89: 74#阀室★ | E89: 西北公司 | F89: 靖边作业区 | G89: 2244.0381 | H89: =G89-G88 -> 24.1321 | I89: 1418 | J89: 18133.266 | K89: =K88+J89 -> 1704954.5 | M89: 西一 | N89: ★ | O89: 监控阀室 | P89: 监控阀室 | Q89: 陕西省榆林市定边县贺圈镇石井子村
... A92: 西气东输一线 | B92: 西一线干线东段 | C92: 西一77#阀室 | D92: 77#阀室★ | E92: 西北公司 | F92: 靖边作业区 | G92: 2318.586 | H92: =G92-G91 -> 20.3625 | I92: 1350 | J92: 15324.002 | K92: =K91+J92 -> 1761097.9 | M92: 西一 | N92: ★ | O92: 监控阀室 | P92: 监控阀室 | Q92: 陕西省榆林市靖边县东坑镇硬地梁村
A93: 西气东输一线 | B93: 西一线干线东段 | C93: 西一靖边压气站 | D93: 靖边压气站● | E93: 西北公司 | F93: 靖边作业区 | G93: 2343.806 | H93: =G93-G92 -> 25.22 | I93: 1327 | J93: 18992.559 | K93: =K92+J93 -> 1780090.5 | L93: 西一、西二中靖、西三中靖合建、连通 | M93: 西一 | N93: ● | O93: 压气站 | P93: 压气站 | Q93: 陕西省榆林市靖边县张家畔镇胡伙场村
A94: 西气东输一线 | B94: 西一线干线东段 | C94: 西一78#阀室 | D94: 78#阀室★ | E94: 西北公司 | F94: 靖边作业区 | G94: 2349.6473 | H94: =G94-G93 -> 5.8413 | I94: 1331 | J94: 4464.1501 | K94: =K93+J94 -> 1784554.6 | M94: 西一 | N94: ★ | O94: 监控阀室 | P94: 监控阀室 | Q94: 陕西省榆林市靖边县张家畔镇新房滩村
A95: 西气东输一线 | B95: 西一线干线东段 | C95: 西一79#阀室 | D95: 79#阀室★ | E95: 西北公司 | F95: 靖边作业区 | G95: 2373.0528 | H95: =G95-G94 -> 23.4055 | I95: 1519 | J95: 17870.298 | K95: =K94+J95 -> 1802424.9 | M95: 西一 | N95: ★ | O95: 监控阀室 | P95: 监控阀室 | Q95: 陕西省榆林市靖边县乔沟湾乡乔沟湾村
A96: 西气东输一线 | B96: 西一线干线东段 | C96: 西一80#阀室 | D96: 80#阀室★ | E96: 西北公司 | F96: 靖边作业区 | G96: 2402.869 | H96: =G96-G95 -> 29.8162 | I96: 1171 | J96: 22772.689 | K96: =K95+J96 -> 1825197.6 | M96: 西一 | N96: ★ | O96: 监控阀室 | P96: 监控阀室 | Q96: 陕西省榆林市靖边县青阳岔镇阳平村
A97: 西气东输一线 | B97: 西一线干线东段 | C97: 西一81#阀室 | D97: 81#阀室★ | E97: 西北公司 | F97: 延川作业区 | G97: 2430.8451 | H97: =G97-G96 -> 27.9761 | I97: 1205 | J97: 21391.34 | K97: =K96+J97 -> 1846588.9 | M97: 西一 | N97: ★ | O97: 监控阀室 | P97: 监控阀室 | Q97: 陕西省延安市子长市李家岔镇李家岔村
A98: 西气东输一线 | B98: 西一线干线东段 | C98: 西一82#阀室 | D98: 82#阀室★ | E98: 西北公司 | F98: 延川作业区 | G98: 2454.488 | M98: 西一 | N98: ★ | O98: 监控阀室 | P98: 监控阀室 | Q98: 陕西省延安市子长县栾家坪乡桃园村
A99: 西气东输一线 | B99: 西一线干线东段 | C99: 子长分输站 | D99: 子长分输站 | E99: 西北公司 | F99: 延川作业区 | G99: 2454.488 | H99: =G99-G97 -> 23.6429 | I99: 1063 | J99: 18037.936 | K99: =K97+J99 -> 1864626.9 | L99: 原82#阀室 | M99: 西一 | O99: 分输站 | P99: 分输站 | Q99: 陕西省延安市子长县栾家坪乡桃园村
A100: 西气东输一线 | B100: 西一线干线东段 | C100: 西一83#阀室 | D100: 83#阀室★ | E100: 西北公司 | F100: 延川作业区 | G100: 2478.2994 | H100: =G100-G99 -> 23.8114 | I100: 971 | J100: 18114.652 | K100: =K99+J100 -> 1882741.5 | M100: 西一 | N100: ★ | O100: 监控阀室 | P100: 监控阀室 | Q100: 陕西省延安市延川县永坪镇永坪村
A101: 西气东输一线 | B101: 西一线干线东段 | C101: 延川压气站 | D101: 延川压气站 | E101: 西北公司 | F101: 延川作业区 | G101: 2494.007 | H101: =G101-G100 -> 15.7076 | I101: 896 | J101: 11944.048 | K101: =K100+J101 -> 1894685.6 | M101: 西一 | O101: 压气站 | P101: 压气站 | Q101: 陕西省延安市延川县冯家坪乡寺村
A102: 西气东输一线 | B102: 西一线干线东段 | C102: 西一84#阀室 | D102: 84#阀室★ | E102: 西北公司 | F102: 延川作业区 | G102: 2513.3548 | H102: =G102-G101 -> 19.3478 | I102: 798 | J102: 14869.589 | K102: =K101+J102 -> 1909555.2 | M102: 西一 | N102: ★ | O102: 监控阀室 | P102: 监控阀室 | Q102: 陕西省延安市延川县延川镇杨家圪崂村
...

Sheet 分输口
A1: [关联] 干线管道 | B1: [原始] 分输口 | C1: [原始] 自动分输 | D1: [原始]站场/阀室/干线开口 | E1: [关联]站场简称 | F1: 备注 | G1: [关联]调度台 | H1: 站场计量设备情况 | I1: 站场调压设备情况 | J1: 用户合同接气压力 MPa | K1: 投产时间
A2: 西气东输二线 | B2: 新捷伊犁<伊宁> | C2: 五期 | D2: 站场 | E2: 伊宁首 | G2: 西部 | H2: 1用1备 | I2: 1用1备 | J2: 3.8-10
A3: 西气东输二线 | B3: 新捷伊犁<霍尔果斯> | C3: 二期 | D3: 站场 | E3: 霍尔果斯 | G3: 西部 | H3: 1用1备 | I3: 1用1备 | J3: 干线压力
A4: 西气东输二线 | B4: 兵团燃气（喀什）<霍尔果斯> | C4: 二期 | D4: 站场 | E4: 霍尔果斯 | G4: 西部 | H4: 1用1备 | I4: 1用1备 | J4: 干线压力
A5: 西气东输二线 | B5: 新捷博乐<精河> | C5: 二期 | D5: 站场 | E5: 精河 | G5: 西部 | H5: 1用1备 | I5: 1用1备 | J5: 干线压力
A6: 西气东输二线 | B6: 新捷博乐<西二9#> | C6: 2024年已报 | D6: 阀室 | E6: 西二9# | G6: 西部 | J6: 5.5-11.0
A7: 西气东输二线 | B7: 乌苏宏江<乌苏> | C7: 三期 | D7: 站场 | E7: 乌苏 | G7: 西部 | H7: 1用1备 | J7: 干线压力
A8: 西气东输二线 | B8: 玛纳斯新捷<玛纳斯> | C8: 二期 | D8: 站场 | E8: 玛纳斯 | G8: 西部 | H8: 1用1备 | I8: 1用1备 | J8: 干线压力
A9: 西气东输三线 | B9: 天富天源（西三线）<石河子> | C9: 二期 | D9: 站场 | E9: 石河子 | G9: 西部 | H9: 1用1备 | I9: 1用1备 | J9: 干线压力
A10: 西气东输二线 | B10: 独山子石化(西二线)<奎屯> | C10: 二期 | D10: 站场 | E10: 奎屯 | G10: 西部 | H10: 1用1备 | I10: 1用1备 | J10: 干线压力
A11: 西气东输二线 | B11: 奎屯德信<奎屯> | C11: 二期 | D11: 站场 | E11: 奎屯 | G11: 西部 | H11: 1用1备 | I11: 1用1备 | J11: 干线压力
A12: 西气东输二线 | B12: 奎屯非创<奎屯> | C12: 二期 | D12: 站场 | E12: 奎屯 | G12: 西部 | H12: 1用1备 | I12: 1用1备 | J12: 干线压力
A13: 西气东输二线 | B13: 奎屯新捷<奎屯> | C13: 四期 | D13: 站场 | E13: 奎屯 | G13: 西部 | H13: 1用1备 | I13: 1用1备 | J13: 干线压力
A14: 西气东输二线 | B14: 沙湾东升<西二14#> | C14: 四期 | D14: 阀室 | E14: 西二14# | G14: 西部 | H14: 1用1备 | I14: 1用1备 | J14: 干线压力
A15: 西气东输二线 | B15: 鑫泰燃气公司(米泉)<乌石化> | C15: 一期 | D15: 站场 | E15: 乌石化 | G15: 西部 | H15: 1用1备 | I15: 1用1备 | J15: 干线压力
A16: 西气东输二线 | B16: 新疆油田<乌石化> | C16: 一期 | D16: 站场 | E16: 乌石化 | G16: 西部 | H16: 无 | I16: 1用1备 | J16: 4.5-9.0
A17: 西气东输二线 | B17: 乌石化(西二线)<乌石化> | C17: 一期 | D17: 站场 | E17: 乌石化 | G17: 西部 | H17: 1用1备 | I17: 1用1备 | J17: 干线压力
A18: 西气东输二线 | B18: 新捷燃气<西二19#> | C18: 2024年已报 | D18: 阀室 | E18: 西二19# | G18: 西部 | H18: 2用1备 | I18: 1用1备 | J18: 7-11.6
A19: 西气东输二线 | B19: 昊通百圣<昌吉> | C19: 二期 | D19: 站场 | E19: 昌吉 | G19: 西部 | H19: 1用1备 | I19: 1用1备 | J19: 7.0-11.5
... A25: 西气东输二线 | B25: 新捷燃气<乌鲁木齐> | C25: 一期 | D25: 站场 | E25: 乌鲁木齐 | G25: 西部 | H25: 1用1备 | I25: 1用1备 | J25: 干线压力
A26: 西气东输二线 | B26: 巴州洪通<孔雀河> | D26: 站场 | E26: 孔雀河 | G26: 西部 | H26: 2用1备 | I26: 2用1备 | J26: 2.5-9.0 | K26: 2024.3
A27: 西气东输二线 | B27: 昆仑燃气巴州分公司<孔雀河> | C27: 2025已投 | D27: 站场 | E27: 孔雀河 | G27: 西部 | H27: 1用1备 | I27: 1用1备 | J27: 2.5-9 | K27: 45929
A28: 西气东输二线 | B28: 国泰鸿远<轮吐6#> | C28: 二期 | D28: 阀室 | E28: 轮吐6# | G28: 西部 | H28: 1用1备 | I28: 1用1备 | J28: 干线压力
A29: 西气东输二线 | B29: 吐鲁番新捷<库米什> | D29: 站场 | E29: 库米什 | G29: 西部 | H29: 1用1备 | I29: 1用1备 | J29: 2.5-10.0 | K29: 2024.2
A30: 西气东输二线 | B30: 托克逊新捷<轮吐14#> | C30: 二期 | D30: 阀室 | E30: 轮吐14# | G30: 西部 | H30: 1用1备 | I30: 1用1备 | J30: 干线压力
A31: 西气东输二线 | B31: 哈密新捷<哈密>A | C31: 二期 | D31: 站场 | E31: 哈密 | G31: 西部 | H31: 1用1备 | I31: 1用1备 | J31: 5.8
A32: 西气东输二线 | B32: 哈密新捷<哈密>B | C32: 2024年已报 | D32: 站场 | E32: 哈密 | G32: 西部 | J32: 5.0-12.0
A33: 西气东输二线 | B33: 哈密洪通<哈密> | C33: 2024年已报 | D33: 站场 | E33: 哈密 | G33: 西部 | J33: 5.0-10.0
A34: 西气东输一线 | B34: 瓜州昆仑<瓜州> | C34: 2024年已报 | D34: 站场 | E34: 瓜州 | G34: 西部 | J34: 4-10
A35: 西气东输二线 | B35: 嘉峪关昆仑<嘉峪关> | C35: 二期 | D35: 站场 | E35: 嘉峪关 | G35: 西部 | H35: 1用1备 | I35: 1用1备 | J35: 干线压力
A36: 西气东输二线 | B36: 酒泉昆仑<嘉峪关> | C36: 二期 | D36: 站场 | E36: 嘉峪关 | G36: 西部 | H36: 1用1备 | I36: 1用1备 | J36: 干线压力
A37: 西气东输二线 | B37: 嘉峪关昆仑(新)<嘉峪关> | C37: 2024已投 | D37: 站场 | E37: 嘉峪关 | G37: 西部 | H37: 两用一备 | I37: 1用1备 | J37: 0.5-6.3 | K37: 2024.5
A38: 西气东输二线 | B38: 张掖中油<张掖> | C38: 四期 | D38: 站场 | E38: 张掖 | G38: 西部 | H38: 1用1备 | I38: 1用1备 | J38: 干线压力
A39: 西气东输二线 | B39: 张掖昆仑<张掖> | C39: 二期 | D39: 站场 | E39: 张掖 | G39: 西部 | H39: 1用1备 | I39: 1用1备 | J39: 干线压力
A40: 西气东输二线 | B40: 丰聚能源<西二57#> | C40: 四期 | D40: 阀室 | E40: 西二57# | G40: 西部 | H40: 2用2备 | I40: 1用1备 | J40: 干线压力
A41: 西气东输二线 | B41: 甘肃浩源<金昌> | C41: 二期 | D41: 站场 | E41: 金昌 | G41: 西部 | H41: 1用1备 | I41: 1用1备 | J41: 干线压力
A42: 西气东输二线 | B42: 金昌昆仑<金昌> | C42: 二期 | D42: 站场 | E42: 金昌 | G42: 西部 | H42: 1用1备 | I42: 1用1备 | J42: 干线压力
A43: 西气东输二线 | B43: 武威昆仑<武威> | C43: 二期 | D43: 站场 | E43: 武威 | G43: 西部 | H43: 1用1备 | I43: 1用1备 | J43: 干线压力
A44: 西气东输二线 | B44: 时代燃气<霍尔果斯> | C44: 2024已投 | D44: 站场 | E44: 霍尔果斯 | G44: 西部 | H44: 2台流量计，FT112011、FT112021 | I44: 等压 | J44: 6-11.5 | K44: 2024.10
A45: 西气东输二线 | B45: 华海电厂<德庆> | C45: 2024已投 | D45: 站场 | E45: 德庆 | G45: 南部 | H45: 1用1备 | I45: 1用1备 | J45: 4 | K45: 2024.12
A46: 西气东输二线 | B46: 峡江新奥<樟树> | C46: 2024已投 | D46: 站场 | E46: 樟树 | G46: 中部 | H46: 1用1备 | I46: 1用1备 | J46: 2.0-4.0 | K46: 2024.10
A47: 西气东输二线 | B47: 富平通源<富平> | C47: 2025已投 | D47: 站场 | E47: 富平 | G47: 中部 | H47: 1用1备 | I47: 1用1备 | J47: 3.8-4.0 | K47: 45928
A48: 西气东输二线 | B48: 富平中民<富平> | C48: 2025已投 | D48: 站场 | E48: 富平 | G48: 中部 | H48: 1用1备 | I48: 1用1备 | J48: 3.8-4.0 | K48: 45928
A49: 涩宁兰管道 | B49: 德令哈正和<德令哈> | C49: 不改 | D49: 站场 | E49: 德令哈 | G49: 西部 | H49: 1用2备 | I49: 1用1备 | J49: 干线压力
A50: 涩宁兰管道 | B50: 海西金地<德令哈> | C50: 不改 | D50: 站场 | E50: 德令哈 | G50: 西部 | H50: 1用1备 | I50: 1用1备 | J50: 干线压力
A51: 涩宁兰管道 | B51: 海西新源<德令哈> | C51: 不改 | D51: 站场 | E51: 德令哈 | G51: 西部 | H51: 1用1备 | I51: 1用1备 | J51: 干线压力
A52: 涩宁兰管道 | B52: 大柴旦金地<羊肠子沟> | C52: 四期 | D52: 站场 | E52: 羊肠子沟 | G52: 西部 | H52: 1用0备 | I52: 0用0备 | J52: 2.0-6.3
A53: 涩宁兰管道 | B53: 海晏正和<湖东> | C53: 2024年已报 | D53: 站场 | E53: 湖东 | G53: 西部 | J53: 0.6-6.3
A54: 涩宁兰管道 | B54: 桂鲁化工<西宁> | C54: 二期 | D54: 站场 | E54: 西宁 | G54: 西部 | H54: 1用1备 | I54: 无 | J54: 干线压力
A55: 涩宁兰管道 | B55: 湟中华润<西宁> | C55: 二期 | D55: 站场 | E55: 西宁 | G55: 西部 | H55: 1用1备 | I55: 无 | J55: 干线压力
A56: 涩宁兰管道 | B56: 西宁中油<西宁> | C56: 二期 | D56: 站场 | E56: 西宁 | G56: 西部 | H56: 1用1备 | I56: 无 | J56: 干线压力
A57: 涩宁兰管道 | B57: 中复神鹰<西宁> | C57: 2024已投 | D57: 站场 | E57: 西宁 | G57: 西部 | H57: 1用1备 | I57: 无 | J57: 2.0-6.3 | K57: 2024.8
A58: 涩宁兰管道 | B58: 西宁中油<涩宁兰732km+300m> | C58: 不改 | D58: 干线开口 | E58: 涩宁兰732km+300m | G58: 西部 | H58: 2用2备 | I58: 无 | J58: 干线压力
A59: 涩宁兰管道 | B59: 甘河中油<甘和门> | C59: 不改 | D59: 站场 | E59: 甘和门 | G59: 西部 | H59: 1用1备 | I59: 无 | J59: 干线压力
A60: 涩宁兰管道 | B60: 中油燃气投资<涩复21#> | C60: 二期 | D60: 阀室 | E60: 涩复21# | G60: 西部 | H60: 1用1备 | I60: 1用1备 | J60: 干线压力
A61: 涩宁兰管道 | B61: 贵德华天<涩复22#> | C61: 二期 | D61: 阀室 | E61: 涩复22# | G61: 西部 | H61: 1用1备 | I61: 无 | J61: 干线压力
A62: 涩宁兰管道 | B62: 菏泽燃气<拉脊山> | C62: 2024年已报 | D62: 站场 | E62: 拉脊山 | G62: 西部 | H62: 2用1备 | I62: 1用1备 | J62: 2-6.3
A63: 涩宁兰管道 | B63: 东部中油<平安> | C63: 二期 | D63: 站场 | E63: 平安 | G63: 西部 | H63: 1用1备 | I63: 1用1备 | J63: 干线压力
A64: 涩宁兰管道 | B64: 互助金地<平安>B | C64: 二期 | D64: 站场 | E64: 平安 | G64: 西部 | H64: 1用1备 | I64: 1用1备 | J64: 干线压力
A65: 涩宁兰管道 | B65: 平安森昌<平安> | C65: 二期 | D65: 站场 | E65: 平安 | G65: 西部 | H65: 1用1备 | I65: 1用1备 | J65: 干线压力
A66: 涩宁兰管道 | B66: 互助金地<平安>A | C66: 二期 | D66: 站场 | E66: 平安 | G66: 西部 | H66: 1用1备 | I66: 1用1备 | J66: 干线压力
A67: 涩宁兰管道 | B67: 化隆畅辉<平安> | C67: 2025已投 | D67: 站场 | E67: 平安 | G67: 西部 | H67: 2 | I67: 2 | J67: 1.6-4.0 | K67: 45855
A68: 涩宁兰管道 | B68: 东部中油<涩宁兰26#> | C68: 二期 | D68: 阀室 | E68: 涩宁兰26# | G68: 西部 | H68: 1用1备 | I68: 无 | J68: 干线压力
A69: 涩宁兰管道 | B69: 乌兰新源<乌兰> | C69: 二期 | D69: 站场 | E69: 乌兰 | G69: 西部 | H69: 1用1备 | I69: 1用1备 | J69: 3
A70: 涩宁兰管道 | B70: 乌兰金地<乌兰> | C70: 二期 | D70: 站场 | E70: 乌兰 | G70: 西部 | H70: 1用1备 | I70: 无 | J70: 3（干线压力）
A71: 涩宁兰管道 | B71: 海东华润<涩复27#> | C71: 不改 | D71: 站场 | E71: 涩复27# | G71: 西部 | H71: 1用1备 | I71: 1用1备 | J71: 干线压力
A72: 涩宁兰管道 | B72: 青海川垣<涩复857km+800m> | C72: 二期 | D72: 干线开口 | E72: 涩复857km+800m | G72: 西部 | H72: 1用1备 | I72: 1用1备 | J72: 干线压力
A73: 涩宁兰管道 | B73: 民和川中<涩复30#> | C73: 不改 | D73: 阀室 | E73: 涩复30# | G73: 西部 | H73: 1用1备 | I73: 1用1备 | J73: 干线压力
A74: 涩宁兰管道 | B74: 甘南昆仑<合作> | C74: 不改 | D74: 站场 | E74: 合作 | G74: 西部 | H74: 1用1备 | I74: 1用1备 | J74: 0.4-0.6
A75: 涩宁兰管道 | B75: 甘南鑫源<合作> | C75: 不改 | D75: 站场 | E75: 合作 | G75: 西部 | H75: 1用1备 | I75: 1用1备 | J75: 0.3
A76: 涩宁兰管道 | B76: 甘南昆仑<夏河> | C76: 不改 | D76: 站场 | E76: 夏河 | G76: 西部 | H76: 1用1备 | I76: 1用1备 | J76: 干线压力
A77: 涩宁兰管道 | B77: 红古鑫源<涩宁兰30#> | C77: 不改 | D77: 站场 | E77: 涩宁兰30# | G77: 西部 | H77: 1用1备 | I77: 1用2备 | J77: 干线压力
A78: 涩宁兰管道 | B78: 中铝兰州<兰铝> | C78: 不改 | D78: 站场 | E78: 兰铝 | G78: 西部 | H78: 1用1备 | I78: 1用1备 | J78: 干线压力
A79: 涩宁兰管道 | B79: 永靖三峡<甘西南1#> | C79: 五期 | D79: 站场 | E79: 甘西南1# | G79: 西部 | H79: 一线1用1备/ 二线1用1备/三线1用1备/盐锅峡1用1备 | I79: 一线1用1备 二线1用1备 | J79: 干线压力
A80: 涩宁兰管道 | B80: 刘化集团<刘化> | C80: 不改 | D80: 站场 | E80: 刘化 | G80: 西部 | H80: 1用1备 | I80: 1用1备 | J80: 干线压力
A81: 涩宁兰老线 | B81: 永靖三峡（新）<刘化> | C81: 2025已投 | D81: 站场 | E81: 刘化 | G81: 西部 | H81: 1用1备 | I81: 1用1备 | J81: 0.4-2.4 | K81: 45930
A82: 涩宁兰管道 | B82: 临夏昆仑<临夏> | C82: 不改 | D82: 站场 | E82: 临夏 | G82: 西部 | H82: 1用1备 | I82: 1用1备 | J82: 1.2-5.67
A83: 涩宁兰管道 | B83: 甘肃盛和<临夏> | C83: 三期 | D83: 站场 | E83: 临夏 | G83: 西部 | H83: 1用1备 | I83: 无 | J83: 1.6-2.5
A84: 涩宁兰管道 | B84: 昌宏商贸<甘西南3#> | C84: 不改 | D84: 阀室 | E84: 甘西南3# | G84: 西部 | H84: 1用1备 | I84: 无 | J84: 2.5
A85: 涩宁兰管道 | B85: 蓝星化工<涩宁兰32#> | C85: 不改 | D85: 阀室 | E85: 涩宁兰32# | G85: 西部 | H85: 1用1备 | I85: 1用1备 | J85: 干线压力
A86: 涩宁兰管道 | B86: 甘肃昆仑<涩复35#> | C86: 二期 | D86: 阀室 | E86: 涩复35# | G86: 西部 | H86: 1用2备（夏季）2用1备（冬季） | I86: 1用2备 | J86: 干线压力
A87: 涩宁兰管道 | B87: 兰州石化<兰州> | C87: 不改 | D87: 站场 | E87: 兰州 | G87: 西部 | H87: 二线1用1备 | I87: 一线1用1备 二线1用1备 | J87: 干线压力
A88: 涩宁兰管道 | B88: 甘肃昆仑<兰州> | C88: 不改 | D88: 站场 | E88: 兰州 | G88: 西部 | H88: 二线1用2备（夏季 二线2用1备（冬季） | I88: 一线1用3备 二线1用1备 | J88: 干线压力
A89: 涩宁兰管道 | B89: 甘肃销售<兰州> | C89: 不改 | D89: 站场 | E89: 兰州 | G89: 西部 | H89: 1用1备 | I89: 1用1备 | J89: 干线压力
A90: 涩宁兰管道 | B90: 榆中昆仑<和平> | C90: 四期 | D90: 站场 | E90: 和平 | G90: 西部 | H90: 1用1备 | I90: 1用1备 | J90: 1.4-2.2
A91: 涩宁兰管道 | B91: 榆中昆仑<榆中> | C91: 四期 | D91: 站场 | E91: 榆中 | G91: 西部 | H91: 1用1备 | J91: 干线压力
A92: 涩宁兰管道 | B92: 甘肃金地<甘西南2#> | C92: 五期 | D92: 站场 | E92: 甘西南2# | G92: 西部 | H92: 1用1备 | J92: 干线压力
A93: 涩宁兰管道 | B93: 定西昆仑<定西> | C93: 二期 | D93: 站场 | E93: 定西 | G93: 西部 | H93: 1用1备 | J93: 干线压力
A94: 涩宁兰管道 | B94: 临夏昆仑<1#阀室> | C94: 2025已投 | D94: 站场 | E94: 1#阀室 | G94: 西部 | H94: 1用1备 | I94: 1用1备 | J94: 0.1-4.0 | K94: 45888
A95: 长宁线 | B95: 哈纳斯<银川> | C95: 二期 | D95: 站场 | E95: 银川 | G95: 西部 | H95: 2用2备 | I95: 2用2备 | J95: 2.6-6.2
A96: 长宁线 | B96: 宁夏石化<银川>A | C96: 三期 | D96: 站场 | E96: 银川 | G96: 西部 | H96: 2用1备 | I96: 无 | J96: 2.6-6.2
A97: 长宁线 | B97: 宁夏石化<银川>B | C97: 三期 | D97: 站场 | E97: 银川 | F97: B分输口 | G97: 西部 | H97: 1用1备 | I97: 1用1备 | J97: 2.6-6.2
A98: 长宁线 | B98: 洁能科技<银川> | C98: 二期 | D98: 站场 | E98: 银川 | G98: 西部 | H98: 1用1备 | I98: 1用1备 | J98: 2.6-6.2
A99: 长宁线 | B99: 宝塔实业<银川> | C99: 二期 | D99: 站场 | E99: 银川 | G99: 西部 | H99: 1用1备 | I99: 1用1备 | J99: 2.6-6.2
A100: 长宁线 | B100: 银川昆仑<银川> | C100: 三期 | D100: 站场 | E100: 银川 | G100: 西部 | H100: 1用1备 | I100: 无 | J100: 2.6-6.2
A101: 长宁线 | B101: 石嘴山星泽<银川> | C101: 三期 | D101: 站场 | E101: 银川 | G101: 西部 | H101: 2用1备 | I101: 无 | J101: 2.6-6.2
A102: 长宁线 | B102: 清洁能源<银川> | C102: 三期 | D102: 站场 | E102: 银川 | G102: 西部 | H102: 1用无备 | I102: 无 | J102: 2.6-6.2
A103: 长宁线 | B103: 宝塔实业<长宁6#-15.25km> | C103: 不改 | D103: 干线开口 | E103: 长宁6#-15.25km | G103: 西部 | H103: 1用1备 | I103: 无 | J103: 2.6-6.2
A104: 长宁线 | B104: 神华宁煤<宁东> | C104: 不改 | D104: 站场 | E104: 宁东 | G104: 西部 | H104: 1用1备 | I104: 无 | J104: 2-4
A105: 长宁线 | B105: 新捷宁东<宁东> | C105: 不改 | D105: 站场 | E105: 宁东 | G105: 西部 | H105: 1用1备 | I105: 无 | J105: 2-4
...

Sheet 调度台
A1: [原始]序号 | B1: [原始]调度台
A2: 1 | B2: 西部
A3: 2 | B3: 北部
A4: 3 | B4: 中部
A5: 4 | B5: 东部
A6: 5 | B6: 南部
A7: 6 | B7: 省网

Sheet 压缩机
A1: [原始]地区公司 | B1: [计算]调控级别 | C1: [计算]干线管道 | D1: [计算]支线管道 | E1: [关联]站场 | F1: [原始]机组配置 | G1: [原始]压缩机组编号 | H1: [原始]72h测试完成时间 | I1: [原始]驱动方式 | J1: [原始]进口/国产 | K1: [原始]压缩机厂商 | L1: [原始]压缩机型号 | M1: [原始]驱动机型号及 制造商 | N1: [原始]连续运行工作转速范围rpm | O1: [原始]最大连续运行转速rpm | P1: [原始]入口压力范围MPa | Q1: [原始]驱动机额定功率MW | R1: [原始]机组投产情况 | S1: [原始]余热利用 | T1: 压缩机平台 | U1: [原始]备注
A2: 西部管道 | B2: =VLOOKUP(C2,[1]干线管道!B:C,2,FALSE) -> 一级 | C2: =VLOOKUP(E2,[1]站场阀室!A:D,3,FALSE) -> 西气东输一线 | D2: 西一线干线新疆段 | E2: 轮南压气站 | F2: 2+1 | G2: 1# | H2: 38231 | I2: 燃驱 | J2: 进口 | K2: Rolls-Royce | L2: RF2BB36 | M2: RB211-24G/RR | N2: 3120-4800 | O2: 5040 | P2: >5 | Q2: 29.53 | R2: 投产 | S2: 无 | T2: 一期
A3: 西部管道 | B3: =VLOOKUP(C3,[1]干线管道!B:C,2,FALSE) -> 一级 | C3: =VLOOKUP(E3,[1]站场阀室!A:D,3,FALSE) -> 西气东输一线 | D3: 西一线干线新疆段 | E3: 轮南压气站 | F3: 2+1 | G3: 2# | H3: 38231 | I3: 燃驱 | J3: 进口 | K3: Rolls-Royce | L3: RF2BB36 | M3: RB211-24G/RR | N3: 3120-4800 | O3: 5040 | P3: >5 | Q3: 29.53 | R3: 投产 | T3: 一期
A4: 西部管道 | B4: =VLOOKUP(C4,[1]干线管道!B:C,2,FALSE) -> 一级 | C4: =VLOOKUP(E4,[1]站场阀室!A:D,3,FALSE) -> 西气东输一线 | D4: 西一线干线新疆段 | E4: 轮南压气站 | F4: 2+1 | G4: 3# | H4: 40126 | I4: 燃驱 | J4: 进口 | K4: Rolls-Royce | L4: RF2BB36 | M4: RB211-24G/RR | N4: 3120-4800 | O4: 5040 | P4: >5 | Q4: 29.53 | R4: 投产 | T4: 一期
A5: 西部管道 | B5: =VLOOKUP(C5,[1]干线管道!B:C,2,FALSE) -> 一级 | C5: =VLOOKUP(E5,[1]站场阀室!A:D,3,FALSE) -> 西气东输一线 | D5: 西一线干线新疆段 | E5: 孔雀河压气站 | F5: 2+1 | G5: 1# | H5: 39080 | I5: 燃驱 | J5: 进口 | K5: General Electric | L5: PCL804 | M5: PGT25+SAC/GE | N5: 3965-6100 | O5: 6405 | P5: >3.8 | Q5: 31.4 | R5: 投产 | S5: 无 | T5: 一期
A6: 西部管道 | B6: =VLOOKUP(C6,[1]干线管道!B:C,2,FALSE) -> 一级 | C6: =VLOOKUP(E6,[1]站场阀室!A:D,3,FALSE) -> 西气东输一线 | D6: 西一线干线新疆段 | E6: 孔雀河压气站 | F6: 2+1 | G6: 2# | H6: 39117 | I6: 燃驱 | J6: 进口 | K6: General Electric | L6: PCL804 | M6: PGT25+SAC/GE | N6: 3965-6100 | O6: 6405 | P6: >3.8 | Q6: 31.4 | R6: 投产 | T6: 一期
A7: 西部管道 | B7: =VLOOKUP(C7,[1]干线管道!B:C,2,FALSE) -> 一级 | C7: =VLOOKUP(E7,[1]站场阀室!A:D,3,FALSE) -> 西气东输一线 | D7: 西一线干线新疆段 | E7: 孔雀河压气站 | F7: 2+1 | G7: 3# | H7: 40483 | I7: 燃驱 | J7: 进口 | K7: General Electric | L7: PCL804 | M7: PGT25+SAC/GE | N7: 3965-6100 | O7: 6405 | P7: >3.8 | Q7: 31.4 | R7: 投产 | T7: 一期
A8: 西部管道 | B8: =VLOOKUP(C8,[1]干线管道!B:C,2,FALSE) -> 一级 | C8: =VLOOKUP(E8,[1]站场阀室!A:D,3,FALSE) -> 西气东输一线 | D8: 西一线干线新疆段 | E8: 四道班压气站 | F8: 1+1 | G8: 1# | H8: 39071 | I8: 燃驱 | J8: 进口 | K8: Rolls-Royce | L8: RF2BB36 | M8: RB211-24G/RR | N8: 3120-4800 | O8: 5040 | P8: 报警值4，停机值3 | Q8: 29.53 | R8: 投产 | S8: 无 | T8: 一期
A9: 西部管道 | B9: =VLOOKUP(C9,[1]干线管道!B:C,2,FALSE) -> 一级 | C9: =VLOOKUP(E9,[1]站场阀室!A:D,3,FALSE) -> 西气东输一线 | D9: 西一线干线新疆段 | E9: 四道班压气站 | F9: 1+1 | G9: 2# | H9: 38248 | I9: 燃驱 | J9: 进口 | K9: Rolls-Royce | L9: RF2BB36 | M9: RB211-24G/RR | N9: 3120-4800 | O9: 5040 | P9: 报警值4，停机值3 | Q9: 29.53 | R9: 投产 | T9: 一期
A10: 西部管道 | B10: =VLOOKUP(C10,[1]干线管道!B:C,2,FALSE) -> 一级 | C10: =VLOOKUP(E10,[1]站场阀室!A:D,3,FALSE) -> 西气东输一线 | D10: 西一线干线新疆段 | E10: 鄯善压气站 | F10: 2+1 | G10: 1# | H10: 39122 | I10: 燃驱 | J10: 进口 | K10: General Electric | L10: PCL804 | M10: PGT25+SAC/GE | N10: 3965-6100 | O10: 6405 | P10: >5.8 | Q10: 31.364 | R10: 投产 | S10: 无 | T10: 一期
A11: 西部管道 | B11: =VLOOKUP(C11,[1]干线管道!B:C,2,FALSE) -> 一级 | C11: =VLOOKUP(E11,[1]站场阀室!A:D,3,FALSE) -> 西气东输一线 | D11: 西一线干线新疆段 | E11: 鄯善压气站 | F11: 2+1 | G11: 2# | H11: 39078 | I11: 燃驱 | J11: 进口 | K11: General Electric | L11: PCL804 | M11: PGT25+SAC/GE | N11: 3965-6100 | O11: 6405 | P11: >5.8 | Q11: 31.364 | R11: 投产 | T11: 一期
A12: 西部管道 | B12: =VLOOKUP(C12,[1]干线管道!B:C,2,FALSE) -> 一级 | C12: =VLOOKUP(E12,[1]站场阀室!A:D,3,FALSE) -> 西气东输一线 | D12: 西一线干线新疆段 | E12: 鄯善压气站 | F12: 2+1 | G12: 3# | H12: 40544 | I12: 燃驱 | J12: 进口 | K12: General Electric | L12: PCL804 | M12: PGT25+SAC/GE | N12: 3965-6100 | O12: 6405 | P12: >5.8 | Q12: 31.364 | R12: 投产 | T12: 一期
A13: 西部管道 | B13: =VLOOKUP(C13,[1]干线管道!B:C,2,FALSE) -> 一级 | C13: =VLOOKUP(E13,[1]站场阀室!A:D,3,FALSE) -> 西气东输一线 | D13: 西一线干线新疆段 | E13: 哈密压气站 | F13: 2+1 | G13: 1# | H13: 38658 | I13: 燃驱 | J13: 进口 | K13: Rolls-Royce | L13: RF3BB36 | M13: RB211-24G/RR | N13: 3120-4800 | O13: 5040 | P13: >4 | Q13: 29.53 | R13: 投产 | S13: 无 | T13: 一期
A14: 西部管道 | B14: =VLOOKUP(C14,[1]干线管道!B:C,2,FALSE) -> 一级 | C14: =VLOOKUP(E14,[1]站场阀室!A:D,3,FALSE) -> 西气东输一线 | D14: 西一线干线新疆段 | E14: 哈密压气站 | F14: 2+1 | G14: 2# | H14: 38695 | I14: 燃驱 | J14: 进口 | K14: Rolls-Royce | L14: RF3BB36 | M14: RB211-24G/RR | N14: 3120-4800 | O14: 5040 | P14: >4 | Q14: 29.53 | R14: 投产 | T14: 一期
A15: 西部管道 | B15: =VLOOKUP(C15,[1]干线管道!B:C,2,FALSE) -> 一级 | C15: =VLOOKUP(E15,[1]站场阀室!A:D,3,FALSE) -> 西气东输一线 | D15: 西一线干线新疆段 | E15: 哈密压气站 | F15: 2+1 | G15: 3# | H15: 40505 | I15: 燃驱 | J15: 进口 | K15: Rolls-Royce | L15: RF3BB36 | M15: RB211-24G/RR | N15: 3120-4800 | O15: 5040 | P15: >4 | Q15: 29.53 | R15: 投产 | T15: 一期
A16: 西部管道 | B16: =VLOOKUP(C16,[1]干线管道!B:C,2,FALSE) -> 一级 | C16: =VLOOKUP(E16,[1]站场阀室!A:D,3,FALSE) -> 西气东输一线 | D16: 西一线干线新疆段 | E16: 雅满苏压气站 | F16: 1+1 | G16: 1# | H16: 39351 | I16: 燃驱 | J16: 进口 | K16: General Electric | L16: PCL804 | M16: PGT25+SAC/GE | N16: 3965-6100 | O16: 6405 | P16: >5.8 | Q16: 31.364 | R16: 投产 | S16: 无 | T16: 一期
A17: 西部管道 | B17: =VLOOKUP(C17,[1]干线管道!B:C,2,FALSE) -> 一级 | C17: =VLOOKUP(E17,[1]站场阀室!A:D,3,FALSE) -> 西气东输一线 | D17: 西一线干线新疆段 | E17: 雅满苏压气站 | F17: 1+1 | G17: 2# | H17: 39262 | I17: 燃驱 | J17: 进口 | K17: General Electric | L17: PCL804 | M17: PGT25+SAC/GE | N17: 3965-6100 | O17: 6405 | P17: >5.8 | Q17: 31.364 | R17: 投产 | T17: 一期
A18: 甘肃公司 | B18: =VLOOKUP(C18,[1]干线管道!B:C,2,FALSE) -> 一级 | C18: =VLOOKUP(E18,[1]站场阀室!A:D,3,FALSE) -> 西气东输一线 | D18: =VLOOKUP(E18,[1]站场阀室!A:D,4,FALSE) -> 西一线干线甘肃段 | E18: 红柳压气站 | F18: 2+1 | G18: 1# | H18: 38607 | I18: 燃驱 | J18: 进口 | K18: Rolls-Royce | L18: RF2BB36 | M18: RB211-24G/RR | N18: 3120-4800 | O18: 5040 | P18: >4 | Q18: 29.53 | R18: 投产 | S18: 无 | T18: 一期
A19: 甘肃公司 | B19: =VLOOKUP(C19,[1]干线管道!B:C,2,FALSE) -> 一级 | C19: =VLOOKUP(E19,[1]站场阀室!A:D,3,FALSE) -> 西气东输一线 | D19: =VLOOKUP(E19,[1]站场阀室!A:D,4,FALSE) -> 西一线干线甘肃段 | E19: 红柳压气站 | F19: 2+1 | G19: 2# | H19: 38607 | I19: 燃驱 | J19: 进口 | K19: Rolls-Royce | L19: RF2BB36 | M19: RB211-24G/RR | N19: 3120-4800 | O19: 5040 | P19: >4 | Q19: 29.53 | R19: 投产 | T19: 一期
A20: 甘肃公司 | B20: =VLOOKUP(C20,[1]干线管道!B:C,2,FALSE) -> 一级 | C20: =VLOOKUP(E20,[1]站场阀室!A:D,3,FALSE) -> 西气东输一线 | D20: =VLOOKUP(E20,[1]站场阀室!A:D,4,FALSE) -> 西一线干线甘肃段 | E20: 红柳压气站 | F20: 2+1 | G20: 3# | H20: 40494 | I20: 燃驱 | J20: 进口 | K20: Rolls-Royce | L20: RF2BB36 | M20: RB211-24G/RR | N20: 3120-4800 | O20: 5040 | P20: >4 | Q20: 29.53 | R20: 投产 | T20: 一期
A21: 甘肃公司 | B21: =VLOOKUP(C21,[1]干线管道!B:C,2,FALSE) -> 一级 | C21: =VLOOKUP(E21,[1]站场阀室!A:D,3,FALSE) -> 西气东输一线 | D21: =VLOOKUP(E21,[1]站场阀室!A:D,4,FALSE) -> 西一线干线甘肃段 | E21: 柳园压气站 | F21: 2+1 | G21: 1# | H21: 39083 | I21: 燃驱 | J21: 进口 | K21: General Electric | L21: PCL804 | M21: PGT25+SAC/GE | N21: 3965-6100 | O21: 6405 | P21: >5.8 | Q21: 31.364 | R21: 投产 | S21: 无 | T21: 一期
A22: 甘肃公司 | B22: =VLOOKUP(C22,[1]干线管道!B:C,2,FALSE) -> 一级 | C22: =VLOOKUP(E22,[1]站场阀室!A:D,3,FALSE) -> 西气东输一线 | D22: =VLOOKUP(E22,[1]站场阀室!A:D,4,FALSE) -> 西一线干线甘肃段 | E22: 柳园压气站 | F22: 2+1 | G22: 2# | H22: 39090 | I22: 燃驱 | J22: 进口 | K22: General Electric | L22: PCL804 | M22: PGT25+SAC/GE | N22: 3965-6100 | O22: 6405 | P22: >5.8 | Q22: 31.364 | R22: 投产 | T22: 一期
A23: 甘肃公司 | B23: =VLOOKUP(C23,[1]干线管道!B:C,2,FALSE) -> 一级 | C23: =VLOOKUP(E23,[1]站场阀室!A:D,3,FALSE) -> 西气东输一线 | D23: =VLOOKUP(E23,[1]站场阀室!A:D,4,FALSE) -> 西一线干线甘肃段 | E23: 柳园压气站 | F23: 2+1 | G23: 3# | H23: 40490 | I23: 燃驱 | J23: 进口 | K23: General Electric | L23: PCL804 | M23: PGT25+SAC/GE | N23: 3965-6100 | O23: 6405 | P23: >5.8 | Q23: 31.364 | R23: 投产 | T23: 一期
A24: 甘肃公司 | B24: =VLOOKUP(C24,[1]干线管道!B:C,2,FALSE) -> 一级 | C24: =VLOOKUP(E24,[1]站场阀室!A:D,3,FALSE) -> 西气东输一线 | D24: =VLOOKUP(E24,[1]站场阀室!A:D,4,FALSE) -> 西一线干线甘肃段 | E24: 玉门压气站 | F24: 2+1 | G24: 1# | H24: 39256 | I24: 电驱 | J24: 进口 | K24: Rolls-Royce | L24: RF3BB36 | M24: 1DX 1749-8ES01-Z/西门子 西门子变频器 | N24: 3120-4800 | O24: 5040 | P24: >4 | Q24: 22 | R24: 投产 | S24: 无 | T24: 一期
A25: 甘肃公司 | B25: =VLOOKUP(C25,[1]干线管道!B:C,2,FALSE) -> 一级 | C25: =VLOOKUP(E25,[1]站场阀室!A:D,3,FALSE) -> 西气东输一线 | D25: =VLOOKUP(E25,[1]站场阀室!A:D,4,FALSE) -> 西一线干线甘肃段 | E25: 玉门压气站 | F25: 2+1 | G25: 2# | H25: 38671 | I25: 燃驱 | J25: 进口 | K25: Rolls-Royce | L25: RF2BB36 | M25: RB211-24G/RR | N25: 3120-4800 | O25: 5040 | P25: >4 | Q25: 29.53 | R25: 投产 | T25: 一期
A26: 甘肃公司 | B26: =VLOOKUP(C26,[1]干线管道!B:C,2,FALSE) -> 一级 | C26: =VLOOKUP(E26,[1]站场阀室!A:D,3,FALSE) -> 西气东输一线 | D26: =VLOOKUP(E26,[1]站场阀室!A:D,4,FALSE) -> 西一线干线甘肃段 | E26: 玉门压气站 | F26: 2+1 | G26: 3# | H26: 2010.12 | I26: 电驱 | J26: 进口 | K26: Rolls-Royce | L26: RF3BB36 | M26: 1DX 1749-8ES01-Z/西门子 西门子变频器 | N26: 3120-4800 | O26: 5040 | P26: >4 | Q26: 22 | R26: 投产 | T26: 一期
A27: 甘肃公司 | B27: =VLOOKUP(C27,[1]干线管道!B:C,2,FALSE) -> 一级 | C27: =VLOOKUP(E27,[1]站场阀室!A:D,3,FALSE) -> 西气东输一线 | D27: =VLOOKUP(E27,[1]站场阀室!A:D,4,FALSE) -> 西一线干线甘肃段 | E27: 酒泉压气站 | F27: 2+1 | G27: 1# | H27: 39125 | I27: 燃驱 | J27: 进口 | K27: General Electric | L27: PCL804 | M27: PGT25+SAC/GE | N27: 3965-6100 | O27: 6405 | P27: >5.8 | Q27: 31.364 | R27: 投产 | S27: 无 | T27: 一期
A28: 甘肃公司 | B28: =VLOOKUP(C28,[1]干线管道!B:C,2,FALSE) -> 一级 | C28: =VLOOKUP(E28,[1]站场阀室!A:D,3,FALSE) -> 西气东输一线 | D28: =VLOOKUP(E28,[1]站场阀室!A:D,4,FALSE) -> 西一线干线甘肃段 | E28: 酒泉压气站 | F28: 2+1 | G28: 2# | H28: 39125 | I28: 燃驱 | J28: 进口 | K28: General Electric | L28: PCL804 | M28: PGT25+SAC/GE | N28: 3965-6100 | O28: 6405 | P28: >5.8 | Q28: 31.364 | R28: 投产 | T28: 一期
A29: 甘肃公司 | B29: =VLOOKUP(C29,[1]干线管道!B:C,2,FALSE) -> 一级 | C29: =VLOOKUP(E29,[1]站场阀室!A:D,3,FALSE) -> 西气东输一线 | D29: =VLOOKUP(E29,[1]站场阀室!A:D,4,FALSE) -> 西一线干线甘肃段 | E29: 酒泉压气站 | F29: 2+1 | G29: 3# | H29: 40494 | I29: 燃驱 | J29: 进口 | K29: General Electric | L29: PCL804 | M29: PGT25+SAC/GE | N29: 3965-6100 | O29: 6405 | P29: >5.8 | Q29: 31.364 | R29: 投产 | T29: 一期
A30: 甘肃公司 | B30: =VLOOKUP(C30,[1]干线管道!B:C,2,FALSE) -> 一级 | C30: =VLOOKUP(E30,[1]站场阀室!A:D,3,FALSE) -> 西气东输一线 | D30: =VLOOKUP(E30,[1]站场阀室!A:D,4,FALSE) -> 西一线干线甘肃段 | E30: 山丹压气站 | F30: 2+1 | G30: 1# | H30: 39063 | I30: 燃驱 | J30: 进口 | K30: Rolls-Royce | L30: RF3BB36 | M30: RB211-24G/RR | N30: 3120-4800 | O30: 5040 | P30: >4 | Q30: 29.53 | R30: 投产 | S30: 无 | T30: 一期
A31: 甘肃公司 | B31: =VLOOKUP(C31,[1]干线管道!B:C,2,FALSE) -> 一级 | C31: =VLOOKUP(E31,[1]站场阀室!A:D,3,FALSE) -> 西气东输一线 | D31: =VLOOKUP(E31,[1]站场阀室!A:D,4,FALSE) -> 西一线干线甘肃段 | E31: 山丹压气站 | F31: 2+1 | G31: 2# | H31: 38565 | I31: 燃驱 | J31: 进口 | K31: Rolls-Royce | L31: RF3BB36 | M31: RB211-24G/RR | N31: 3120-4800 | O31: 5040 | P31: >4 | Q31: 29.53 | R31: 投产 | T31: 一期
A32: 甘肃公司 | B32: =VLOOKUP(C32,[1]干线管道!B:C,2,FALSE) -> 一级 | C32: =VLOOKUP(E32,[1]站场阀室!A:D,3,FALSE) -> 西气东输一线 | D32: =VLOOKUP(E32,[1]站场阀室!A:D,4,FALSE) -> 西一线干线甘肃段 | E32: 山丹压气站 | F32: 2+1 | G32: 3# | H32: 40483 | I32: 燃驱 | J32: 进口 | K32: Rolls-Royce | L32: RF3BB36 | M32: RB211-24G/RR | N32: 3120-4800 | O32: 5040 | P32: >4 | Q32: 29.53 | R32: 投产 | T32: 一期
A33: 甘肃公司 | B33: =VLOOKUP(C33,[1]干线管道!B:C,2,FALSE) -> 一级 | C33: =VLOOKUP(E33,[1]站场阀室!A:D,3,FALSE) -> 西气东输一线 | D33: =VLOOKUP(E33,[1]站场阀室!A:D,4,FALSE) -> 西一线干线甘肃段 | E33: 金昌压气站 | F33: 1+1 | G33: 1# | H33: 39243 | I33: 燃驱 | J33: 进口 | K33: General Electric | L33: PCL804 | M33: PGT25+SAC/GE | N33: 3965-6100 | O33: 6405 | P33: >5.8 | Q33: 31.364 | R33: 投产 | S33: 无 | T33: 一期
A34: 甘肃公司 | B34: =VLOOKUP(C34,[1]干线管道!B:C,2,FALSE) -> 一级 | C34: =VLOOKUP(E34,[1]站场阀室!A:D,3,FALSE) -> 西气东输一线 | D34: =VLOOKUP(E34,[1]站场阀室!A:D,4,FALSE) -> 西一线干线甘肃段 | E34: 金昌压气站 | F34: 1+1 | G34: 2# | H34: 39337 | I34: 燃驱 | J34: 进口 | K34: General Electric | L34: PCL804 | M34: PGT25+SAC/GE | N34: 3965-6100 | O34: 6405 | P34: >5.8 | Q34: 31.364 | R34: 投产 | T34: 一期
A35: 甘肃公司 | B35: =VLOOKUP(C35,[1]干线管道!B:C,2,FALSE) -> 一级 | C35: =VLOOKUP(E35,[1]站场阀室!A:D,3,FALSE) -> 西气东输一线 | D35: =VLOOKUP(E35,[1]站场阀室!A:D,4,FALSE) -> 西一线干线甘肃段 | E35: 古浪压气站 | F35: 1+1 | G35: １＃ | H35: 39073 | I35: 燃驱 | J35: 进口 | K35: General Electric | L35: PCL804 | M35: PGT25+SAC/GE | N35: 3965-6100 | O35: 6405 | P35: >5.8 | Q35: 31.364 | R35: 投产 | S35: 无 | T35: 一期
A36: 甘肃公司 | B36: =VLOOKUP(C36,[1]干线管道!B:C,2,FALSE) -> 一级 | C36: =VLOOKUP(E36,[1]站场阀室!A:D,3,FALSE) -> 西气东输一线 | D36: =VLOOKUP(E36,[1]站场阀室!A:D,4,FALSE) -> 西一线干线甘肃段 | E36: 古浪压气站 | F36: 1+1 | G36: ２＃ | H36: 39044 | I36: 燃驱 | J36: 进口 | K36: General Electric | L36: PCL804 | M36: PGT25+SAC/GE | N36: 3965-6100 | O36: 6405 | P36: >5.8 | Q36: 31.364 | R36: 投产 | T36: 一期
A37: 西北公司 | B37: =VLOOKUP(C37,[1]干线管道!B:C,2,FALSE) -> 一级 | C37: =VLOOKUP(E37,[1]站场阀室!A:D,3,FALSE) -> 西气东输一线 | D37: =VLOOKUP(E37,[1]站场阀室!A:D,4,FALSE) -> 西一线干线东段 | E37: 中卫压气站 | F37: 1+1 | G37: 1# | H37: 38995 | I37: 燃驱 | J37: 进口 | K37: Rolls-Royce | L37: RF2BB36 | M37: RB211-24G/RR | N37: 3120-4800 | O37: 5040 | P37: >4 | Q37: 29.53 | R37: 投产 | S37: 有 | T37: 一期 | U37: 有余热发电
A38: 西北公司 | B38: =VLOOKUP(C38,[1]干线管道!B:C,2,FALSE) -> 一级 | C38: =VLOOKUP(E38,[1]站场阀室!A:D,3,FALSE) -> 西气东输一线 | D38: =VLOOKUP(E38,[1]站场阀室!A:D,4,FALSE) -> 西一线干线东段 | E38: 中卫压气站 | F38: 1+1 | G38: 2# | H38: 38628 | I38: 燃驱 | J38: 进口 | K38: Rolls-Royce | L38: RF2BB36 | M38: RB211-24G/RR | N38: 3120-4800 | O38: 5040 | P38: >4 | Q38: 29.53 | R38: 投产 | T38: 一期
A39: 西北公司 | B39: =VLOOKUP(C39,[1]干线管道!B:C,2,FALSE) -> 一级 | C39: =VLOOKUP(E39,[1]站场阀室!A:D,3,FALSE) -> 西气东输一线 | D39: =VLOOKUP(E39,[1]站场阀室!A:D,4,FALSE) -> 西一线干线东段 | E39: 西一盐池压气站 | F39: 2+1 | G39: 1# | H39: 39140 | I39: 燃驱 | J39: 进口 | K39: General Electric | L39: PCL804/NP | M39: PGT25+SAC/GE | N39: 3965-6100 | O39: 6405 | P39: >5.8 | Q39: 31.364 | R39: 投产 | S39: 无 | T39: 一期
A40: 西北公司 | B40: =VLOOKUP(C40,[1]干线管道!B:C,2,FALSE) -> 一级 | C40: =VLOOKUP(E40,[1]站场阀室!A:D,3,FALSE) -> 西气东输一线 | D40: =VLOOKUP(E40,[1]站场阀室!A:D,4,FALSE) -> 西一线干线东段 | E40: 西一盐池压气站 | F40: 2+1 | G40: 2# | H40: 39141 | I40: 燃驱 | J40: 进口 | K40: General Electric | L40: PCL804/NP | M40: PGT25+SAC/GE | N40: 3965-6100 | O40: 6405 | P40: >5.8 | Q40: 31.364 | R40: 投产 | T40: 一期
A41: 西北公司 | B41: =VLOOKUP(C41,[1]干线管道!B:C,2,FALSE) -> 一级 | C41: =VLOOKUP(E41,[1]站场阀室!A:D,3,FALSE) -> 西气东输一线 | D41: =VLOOKUP(E41,[1]站场阀室!A:D,4,FALSE) -> 西一线干线东段 | E41: 西一盐池压气站 | F41: 2+1 | G41: 3# | H41: 40468 | I41: 燃驱 | J41: 进口 | K41: General Electric | L41: PCL804/NP | M41: PGT25+SAC/GE | N41: 3965-6100 | O41: 6405 | P41: >5.8 | Q41: 31.364 | R41: 投产 | T41: 一期
A42: 西北公司 | B42: =VLOOKUP(C42,[1]干线管道!B:C,2,FALSE) -> 一级 | C42: =VLOOKUP(E42,[1]站场阀室!A:D,3,FALSE) -> 西气东输一线 | D42: =VLOOKUP(E42,[1]站场阀室!A:D,4,FALSE) -> 西一线干线东段 | E42: 西一靖边压气站 | F42: 1+1 | G42: 1# | H42: 38261 | I42: 燃驱 | J42: 进口 | K42: Rolls-Royce | L42: RF2BB36 | M42: RB211-24G/RR | N42: 3120-4800 | O42: 5040 | P42: >4 | Q42: 29.53 | R42: 投产 | S42: 无 | T42: 一期
A43: 西北公司 | B43: =VLOOKUP(C43,[1]干线管道!B:C,2,FALSE) -> 一级 | C43: =VLOOKUP(E43,[1]站场阀室!A:D,3,FALSE) -> 西气东输一线 | D43: =VLOOKUP(E43,[1]站场阀室!A:D,4,FALSE) -> 西一线干线东段 | E43: 西一靖边压气站 | F43: 1+1 | G43: 2# | H43: 38262 | I43: 燃驱 | J43: 进口 | K43: Rolls-Royce | L43: RF2BB36 | M43: RB211-24G/RR | N43: 3120-4800 | O43: 5040 | P43: >4 | Q43: 29.53 | R43: 投产 | T43: 一期
A44: 西北公司 | B44: =VLOOKUP(C44,[1]干线管道!B:C,2,FALSE) -> 一级 | C44: =VLOOKUP(E44,[1]站场阀室!A:D,3,FALSE) -> 西气东输一线 | D44: =VLOOKUP(E44,[1]站场阀室!A:D,4,FALSE) -> 西一线干线东段 | E44: 延川压气站 | F44: 1+1 | G44: 1# | H44: 39752 | I44: 燃驱 | J44: 进口 | K44: General Electric | L44: PCL804/NP | M44: PGT25+SAC/GE | N44: 3965-6100 | O44: 6405 | P44: >5.8 | Q44: 31.364 | R44: 投产 | S44: 有 | T44: 一期 | U44: 有余热发电
A45: 西北公司 | B45: =VLOOKUP(C45,[1]干线管道!B:C,2,FALSE) -> 一级 | C45: =VLOOKUP(E45,[1]站场阀室!A:D,3,FALSE) -> 西气东输一线 | D45: =VLOOKUP(E45,[1]站场阀室!A:D,4,FALSE) -> 西一线干线东段 | E45: 延川压气站 | F45: 1+1 | G45: 2# | H45: 39801 | I45: 燃驱 | J45: 进口 | K45: General Electric | L45: PCL804/NP | M45: PGT25+SAC/GE | N45: 3965-6100 | O45: 6405 | P45: >5.8 | Q45: 31.364 | R45: 投产 | T45: 一期
A46: 西北公司 | B46: =VLOOKUP(C46,[1]干线管道!B:C,2,FALSE) -> 一级 | C46: =VLOOKUP(E46,[1]站场阀室!A:D,3,FALSE) -> 西气东输一线 | D46: =VLOOKUP(E46,[1]站场阀室!A:D,4,FALSE) -> 西一线干线东段 | E46: 蒲县压气站 | F46: 1+1 | G46: 1# | H46: 39129 | I46: 电驱 | J46: 进口 | K46: Rolls-Royce | L46: RF2BB36 | M46: 1DX 1749-8ES01-Z/西门子 西门子变频器 | N46: 3120-4800 | O46: 5040 | P46: >4 | Q46: 22 | R46: 投产 | S46: 无 | T46: 一期
A47: 西北公司 | B47: =VLOOKUP(C47,[1]干线管道!B:C,2,FALSE) -> 一级 | C47: =VLOOKUP(E47,[1]站场阀室!A:D,3,FALSE) -> 西气东输一线 | D47: =VLOOKUP(E47,[1]站场阀室!A:D,4,FALSE) -> 西一线干线东段 | E47: 蒲县压气站 | F47: 1+1 | G47: 2# | H47: 39256 | I47: 电驱 | J47: 进口 | K47: Rolls-Royce | L47: RF2BB36 | M47: 1DX 1749-8ES01-Z/西门子 西门子变频器 | N47: 3120-4800 | O47: 5040 | P47: >4 | Q47: 22 | R47: 投产 | T47: 一期
A48: 西北公司 | B48: =VLOOKUP(C48,[1]干线管道!B:C,2,FALSE) -> 一级 | C48: =VLOOKUP(E48,[1]站场阀室!A:D,3,FALSE) -> 西气东输一线 | D48: =VLOOKUP(E48,[1]站场阀室!A:D,4,FALSE) -> 西一线干线东段 | E48: 沁水压气站 | F48: 1+1 | G48: 1# | H48: 40106 | I48: 燃驱 | J48: 进口 | K48: General Electric | L48: PCL803/NP | M48: PGT25+SAC/GE | N48: 3965-6100 | O48: 6405 | P48: >5.8 | Q48: 31.364 | R48: 投产 | S48: 无 | T48: 一期
A49: 西北公司 | B49: =VLOOKUP(C49,[1]干线管道!B:C,2,FALSE) -> 一级 | C49: =VLOOKUP(E49,[1]站场阀室!A:D,3,FALSE) -> 西气东输一线 | D49: =VLOOKUP(E49,[1]站场阀室!A:D,4,FALSE) -> 西一线干线东段 | E49: 沁水压气站 | F49: 1+1 | G49: 2# | H49: 40146 | I49: 燃驱 | J49: 进口 | K49: General Electric | L49: PCL803/NP | M49: PGT25+SAC/GE | N49: 3965-6100 | O49: 6405 | P49: >5.8 | Q49: 31.364 | R49: 投产 | T49: 一期
A50: 西北公司 | B50: 一级 | C50: 西气东输一线 | D50: 西一线干线东段 | E50: 沁水煤层气 | F50: - | G50: 1# | H50: 40104 | I50: 电驱 | J50: 国产 | K50: 江汉石油管理局第三机械厂 | L50: 4RDS-B-1 | M50: YD800M1-6 /湘潭电机股份公司 | N50: 993固定值 | O50: 993固定值 | P50: >5.5 | Q50: 2 | R50: 投产 | S50: - | T50: 不纳入
A51: 西北公司 | B51: 一级 | C51: 西气东输一线 | D51: 西一线干线东段 | E51: 沁水煤层气 | F51: - | G51: 2# | H51: 40075 | I51: 电驱 | J51: 国产 | K51: 江汉石油管理局第三机械厂 | L51: 4RDS-B-1 | M51: ET800 W6 /安萨尔多 | N51: 993固定值 | O51: 993固定值 | P51: >5.5 | Q51: 2 | R51: 投产 | T51: 不纳入
A52: 西北公司 | B52: 一级 | C52: 西气东输一线 | D52: 西一线干线东段 | E52: 沁水煤层气 | F52: - | G52: 3# | H52: 40071 | I52: 电驱 | J52: 国产 | K52: 江汉石油管理局第三机械厂 | L52: 4RDS-B-1 | M52: YD800M1-6 /湘潭电机股份公司 | N52: 993固定值 | O52: 993固定值 | P52: >5.5 | Q52: 2 | R52: 投产 | T52: 不纳入
A53: 西北公司 | B53: 一级 | C53: 西气东输一线 | D53: 西一线干线东段 | E53: 沁水煤层气 | F53: - | G53: 4# | H53: 41339 | I53: 电驱 | J53: 国产 | K53: 北京杰利阳能源设备制造有限公司 | L53: MH64 美国库伯 | M53: YD800M1-6 /湘潭电机股份公司 | N53: 993固定值 | O53: 993固定值 | P53: >5.5 | Q53: 2 | R53: 投产 | T53: 不纳入
A54: 西北公司 | B54: 一级 | C54: 西气东输一线 | D54: 西一线干线东段 | E54: 沁水煤层气 | F54: - | G54: 5# | H54: 40360 | I54: 电驱 | J54: 国产 | K54: 北京杰利阳能源设备制造有限公司 | L54: MH62 美国库伯 | M54: MH62-YB630/佳木斯电机 | N54: 993固定值 | O54: 993固定值 | P54: >5.5 | Q54: 0.8 | R54: 投产 | T54: 不纳入
A55: 北方管道 | B55: =VLOOKUP(C55,[1]干线管道!B:C,2,FALSE) -> 一级 | C55: =VLOOKUP(E55,[1]站场阀室!A:D,3,FALSE) -> 西气东输一线 | D55: =VLOOKUP(E55,[1]站场阀室!A:D,4,FALSE) -> 西一线干线东段 | E55: 郑州压气站 | F55: 1+1 | G55: 1# | H55: 39198 | I55: 电驱 | J55: 进口 | K55: Rolls-Royce | L55: RF2BB36 | M55: 1DX 1749-8ES01-Z/西门子 西门子变频器 | N55: 3120-4800 | O55: 5040 | P55: >4 | Q55: 22 | R55: 投产 | S55: 无 | T55: 一期
A56: 北方管道 | B56: =VLOOKUP(C56,[1]干线管道!B:C,2,FALSE) -> 一级 | C56: =VLOOKUP(E56,[1]站场阀室!A:D,3,FALSE) -> 西气东输一线 | D56: =VLOOKUP(E56,[1]站场阀室!A:D,4,FALSE) -> 西一线干线东段 | E56: 郑州压气站 | F56: 1+1 | G56: 2# | H56: 39252 | I56: 电驱 | J56: 进口 | K56: Rolls-Royce | L56: RF2BB36 | M56: 1DX 1749-8ES01-Z/西门子 西门子变频器 | N56: 3120-4800 | O56: 5040 | P56: >4 | Q56: 22 | R56: 投产 | T56: 一期
A57: 北方管道 | B57: =VLOOKUP(C57,[1]干线管道!B:C,2,FALSE) -> 一级 | C57: =VLOOKUP(E57,[1]站场阀室!A:D,3,FALSE) -> 西气东输一线 | D57: =VLOOKUP(E57,[1]站场阀室!A:D,4,FALSE) -> 西一线干线东段 | E57: 淮阳压气站 | F57: 1+1 | G57: 1# | H57: 40121 | I57: 电驱 | J57: 进口 | K57: General Electric | L57: PCL803 | M57: 1DX 1749-8ES01-Z/西门子 西门子变频器 | N57: 3120-4800 | O57: 5040 | P57: >5.8 | Q57: 22 | R57: 投产 | S57: 无 | T57: 一期
A58: 北方管道 | B58: =VLOOKUP(C58,[1]干线管道!B:C,2,FALSE) -> 一级 | C58: =VLOOKUP(E58,[1]站场阀室!A:D,3,FALSE) -> 西气东输一线 | D58: =VLOOKUP(E58,[1]站场阀室!A:D,4,FALSE) -> 西一线干线东段 | E58: 淮阳压气站 | F58: 1+1 | G58: 2# | H58: 40154 | I58: 电驱 | J58: 进口 | K58: General Electric | L58: PCL803 | M58: 1DX 1749-8ES01-Z/西门子 西门子变频器 | N58: 3120-4800 | O58: 5040 | P58: >5.8 | Q58: 22 | R58: 投产 | T58: 一期
A59: 西气东输 | B59: =VLOOKUP(C59,[1]干线管道!B:C,2,FALSE) -> 一级 | C59: =VLOOKUP(E59,[1]站场阀室!A:D,3,FALSE) -> 西气东输一线 | D59: =VLOOKUP(E59,[1]站场阀室!A:D,4,FALSE) -> 西一线干线东段 | E59: 定远压气站 | F59: 1+1 | G59: 1# | H59: 39762 | I59: 燃驱 | J59: 进口 | K59: General Electric | L59: PCL803 | M59: PGT25+SAC/GE | N59: 3965-6100 | O59: 6405 | P59: >5.8 | Q59: 31.364 | R59: 投产 | S59: 有 | T59: 一期 | U59: 有余热发电
A60: 西气东输 | B60: =VLOOKUP(C60,[1]干线管道!B:C,2,FALSE) -> 一级 | C60: =VLOOKUP(E60,[1]站场阀室!A:D,3,FALSE) -> 西气东输一线 | D60: =VLOOKUP(E60,[1]站场阀室!A:D,4,FALSE) -> 西一线干线东段 | E60: 定远压气站 | F60: 1+1 | G60: 2# | H60: 40016 | I60: 燃驱 | J60: 进口 | K60: General Electric | L60: PCL803 | M60: PGT25+SAC/GE | N60: 3965-6100 | O60: 6405 | P60: >5.8 | Q60: 31.364 | R60: 投产 | T60: 一期
A61: 北京管道 | B61: =VLOOKUP(C61,[1]干线管道!B:C,2,FALSE) -> 一级 | C61: =VLOOKUP(E61,[1]站场阀室!A:D,3,FALSE) -> 冀宁线 | D61: =VLOOKUP(E61,[1]站场阀室!A:D,4,FALSE) -> 冀宁线干线冀鲁段 | E61: 安平压气站 | F61: 1+0 | G61: 1# | H61: 2017.12.6 | I61: 燃驱 | J61: 进口 | K61: Dresser-Rand | L61: CDP-416 | M61: SOLAR | N61: 7800-14300 | O61: 14300 | P61: 3.7-5.2 | Q61: 5.43 | S61: 无 | T61: 不纳入
A62: 山东公司 | B62: =VLOOKUP(C62,[1]干线管道!B:C,2,FALSE) -> 一级 | C62: =VLOOKUP(E62,[1]站场阀室!A:D,3,FALSE) -> 冀宁线 | D62: =VLOOKUP(E62,[1]站场阀室!A:D,4,FALSE) -> 冀宁线干线冀鲁段 | E62: 泰安压气站 | F62: 2+0 | G62: 1# | H62: 2011.11 | I62: 电驱 | J62: 进口 | K62: SIMENS | L62: STC-SV（08-3-A） | M62: YZKS630-4/上电 荣信变频器 | N62: 9130-13695 | O62: 13695 | P62: 5.5-7.7 | Q62: 7.1 | R62: 投产 | S62: 无 | T62: 一期
A63: 山东公司 | B63: =VLOOKUP(C63,[1]干线管道!B:C,2,FALSE) -> 一级 | C63: =VLOOKUP(E63,[1]站场阀室!A:D,3,FALSE) -> 冀宁线 | D63: =VLOOKUP(E63,[1]站场阀室!A:D,4,FALSE) -> 冀宁线干线冀鲁段 | E63: 泰安压气站 | F63: 2+0 | G63: 2# | H63: 40982 | I63: 电驱 | J63: 进口 | K63: SIMENS | L63: STC-SV（08-3-A） | M63: YZKS630-4/上电 荣信变频器 | N63: 9130-13695 | O63: 13695 | P63: 5.5-7.7 | Q63: 7.1 | R63: 投产 | T63: 一期
A64: 西气东输 | B64: =VLOOKUP(C64,[1]干线管道!B:C,2,FALSE) -> 一级 | C64: =VLOOKUP(E64,[1]站场阀室!A:D,3,FALSE) -> 冀宁线 | D64: =VLOOKUP(E64,[1]站场阀室!A:D,4,FALSE) -> 冀宁线干线苏北段 | E64: 邳州压气站 | F64: 2+0 | G64: 1# | H64: 40978 | I64: 电驱 | J64: 进口 | K64: SIMENS | L64: STC-SV（08-3-A） | M64: YZKS630-4/上电 上广电变频器 | N64: 9130-13695 | O64: 13695 | P64: >5 | Q64: 7.1 | R64: 投产 | S64: 无 | T64: 一期
A65: 西气东输 | B65: =VLOOKUP(C65,[1]干线管道!B:C,2,FALSE) -> 一级 | C65: =VLOOKUP(E65,[1]站场阀室!A:D,3,FALSE) -> 冀宁线 | D65: =VLOOKUP(E65,[1]站场阀室!A:D,4,FALSE) -> 冀宁线干线苏北段 | E65: 邳州压气站 | F65: 2+0 | G65: 2# | H65: 40978 | I65: 电驱 | J65: 进口 | K65: SIMENS | L65: STC-SV（08-3-A） | M65: YZKS630-4/上电 上广电变频器 | N65: 9130-13695 | O65: 13695 | P65: >5 | Q65: 7.1 | R65: 投产 | T65: 一期
A66: 西部管道 | B66: =VLOOKUP(C66,[1]干线管道!B:C,2,FALSE) -> 一级 | C66: =VLOOKUP(E66,[1]站场阀室!A:D,3,FALSE) -> 西气东输二线 | D66: 西二线干线新疆段 | E66: 霍尔果斯压气站 | F66: 3+1 | G66: 1# | H66: 2010.8.1 | I66: 燃驱 | J66: 进口 | K66: General Electric | L66: PCL803/NP | M66: PGT25+SAC/GE | N66: 3965-6100 | O66: 6405 | P66: 4-10 | Q66: 31.372 | R66: 投产 | S66: 有 | T66: 一期
A67: 西部管道 | B67: =VLOOKUP(C67,[1]干线管道!B:C,2,FALSE) -> 一级 | C67: =VLOOKUP(E67,[1]站场阀室!A:D,3,FALSE) -> 西气东输二线 | D67: 西二线干线新疆段 | E67: 霍尔果斯压气站 | F67: 3+1 | G67: 2# | H67: 2010.8.1 | I67: 燃驱 | J67: 进口 | K67: General Electric | L67: PCL803/NP | M67: PGT25+SAC/GE | N67: 3965-6100 | O67: 6405 | P67: 4-10 | Q67: 31.372 | R67: 投产 | T67: 一期
A68: 西部管道 | B68: =VLOOKUP(C68,[1]干线管道!B:C,2,FALSE) -> 一级 | C68: =VLOOKUP(E68,[1]站场阀室!A:D,3,FALSE) -> 西气东输二线 | D68: 西二线干线新疆段 | E68: 霍尔果斯压气站 | F68: 3+1 | G68: 3# | H68: 2010.8.1 | I68: 燃驱 | J68: 进口 | K68: General Electric | L68: PCL803/NP | M68: PGT25+SAC/GE | N68: 3965-6100 | O68: 6405 | P68: 4-10 | Q68: 31.372 | R68: 投产 | T68: 一期
A69: 西部管道 | B69: =VLOOKUP(C69,[1]干线管道!B:C,2,FALSE) -> 一级 | C69: =VLOOKUP(E69,[1]站场阀室!A:D,3,FALSE) -> 西气东输二线 | D69: 西二线干线新疆段 | E69: 霍尔果斯压气站 | F69: 3+1 | G69: 4# | H69: 2010.8.1 | I69: 燃驱 | J69: 进口 | K69: General Electric | L69: PCL803/NP | M69: PGT25+SAC/GE | N69: 3965-6100 | O69: 6405 | P69: 4-10 | Q69: 31.372 | R69: 投产 | T69: 一期
A70: 西部管道 | B70: =VLOOKUP(C70,[1]干线管道!B:C,2,FALSE) -> 一级 | C70: =VLOOKUP(E70,[1]站场阀室!A:D,3,FALSE) -> 西气东输二线 | D70: 西二线干线新疆段 | E70: 精河压气站 | F70: 2+1 | G70: 1# | H70: 2012.2.26 | I70: 燃驱 | J70: 进口 | K70: General Electric | L70: PCL802/NP | M70: PGT25+SAC/GE | N70: 3965-6100 | O70: 6405 | P70: 7-9.3 | Q70: 31.372 | R70: 投产 | S70: 无 | T70: 一期
A71: 西部管道 | B71: =VLOOKUP(C71,[1]干线管道!B:C,2,FALSE) -> 一级 | C71: =VLOOKUP(E71,[1]站场阀室!A:D,3,FALSE) -> 西气东输二线 | D71: 西二线干线新疆段 | E71: 精河压气站 | F71: 2+1 | G71: 2# | H71: 2012.2.26 | I71: 燃驱 | J71: 进口 | K71: General Electric | L71: PCL802/NP | M71: PGT25+SAC/GE | N71: 3965-6100 | O71: 6405 | P71: 7-9.3 | Q71: 31.372 | R71: 投产 | T71: 一期
A72: 西部管道 | B72: =VLOOKUP(C72,[1]干线管道!B:C,2,FALSE) -> 一级 | C72: =VLOOKUP(E72,[1]站场阀室!A:D,3,FALSE) -> 西气东输二线 | D72: 西二线干线新疆段 | E72: 精河压气站 | F72: 2+1 | G72: 3# | H72: 2012.2.26 | I72: 燃驱 | J72: 进口 | K72: General Electric | L72: PCL802/NP | M72: PGT25+SAC/GE | N72: 3965-6100 | O72: 6405 | P72: 7-9.3 | Q72: 31.372 | R72: 投产 | T72: 一期
A73: 西部管道 | B73: =VLOOKUP(C73,[1]干线管道!B:C,2,FALSE) -> 一级 | C73: =VLOOKUP(E73,[1]站场阀室!A:D,3,FALSE) -> 西气东输二线 | D73: 西二线干线新疆段 | E73: 乌苏压气站 | F73: 2+1 | G73: 1# | H73: 2012.7.15 | I73: 燃驱 | J73: 进口 | K73: Rolls-Royce | L73: RF2BB36/RR | M73: RB211-24G/RR | N73: 3500-5292 | O73: 5040 | P73: >3.8 | Q73: 29.53 | R73: 投产 | S73: 无 | T73: 一期
A74: 西部管道 | B74: =VLOOKUP(C74,[1]干线管道!B:C,2,FALSE) -> 一级 | C74: =VLOOKUP(E74,[1]站场阀室!A:D,3,FALSE) -> 西气东输二线 | D74: 西二线干线新疆段 | E74: 乌苏压气站 | F74: 2+1 | G74: 2# | H74: 2011.11.31 | I74: 燃驱 | J74: 进口 | K74: Rolls-Royce | L74: RF2BB36/RR | M74: RB211-24G/RR | N74: 3500-5292 | O74: 5040 | P74: >3.8 | Q74: 29.53 | R74: 投产 | T74: 一期
A75: 西部管道 | B75: =VLOOKUP(C75,[1]干线管道!B:C,2,FALSE) -> 一级 | C75: =VLOOKUP(E75,[1]站场阀室!A:D,3,FALSE) -> 西气东输二线 | D75: 西二线干线新疆段 | E75: 乌苏压气站 | F75: 2+1 | G75: 3# | H75: 2011.11.30 | I75: 燃驱 | J75: 进口 | K75: Rolls-Royce | L75: RF2BB36/RR | M75: RB211-24G/RR | N75: 3500-5292 | O75: 5040 | P75: >3.8 | Q75: 29.53 | R75: 投产 | T75: 一期
A76: 西部管道 | B76: =VLOOKUP(C76,[1]干线管道!B:C,2,FALSE) -> 一级 | C76: =VLOOKUP(E76,[1]站场阀室!A:D,3,FALSE) -> 西气东输二线 | D76: 西二线干线新疆段 | E76: 玛纳斯压气站 | F76: 2+1 | G76: 1# | H76: 2011.3.1 | I76: 燃驱 | J76: 进口 | K76: General Electric | L76: PCL802/NP | M76: PGT25+SAC/GE | N76: 3965-6100 | O76: 6405 | P76: 7-9.3 | Q76: 31.372 | R76: 投产 | S76: 有 | T76: 一期 | U76: 未投用
A77: 西部管道 | B77: =VLOOKUP(C77,[1]干线管道!B:C,2,FALSE) -> 一级 | C77: =VLOOKUP(E77,[1]站场阀室!A:D,3,FALSE) -> 西气东输二线 | D77: 西二线干线新疆段 | E77: 玛纳斯压气站 | F77: 2+1 | G77: 2# | H77: 2011.3.1 | I77: 燃驱 | J77: 进口 | K77: General Electric | L77: PCL802/NP | M77: PGT25+SAC/GE | N77: 3965-6100 | O77: 6405 | P77: 7-9.3 | Q77: 31.372 | R77: 投产 | T77: 一期
A78: 西部管道 | B78: =VLOOKUP(C78,[1]干线管道!B:C,2,FALSE) -> 一级 | C78: =VLOOKUP(E78,[1]站场阀室!A:D,3,FALSE) -> 西气东输二线 | D78: 西二线干线新疆段 | E78: 玛纳斯压气站 | F78: 2+1 | G78: 3# | H78: 2011.3.1 | I78: 燃驱 | J78: 进口 | K78: General Electric | L78: PCL802/NP | M78: PGT25+SAC/GE | N78: 3965-6100 | O78: 6405 | P78: 7-9.3 | Q78: 31.372 | R78: 投产 | T78: 一期
A79: 西部管道 | B79: =VLOOKUP(C79,[1]干线管道!B:C,2,FALSE) -> 一级 | C79: =VLOOKUP(E79,[1]站场阀室!A:D,3,FALSE) -> 西气东输二线 | D79: 西二线干线新疆段 | E79: 乌鲁木齐压气站 | F79: 3+1 | G79: 1# | H79: 41197 | I79: 电驱 | J79: 进口 | K79: General Electric | L79: PCL803/NP | M79: SHBLR/TMEIC TMEIC变频器 | N79: 3960-5200 | O79: 5460 | P79: 7.9-9.3 | Q79: 18 | R79: 投产 | S79: 无 | T79: 一期
A80: 西部管道 | B80: =VLOOKUP(C80,[1]干线管道!B:C,2,FALSE) -> 一级 | C80: =VLOOKUP(E80,[1]站场阀室!A:D,3,FALSE) -> 西气东输二线 | D80: 西二线干线新疆段 | E80: 乌鲁木齐压气站 | F80: 3+1 | G80: 2# | H80: 41198 | I80: 电驱 | J80: 进口 | K80: General Electric | L80: PCL803/NP | M80: SHBLR/TMEIC TMEIC变频器 | N80: 3960-5200 | O80: 5460 | P80: 7.9-9.3 | Q80: 18 | R80: 投产 | T80: 一期
A81: 西部管道 | B81: =VLOOKUP(C81,[1]干线管道!B:C,2,FALSE) -> 一级 | C81: =VLOOKUP(E81,[1]站场阀室!A:D,3,FALSE) -> 西气东输二线 | D81: 西二线干线新疆段 | E81: 乌鲁木齐压气站 | F81: 3+1 | G81: 3# | H81: 41199 | I81: 电驱 | J81: 进口 | K81: General Electric | L81: PCL803/NP | M81: SHBLR/TMEIC TMEIC变频器 | N81: 3960-5200 | O81: 5460 | P81: 7.9-9.3 | Q81: 18 | R81: 投产 | T81: 一期
A82: 西部管道 | B82: =VLOOKUP(C82,[1]干线管道!B:C,2,FALSE) -> 一级 | C82: =VLOOKUP(E82,[1]站场阀室!A:D,3,FALSE) -> 西气东输二线 | D82: 西二线干线新疆段 | E82: 乌鲁木齐压气站 | F82: 3+1 | G82: 4# | H82: 41200 | I82: 电驱 | J82: 国产 | K82: 沈鼓 | L82: PCL803（又称H1156）/SBW | M82: SHBLR/TMEIC TMEIC变频器 | N82: 3960-5200 | O82: 5460 | P82: 0-8.89 | Q82: 18 | R82: 投产 | T82: 一期
A83: 西部管道 | B83: =VLOOKUP(C83,[1]干线管道!B:C,2,FALSE) -> 一级 | C83: =VLOOKUP(E83,[1]站场阀室!A:D,3,FALSE) -> 西气东输二线 | D83: 西二线干线新疆段 | E83: 连木沁压气站 | F83: 2+1 | G83: 1# | H83: 2011.8.13 | I83: 燃驱 | J83: 进口 | K83: General Electric | L83: PCL802/NP | M83: PGT25+SAC/GE | N83: 3965-6100 | O83: 6405 | P83: 7-9.3 | Q83: 31.372 | R83: 投产 | S83: 有 | T83: 一期
A84: 西部管道 | B84: =VLOOKUP(C84,[1]干线管道!B:C,2,FALSE) -> 一级 | C84: =VLOOKUP(E84,[1]站场阀室!A:D,3,FALSE) -> 西气东输二线 | D84: 西二线干线新疆段 | E84: 连木沁压气站 | F84: 2+1 | G84: 2# | H84: 2011.8.18 | I84: 燃驱 | J84: 进口 | K84: General Electric | L84: PCL802/NP | M84: PGT25+SAC/GE | N84: 3965-6100 | O84: 6405 | P84: 7-9.3 | Q84: 31.372 | R84: 投产 | T84: 一期
A85: 西部管道 | B85: =VLOOKUP(C85,[1]干线管道!B:C,2,FALSE) -> 一级 | C85: =VLOOKUP(E85,[1]站场阀室!A:D,3,FALSE) -> 西气东输二线 | D85: 西二线干线新疆段 | E85: 连木沁压气站 | F85: 2+1 | G85: 3# | H85: 2011.8.22 | I85: 燃驱 | J85: 进口 | K85: General Electric | L85: PCL802/NP | M85: PGT25+SAC/GE | N85: 3965-6100 | O85: 6405 | P85: ＞3.8 | Q85: 31.372 | R85: 投产 | T85: 一期
A86: 西部管道 | B86: =VLOOKUP(C86,[1]干线管道!B:C,2,FALSE) -> 一级 | C86: =VLOOKUP(E86,[1]站场阀室!A:D,3,FALSE) -> 西气东输二线 | D86: 西二线干线新疆段 | E86: 了墩压气站 | F86: 2+1 | G86: 1# | H86: 2011.12.24 | I86: 燃驱 | J86: 进口 | K86: General Electric | L86: PCL802/NP | M86: PGT25+SAC/GE | N86: 3965-6100 | O86: 6405 | P86: ＞3.8 | Q86: 31.372 | R86: 投产 | S86: 无 | T86: 一期 | U86: 余热发电未建完
A87: 西部管道 | B87: =VLOOKUP(C87,[1]干线管道!B:C,2,FALSE) -> 一级 | C87: =VLOOKUP(E87,[1]站场阀室!A:D,3,FALSE) -> 西气东输二线 | D87: 西二线干线新疆段 | E87: 了墩压气站 | F87: 2+1 | G87: 2# | H87: 2011.12.24 | I87: 燃驱 | J87: 进口 | K87: General Electric | L87: PCL802/NP | M87: PGT25+SAC/GE | N87: 3965-6100 | O87: 6405 | P87: ＞3.8 | Q87: 31.372 | R87: 投产 | T87: 一期
A88: 西部管道 | B88: =VLOOKUP(C88,[1]干线管道!B:C,2,FALSE) -> 一级 | C88: =VLOOKUP(E88,[1]站场阀室!A:D,3,FALSE) -> 西气东输二线 | D88: 西二线干线新疆段 | E88: 了墩压气站 | F88: 2+1 | G88: 3# | H88: 2011.12.24 | I88: 燃驱 | J88: 进口 | K88: General Electric | L88: PCL802/NP | M88: PGT25+SAC/GE | N88: 3965-6100 | O88: 6405 | P88: 7-9.3 | Q88: 31.372 | R88: 投产 | T88: 一期
A89: 西部管道 | B89: =VLOOKUP(C89,[1]干线管道!B:C,2,FALSE) -> 一级 | C89: =VLOOKUP(E89,[1]站场阀室!A:D,3,FALSE) -> 西气东输二线 | D89: 西二线干线新疆段 | E89: 烟墩压气站 | F89: 2+1 | G89: 1# | H89: 2011.8.23 | I89: 燃驱 | J89: 进口 | K89: Rolls-Royce | L89: RF2BB36/RR | M89: RB211-24G/RR | N89: 3120-5040 | O89: 5040 | P89: >4.0 | Q89: 29.53 | R89: 投产 | S89: 无 | T89: 一期 | U89: 余热发电未建完
A90: 西部管道 | B90: =VLOOKUP(C90,[1]干线管道!B:C,2,FALSE) -> 一级 | C90: =VLOOKUP(E90,[1]站场阀室!A:D,3,FALSE) -> 西气东输二线 | D90: 西二线干线新疆段 | E90: 烟墩压气站 | F90: 2+1 | G90: 2# | H90: 2011.8.23 | I90: 燃驱 | J90: 进口 | K90: Rolls-Royce | L90: RF2BB36/RR | M90: RB211-24G/RR | N90: 3250-4800 | O90: 5040 | P90: >4.0 | Q90: 29.53 | R90: 投产 | T90: 一期
A91: 西部管道 | B91: =VLOOKUP(C91,[1]干线管道!B:C,2,FALSE) -> 一级 | C91: =VLOOKUP(E91,[1]站场阀室!A:D,3,FALSE) -> 西气东输二线 | D91: 西二线干线新疆段 | E91: 烟墩压气站 | F91: 2+1 | G91: 3# | H91: 2011.8.23 | I91: 燃驱 | J91: 进口 | K91: Rolls-Royce | L91: RF2BB36/RR | M91: RB211-24G/RR | N91: 3250-4800 | O91: 5040 | P91: >4.0 | Q91: 29.53 | R91: 投产 | T91: 一期
A92: 甘肃公司 | B92: =VLOOKUP(C92,[1]干线管道!B:C,2,FALSE) -> 一级 | C92: =VLOOKUP(E92,[1]站场阀室!A:D,3,FALSE) -> 西气东输一线 | D92: =VLOOKUP(E92,[1]站场阀室!A:D,4,FALSE) -> 西一线干线甘肃段 | E92: 红柳压气站 | F92: 2+1 | G92: 1# | H92: 40398 | I92: 燃驱 | J92: 进口 | K92: General Electric | L92: PCL802 | M92: PGT25+SAC/GE | N92: 3965-6100 | O92: 6405 | P92: 7-9.3 | Q92: 31.372 | R92: 投产 | S92: 无 | T92: 一期
A93: 甘肃公司 | B93: =VLOOKUP(C93,[1]干线管道!B:C,2,FALSE) -> 一级 | C93: =VLOOKUP(E93,[1]站场阀室!A:D,3,FALSE) -> 西气东输一线 | D93: =VLOOKUP(E93,[1]站场阀室!A:D,4,FALSE) -> 西一线干线甘肃段 | E93: 红柳压气站 | F93: 2+1 | G93: 2# | H93: 40401 | I93: 燃驱 | J93: 进口 | K93: General Electric | L93: PCL802 | M93: PGT25+SAC/GE | N93: 3965-6100 | O93: 6405 | P93: 7-9.3 | Q93: 31.372 | R93: 投产 | T93: 一期
A94: 甘肃公司 | B94: =VLOOKUP(C94,[1]干线管道!B:C,2,FALSE) -> 一级 | C94: =VLOOKUP(E94,[1]站场阀室!A:D,3,FALSE) -> 西气东输一线 | D94: =VLOOKUP(E94,[1]站场阀室!A:D,4,FALSE) -> 西一线干线甘肃段 | E94: 红柳压气站 | F94: 2+1 | G94: 3# | H94: 40405 | I94: 燃驱 | J94: 进口 | K94: General Electric | L94: PCL802 | M94: PGT25+SAC/GE | N94: 3965-6100 | O94: 6405 | P94: 7-9.3 | Q94: 31.372 | R94: 投产 | T94: 一期
A95: 甘肃公司 | B95: =VLOOKUP(C95,[1]干线管道!B:C,2,FALSE) -> 一级 | C95: =VLOOKUP(E95,[1]站场阀室!A:D,3,FALSE) -> 西气东输二线 | D95: =VLOOKUP(E95,[1]站场阀室!A:D,4,FALSE) -> 西二线干线甘肃段 | E95: 瓜州压气站 | F95: 3+1 | G95: 1# | H95: 41197 | I95: 电驱 | J95: 进口 | K95: General Electric | L95: PCL803 | M95: SHBLR/TMEIC TMEIC变频器 | N95: 3960-5200 | O95: 5460 | P95: 7.9-9.3 | Q95: 18 | R95: 投产 | S95: 无 | T95: 一期
A96: 甘肃公司 | B96: =VLOOKUP(C96,[1]干线管道!B:C,2,FALSE) -> 一级 | C96: =VLOOKUP(E96,[1]站场阀室!A:D,3,FALSE) -> 西气东输二线 | D96: =VLOOKUP(E96,[1]站场阀室!A:D,4,FALSE) -> 西二线干线甘肃段 | E96: 瓜州压气站 | F96: 3+1 | G96: 2# | H96: 41198 | I96: 电驱 | J96: 进口 | K96: General Electric | L96: PCL803 | M96: SHBLR/TMEIC TMEIC变频器 | N96: 3960-5200 | O96: 5460 | P96: 7.9-9.3 | Q96: 18 | R96: 投产 | T96: 一期
A97: 甘肃公司 | B97: =VLOOKUP(C97,[1]干线管道!B:C,2,FALSE) -> 一级 | C97: =VLOOKUP(E97,[1]站场阀室!A:D,3,FALSE) -> 西气东输二线 | D97: =VLOOKUP(E97,[1]站场阀室!A:D,4,FALSE) -> 西二线干线甘肃段 | E97: 瓜州压气站 | F97: 3+1 | G97: 3# | H97: 41199 | I97: 电驱 | J97: 进口 | K97: General Electric | L97: PCL803 | M97: SHBLR/TMEIC TMEIC变频器 | N97: 3960-5200 | O97: 5460 | P97: 7.9-9.3 | Q97: 18 | R97: 投产 | T97: 一期
A98: 甘肃公司 | B98: =VLOOKUP(C98,[1]干线管道!B:C,2,FALSE) -> 一级 | C98: =VLOOKUP(E98,[1]站场阀室!A:D,3,FALSE) -> 西气东输二线 | D98: =VLOOKUP(E98,[1]站场阀室!A:D,4,FALSE) -> 西二线干线甘肃段 | E98: 瓜州压气站 | F98: 3+1 | G98: 4# | H98: 41200 | I98: 电驱 | J98: 国产 | K98: 沈鼓 | L98: PCL803（又称H1156） | M98: SHBLR/TMEIC TMEIC变频器 | N98: 3960-5200 | O98: 5460 | P98: ＜8.89 | Q98: 18 | R98: 投产 | T98: 一期
A99: 甘肃公司 | B99: =VLOOKUP(C99,[1]干线管道!B:C,2,FALSE) -> 一级 | C99: =VLOOKUP(E99,[1]站场阀室!A:D,3,FALSE) -> 西气东输二线 | D99: =VLOOKUP(E99,[1]站场阀室!A:D,4,FALSE) -> 西二线干线甘肃段 | E99: 嘉峪关压气站 | F99: 2+1 | G99: 1# | H99: 2011.10.20 | I99: 燃驱 | J99: 进口 | K99: General Electric | L99: PCL802 | M99: PGT25+SAC/GE | N99: 3965-6100 | O99: 6405 | P99: 7-9.3 | Q99: 31.372 | R99: 投产 | S99: 无 | T99: 一期
A100: 甘肃公司 | B100: =VLOOKUP(C100,[1]干线管道!B:C,2,FALSE) -> 一级 | C100: =VLOOKUP(E100,[1]站场阀室!A:D,3,FALSE) -> 西气东输二线 | D100: =VLOOKUP(E100,[1]站场阀室!A:D,4,FALSE) -> 西二线干线甘肃段 | E100: 嘉峪关压气站 | F100: 2+1 | G100: 2# | H100: 2011.10.28 | I100: 燃驱 | J100: 进口 | K100: General Electric | L100: PCL802 | M100: PGT25+SAC/GE | N100: 3965-6100 | O100: 6405 | P100: 7-9.3 | Q100: 31.372 | R100: 投产 | T100: 一期
...

Sheet 储气库
A1: [原始]序号 | B1: [原始]名称 | D1: [原始]类型 | E1: [原始]投产时间 | F1: [原始]设计工作气量 亿方 | G1: [原始]当前最大采气能力 万方/日 | H1: [原始]当前最大注气能力 万方/日 | I1: [原始]所属企业
A2: 1 | B2: 大港 | C2: 大张坨 | D2: 枯竭凝析气藏 | E2: 36831 | F2: 30.3 | G2: 2400 | H2: 1500 | I2: 合资
C3: 板876 | E3: 37325
C4: 板中北 | E4: 37802
C5: 板中南 | E5: 38558
C6: 板808 | E6: 2006年9月30日
C7: 板828 | E7: 38990
A8: 2 | B8: 华北 | C8: 京58 | D8: 气顶油气藏 | E8: 40391 | F8: 7.5 | G8: 420 | H8: 420 | I8: 合资
C9: 京51 | D9: 枯竭凝析气藏
C10: 永22 | D10: 含硫化氢凝析气藏
A11: 3 | B11: 刘庄 | D11: 枯竭油气藏 | E11: 40848 | F11: 2.4 | G11: 100 | H11: 150 | I11: 国家管网
A12: 4 | B12: 国网金坛 | C12: 金坛东 | D12: 盐穴 | E12: 39264 | F12: 17.1 | G12: 1500 | H12: 820 | I12: 国家管网
C13: 金坛西 | E13: 41539
A14: 5 | B14: 文23 | D14: 枯竭气藏 | E14: 43677 | F14: 32.7 | G14: 2600 | H14: 1800 | I14: 国家管网
A15: 6 | B15: 呼图壁 | D15: 废弃气藏 | E15: 41434 | F15: 45.1 | G15: 3300 | H15: 1550 | I15: 合资
A16: 7 | B16: 相国寺 | D16: 枯竭油气藏 | E16: 41456 | F16: 28 | G16: 2700 | H16: 1500 | I16: 合资
A17: 8 | B17: 双坨子 | E17: 44105 | F17: 11.2 | G17: 200 | I17: 中石油
A18: 9 | B18: 板南 | D18: 枯竭油气藏 | E18: 41806 | F18: 5.6 | G18: 430 | H18: 310 | I18: 中石油
A19: 10 | B19: 苏桥 | D19: 浅山气藏 | E19: 41439 | F19: 23.3 | G19: 1500 | H19: 1000 | I19: 中石油
A20: 11 | B20: 温吉桑 | D20: 枯竭油气藏 | E20: 44806 | F20: 5.5 | G20: 40 | H20: 330 | I20: 中石油
A21: 12 | B21: 文96 | D21: 枯竭气藏 | F21: 2.9 | G21: 200 | H21: 180 | I21: 中石化
A22: 13 | B22: 中石化金坛 | D22: 盐穴 | E22: 42520 | F22: 7.2 | G22: 200 | H22: 300 | I22: 中石化
A23: 14 | B23: 卫11 | D23: 枯竭油藏 | E23: 44478 | F23: 5.1 | G23: 200 | H23: 350 | I23: 中石化
A24: 15 | B24: 白9 | D24: 枯竭油气藏 | E24: 44652 | F24: 1.54 | G24: 50 | H24: 80 | I24: 中石化
A25: 16 | B25: 清溪 | D25: 枯竭油气藏 | E25: 44491 | F25: 1.94 | G25: 50 | H25: 80 | I25: 中石化
A26: 17 | B26: 江汉 | D26: 盐穴 | E26: 44708 | F26: 1.4 | G26: 20 | H26: 20 | I26: 中石化
A27: 18 | B27: 港华金坛 | D27: 盐穴 | E27: 43374 | F27: 3.1 | G27: 400 | H27: 210 | I27: 港华
A28: 19 | B28: 华北 | D28: 枯竭油气藏 | E28: 40391 | F28: 7.8 | G28: 600 | H28: 540 | I28: 合资
A29: 20 | B29: 双台子（双六） | D29: 枯竭油气藏 | E29: 双六2015年3月/双台子2022年5月 | F29: 54.1 | G29: 3300 | H29: 2600 | I29: 合资
A30: 21 | B30: 白浅
